Workbook

Sheet TJ List
A1: Donations | B1: https://paypal.me/mlbplayeranalys?country.x=CA&locale.x=en_US
A2: Player | B2: TJ Surgery Date | C2: Team | D2: Level | E2: Position | F2: Throws | G2: Country | H2: High School | I2: College(s) | J2: Age | K2: Return Date (same level) | L2: Recovery Time (months) | M2: mlbamid | N2: fgid | O2: Surgeon(s) | P2: Post-TJ MLB G | Q2: Post-TJ MLB IP/PA | R2: Active | S2: Year | T2: Month | U2: Day | V2: Started Throwing | W2: Mound | X2: Bullpen | Y2: Live Hitters | Z2: Game | AA2: Setback | AB2: Setback Type | AC2: Setback | AD2: Setback Type | AE2: G | AF2: GS | AG2: IP | AH2: K-BB% | AI2: ERA- | AJ2: FIP- | AK2: G | AL2: GS | AM2: IP | AN2: K-BB% | AO2: ERA- | AP2: FIP-
A3: Ronny Henriquez | B3: 45992 | C3: MIA | D3: MLB | E3: P | F3: R | G3: Dominican | J3: 25 | M3: 678692 | N3: 24094 | O3: Dr. Keith Meister | P3: 0 | Q3: 0 | R3: 1 | S3: =YEAR(B3) -> 2025 | T3: =MONTH(B3) -> 12 | U3: =DAY(B3) -> 1
A4: Nic Enright | B4: 45959 | C4: CLE | D4: MLB | E4: P | F4: R | G4: United States | H4: Virginia | I4: Virginia Tech | J4: 28 | M4: 663671 | N4: 25553 | P4: 0 | Q4: 0 | R4: 1 | S4: =YEAR(B4) -> 2025 | T4: =MONTH(B4) -> 10 | U4: =DAY(B4) -> 29
A5: Reed Garrett | B5: 45938 | C5: NYM | D5: MLB | E5: P | F5: R | G5: United States | H5: Virginia | I5: Virginia Military | J5: 32 | M5: 657585 | N5: 16866 | P5: 0 | Q5: 0 | R5: 1 | S5: =YEAR(B5) -> 2025 | T5: =MONTH(B5) -> 10 | U5: =DAY(B5) -> 8
A6: Luis Garcia | B6: 45931 | C6: HOU | D6: MLB | E6: P | F6: R | G6: Venezuela | J6: 28 | M6: 677651 | N6: 23735 | P6: 0 | Q6: 0 | R6: 1 | S6: =YEAR(B6) -> 2025 | T6: =MONTH(B6) -> 10 | U6: =DAY(B6) -> 1
A7: Shelby Miller | B7: 45931 | C7: MIL | D7: MLB | E7: P | F7: R | G7: United States | H7: Texas | J7: 34 | M7: 571946 | N7: 10197 | O7: Dr. Keith Meister | P7: 0 | Q7: 0 | R7: 1 | S7: =YEAR(B7) -> 2025 | T7: =MONTH(B7) -> 10 | U7: =DAY(B7) -> 1
A8: Declan Cronin | B8: 45929 | C8: MIA | D8: AAA | E8: P | F8: R | G8: United States | H8: New York | I8: Holy Cross | J8: 27 | M8: 686539 | N8: 25645 | P8: 0 | Q8: 0 | R8: 1 | S8: =YEAR(B8) -> 2025 | T8: =MONTH(B8) -> 9 | U8: =DAY(B8) -> 29
A9: Randy Rodriguez | B9: 45924 | C9: SF | D9: MLB | E9: P | F9: R | G9: Dominican | J9: 25 | M9: 678495 | N9: 23974 | P9: 0 | Q9: 0 | R9: 1 | S9: =YEAR(B9) -> 2025 | T9: =MONTH(B9) -> 9 | U9: =DAY(B9) -> 24
A10: Brandon Walter | B10: 45922 | C10: HOU | D10: MLB | E10: P | F10: L | G10: United States | H10: Delaware | I10: Delaware | J10: 28 | M10: 687888 | N10: 26056 | P10: 0 | Q10: 0 | R10: 1 | S10: =YEAR(B10) -> 2025 | T10: =MONTH(B10) -> 9 | U10: =DAY(B10) -> 22
A11: Tylor Megill | B11: 45922 | C11: NYM | D11: AAA | E11: P | F11: R | G11: United States | H11: California | I11: Loyola Marymount, Arizona | J11: 29 | M11: 656731 | N11: 21318 | O11: Dr. Neal ElAttrache | P11: 0 | Q11: 0 | R11: 1 | S11: =YEAR(B11) -> 2025 | T11: =MONTH(B11) -> 9 | U11: =DAY(B11) -> 22
A12: Frankie Montas | B12: 45909 | C12: NYM | D12: MLB | E12: P | F12: R | G12: Dominican | J12: 32 | M12: 593423 | N12: 14309 | P12: 0 | Q12: 0 | R12: 1 | S12: =YEAR(B12) -> 2025 | T12: =MONTH(B12) -> 9 | U12: =DAY(B12) -> 9
A13: Tanner Houck | B13: 45875 | C13: BOS | D13: AAA | E13: P | F13: R | G13: United States | H13: Illinois | I13: Missouri | J13: 29 | M13: 656557 | N13: 19879 | O13: Dr. Keith Meister | P13: 0 | Q13: 0 | R13: 1 | S13: =YEAR(B13) -> 2025 | T13: =MONTH(B13) -> 8 | U13: =DAY(B13) -> 6
A14: Tyler Stuart | B14: 45870 | C14: WAS | D14: AA | E14: P | F14: R | G14: United States | H14: Illinois | I14: Southern Mississippi | J14: 25 | M14: 701603 | N14: sa3020264 | P14: 0 | Q14: 0 | R14: 1 | S14: =YEAR(B14) -> 2025 | T14: =MONTH(B14) -> 8 | U14: =DAY(B14) -> 1
A15: Travis Sykora | B15: 45870 | C15: WAS | D15: AA | E15: P | F15: R | G15: United States | H15: Texas | J15: 21 | M15: 805809 | N15: sa3023557 | P15: 0 | Q15: 0 | R15: 1 | S15: =YEAR(B15) -> 2025 | T15: =MONTH(B15) -> 8 | U15: =DAY(B15) -> 1
A16: Tekoah Roby | B16: 45863 | C16: STL | D16: AAA | E16: P | F16: R | G16: United States | H16: Florida | J16: 23 | M16: 694358 | N16: sa3014519 | P16: 0 | Q16: 0 | R16: 1 | S16: =YEAR(B16) -> 2025 | T16: =MONTH(B16) -> 7 | U16: =DAY(B16) -> 25
A17: Dedniel Nunez | B17: 45852 | C17: NYM | D17: MLB | E17: P | F17: R | G17: Dominican | J17: 29 | M17: 673380 | N17: 23055 | O17: Dr. Keith Meister | P17: 0 | Q17: 0 | R17: 1 | S17: =YEAR(B17) -> 2025 | T17: =MONTH(B17) -> 7 | U17: =DAY(B17) -> 14
A18: Zach Fogell | B18: 45839 | C18: BOS | D18: A+ | E18: P | F18: R | G18: United States | H18: Rhode Island | I18: Brown, Connecticut | J18: 24 | M18: 808820 | N18: sa3023280 | P18: 0 | Q18: 0 | R18: 1 | S18: =YEAR(B18) -> 2025 | T18: =MONTH(B18) -> 7 | U18: =DAY(B18) -> 1
A19: Peyton Prescott | B19: 45839 | C19: NYM | D19: Coll | E19: P | F19: R | G19: United States | H19: Florida | I19: Florida State, Jacksonville | J19: 21 | M19: 807290 | N19: sa3040183 | P19: 0 | Q19: 0 | R19: 1 | S19: =YEAR(B19) -> 2025 | T19: =MONTH(B19) -> 7 | U19: =DAY(B19) -> 1
A20: Trennor O'Donnell | B20: 45838 | C20: BOS | D20: A | E20: P | F20: R | G20: United States | H20: Texas | I20: Ball State | J20: 24 | M20: 815064 | N20: sa3023531 | P20: 0 | Q20: 0 | R20: 1 | S20: =YEAR(B20) -> 2025 | T20: =MONTH(B20) -> 6 | U20: =DAY(B20) -> 30
A21: Justin Martinez | B21: 45833 | C21: ARI | D21: MLB | E21: P | F21: R | G21: Dominican | J21: 23 | M21: 679885 | N21: 24453 | O21: Dr. Keith Meister | P21: 0 | Q21: 0 | R21: 1 | S21: =YEAR(B21) -> 2025 | T21: =MONTH(B21) -> 6 | U21: =DAY(B21) -> 25
A22: Jair Camargo | B22: 45833 | C22: MIN | D22: AAA | E22: C | F22: R | G22: Colombia | J22: 25 | M22: 665856 | N22: 21730 | O22: Dr. Christopher Camp | P22: 0 | Q22: 0 | R22: 1 | S22: =YEAR(B22) -> 2025 | T22: =MONTH(B22) -> 6 | U22: =DAY(B22) -> 25
A23: Jake Cousins | B23: 45826 | C23: NYY | D23: A+ | E23: P | F23: R | G23: United States | H23: Illinois | I23: Pennsylvania | J23: 30 | M23: 664776 | N23: 21620 | O23: Dr. Keith Meister | P23: 0 | Q23: 0 | R23: 1 | S23: =YEAR(B23) -> 2025 | T23: =MONTH(B23) -> 6 | U23: =DAY(B23) -> 18
A24: Jackson Jobe | B24: 45824 | C24: DET | D24: MLB | E24: P | F24: R | G24: United States | H24: Oklahoma | J24: 22 | M24: 695549 | N24: 30203 | O24: Dr. Keith Meister | P24: 0 | Q24: 0 | R24: 1 | S24: =YEAR(B24) -> 2025 | T24: =MONTH(B24) -> 6 | U24: =DAY(B24) -> 16
A25: Corbin Burnes | B25: 45819 | C25: ARI | D25: MLB | E25: P | F25: R | G25: United States | H25: California | I25: Saint Mary's | J25: 30 | M25: 669203 | N25: 19361 | O25: Dr. Neal ElAttrache | P25: 0 | Q25: 0 | R25: 1 | S25: =YEAR(B25) -> 2025 | T25: =MONTH(B25) -> 6 | U25: =DAY(B25) -> 11
A26: AJ Smith-Shawver | B26: 45817 | C26: ATL | D26: MLB | E26: P | F26: R | G26: United States | H26: Texas | J26: 22 | M26: 700363 | N26: 29960 | O26: Dr. Keith Meister | P26: 0 | Q26: 0 | R26: 1 | S26: =YEAR(B26) -> 2025 | T26: =MONTH(B26) -> 6 | U26: =DAY(B26) -> 9
A27: Will Brennan | B27: 45817 | C27: CLE | D27: MLB | E27: OF | F27: L | G27: United States | H27: Kansas | I27: Kansas State | J27: 27 | M27: 686823 | N27: 25660 | O27: Dr. Keith Meister | P27: 0 | Q27: 0 | R27: 1 | S27: =YEAR(B27) -> 2025 | T27: =MONTH(B27) -> 6 | U27: =DAY(B27) -> 9 | AA27: 45904 | AB27: Sports hernia surgery
A28: Ronel Blanco | B28: 45814 | C28: HOU | D28: MLB | E28: P | F28: R | G28: Dominican | J28: 31 | M28: 669854 | N28: 19407 | P28: 0 | Q28: 0 | R28: 1 | S28: =YEAR(B28) -> 2025 | T28: =MONTH(B28) -> 6 | U28: =DAY(B28) -> 6
A29: Ben Lively | B29: 45812 | C29: CLE | D29: MLB | E29: P | F29: R | G29: United States | H29: Florida | I29: Central Florida | J29: 33 | M29: 594902 | N29: 14932 | O29: Dr. Keith Meister | P29: 0 | Q29: 0 | R29: 1 | S29: =YEAR(B29) -> 2025 | T29: =MONTH(B29) -> 6 | U29: =DAY(B29) -> 4
A30: Evan Phillips | B30: 45812 | C30: LAD | D30: MLB | E30: P | F30: R | G30: United States | H30: North Carolina | I30: North Carolina | J30: 30 | M30: 623465 | N30: 17734 | O30: Dr. Neal ElAttrache | P30: 0 | Q30: 0 | R30: 1 | S30: =YEAR(B30) -> 2025 | T30: =MONTH(B30) -> 6 | U30: =DAY(B30) -> 4
A31: Tommy Henry | B31: 45809 | C31: ARI | D31: MLB | E31: P | F31: L | G31: United States | H31: Michigan | I31: Michigan | J31: 27 | M31: 674072 | N31: 26285 | P31: 0 | Q31: 0 | R31: 1 | S31: =YEAR(B31) -> 2025 | T31: =MONTH(B31) -> 6 | U31: =DAY(B31) -> 1
A32: Yordanny Monegro | B32: 45809 | C32: BOS | D32: AA | E32: P | F32: R | G32: Dominican | J32: 22 | M32: 694057 | N32: sa3015476 | P32: 0 | Q32: 0 | R32: 1 | S32: =YEAR(B32) -> 2025 | T32: =MONTH(B32) -> 6 | U32: =DAY(B32) -> 1
A33: Emmett Olson | B33: 45809 | C33: MIA | D33: A+ | E33: P | F33: L | G33: United States | H33: Illinois | I33: Nebraska | J33: 23 | M33: 801207 | N33: sa3023223 | P33: 0 | Q33: 0 | R33: 1 | S33: =YEAR(B33) -> 2025 | T33: =MONTH(B33) -> 6 | U33: =DAY(B33) -> 1
A34: Hayden Wesneski | B34: 45800 | C34: HOU | D34: MLB | E34: P | F34: R | G34: United States | H34: Texas | I34: Sam Houston State | J34: 27 | M34: 669713 | N34: 27581 | P34: 0 | Q34: 0 | R34: 1 | S34: =YEAR(B34) -> 2025 | T34: =MONTH(B34) -> 5 | U34: =DAY(B34) -> 23
A35: Patrick Reilly | B35: 45791 | C35: BAL | D35: AA | E35: P | F35: R | G35: United States | H35: New Jersey | I35: Vanderbilt | J35: 23 | M35: 694345 | N35: sa3023038 | O35: Dr. Keith Meister | P35: 0 | Q35: 0 | R35: 1 | S35: =YEAR(B35) -> 2025 | T35: =MONTH(B35) -> 5 | U35: =DAY(B35) -> 14
A36: Casey Saucke | B36: 45778 | C36: CHW | D36: A | E36: OF | F36: R | G36: United States | H36: New York | I36: Virginia | J36: 21 | M36: 695565 | N36: sa3025382 | P36: 0 | Q36: 0 | R36: 1 | S36: =YEAR(B36) -> 2025 | T36: =MONTH(B36) -> 5 | U36: =DAY(B36) -> 1
A37: Danny Young | B37: 45778 | C37: NYM | D37: MLB | E37: P | F37: L | G37: United States | H37: Florida | I37: Florida | J37: 31 | M37: 664849 | N37: 18439 | P37: 0 | Q37: 0 | R37: 1 | S37: =YEAR(B37) -> 2025 | T37: =MONTH(B37) -> 5 | U37: =DAY(B37) -> 1
A38: Edgar Barclay | B38: 45778 | C38: NYY | D38: AA | E38: P | F38: L | G38: United States | H38: Oklahoma | I38: Cal State Bakersfield | J38: 27 | M38: 687607 | N38: sa1170012 | P38: 0 | Q38: 0 | R38: 1 | S38: =YEAR(B38) -> 2025 | T38: =MONTH(B38) -> 5 | U38: =DAY(B38) -> 1
A39: Moises Chace | B39: 45778 | C39: PHI | D39: AA | E39: P | F39: R | G39: Venezuela | J39: 22 | M39: 691330 | N39: sa3015346 | P39: 0 | Q39: 0 | R39: 1 | S39: =YEAR(B39) -> 2025 | T39: =MONTH(B39) -> 5 | U39: =DAY(B39) -> 1
A40: Sem Robberse | B40: 45778 | C40: STL | D40: AAA | E40: P | F40: R | G40: Netherlands | J40: 23 | M40: 691828 | N40: sa3011735 | P40: 0 | Q40: 0 | R40: 1 | S40: =YEAR(B40) -> 2025 | T40: =MONTH(B40) -> 5 | U40: =DAY(B40) -> 1
A41: Alfredo Zarraga | B41: 45778 | C41: TB | D41: AA | E41: P | F41: R | G41: Venezuela | J41: 24 | M41: 700287 | N41: sa3018276 | P41: 0 | Q41: 0 | R41: 1 | S41: =YEAR(B41) -> 2025 | T41: =MONTH(B41) -> 5 | U41: =DAY(B41) -> 1
A42: Brayden Jones | B42: 45778 | C42: TB | D42: Coll | E42: P | F42: R | G42: United States | H42: Mississippi | I42: Mississippi | J42: 23 | N42: sa3034850 | P42: 0 | Q42: 0 | R42: 1 | S42: =YEAR(B42) -> 2025 | T42: =MONTH(B42) -> 5 | U42: =DAY(B42) -> 1
A43: Braden Osbolt | B43: 45770 | C43: CIN | D43: Coll | E43: P | F43: R | G43: United States | H43: Georgia | I43: Kennesaw State | J43: 20 | N43: sa3039231 | P43: 0 | Q43: 0 | R43: 1 | S43: =YEAR(B43) -> 2025 | T43: =MONTH(B43) -> 4 | U43: =DAY(B43) -> 23
A44: Justin Steele | B44: 45765 | C44: CHC | D44: MLB | E44: P | F44: L | G44: United States | H44: Mississippi | J44: 29 | M44: 657006 | N44: 17312 | O44: Dr. Keith Meister | P44: 0 | Q44: 0 | R44: 1 | S44: =YEAR(B44) -> 2025 | T44: =MONTH(B44) -> 4 | U44: =DAY(B44) -> 18
A45: DJ Herz | B45: 45763 | C45: WAS | D45: MLB | E45: P | F45: L | G45: United States | H45: North Carolina | J45: 24 | M45: 687792 | N45: 26389 | O45: Dr. Keith Meister | P45: 0 | Q45: 0 | R45: 1 | S45: =YEAR(B45) -> 2025 | T45: =MONTH(B45) -> 4 | U45: =DAY(B45) -> 16
A46: Mason Adams | B46: 45749 | C46: CHW | D46: AAA | E46: P | F46: R | G46: United States | H46: Florida | I46: Jacksonville | J46: 25 | M46: 690279 | N46: sa3020388 | O46: Dr. Keith Meister | P46: 0 | Q46: 0 | R46: 1 | S46: =YEAR(B46) -> 2025 | T46: =MONTH(B46) -> 4 | U46: =DAY(B46) -> 2
A47: Jordan Montgomery | B47: 45748 | C47: ARI | D47: MLB | E47: P | F47: L | G47: United States | H47: South Carolina | I47: South Carolina | J47: 32 | M47: 656756 | N47: 16511 | P47: 0 | Q47: 0 | R47: 1 | S47: =YEAR(B47) -> 2025 | T47: =MONTH(B47) -> 4 | U47: =DAY(B47) -> 1
A48: Michael Salina | B48: 45748 | C48: SD | D48: Coll | E48: P | F48: R | G48: United States | H48: New York | I48: George Mason, St. Bonaventure | J48: 21 | M48: 823745 | N48: sa3041443 | P48: 0 | Q48: 0 | R48: 1 | S48: =YEAR(B48) -> 2025 | T48: =MONTH(B48) -> 4 | U48: =DAY(B48) -> 1
A49: Cooper Hjerpe | B49: 45748 | C49: STL | D49: AA | E49: P | F49: L | G49: United States | H49: California | I49: Oregon State | J49: 24 | M49: 687309 | N49: sa3020736 | P49: 0 | Q49: 0 | R49: 1 | S49: =YEAR(B49) -> 2025 | T49: =MONTH(B49) -> 4 | U49: =DAY(B49) -> 1
A50: Payton Graham | B50: 45748 | C50: STL | D50: Coll | E50: P | F50: R | G50: United States | H50: Washington | I50: Gonzaga | J50: 21 | M50: 804979 | N50: sa3032565 | P50: 0 | Q50: 0 | R50: 1 | S50: =YEAR(B50) -> 2025 | T50: =MONTH(B50) -> 4 | U50: =DAY(B50) -> 1
A51: Mason McConnaughey | B51: 45748 | C51: TEX | D51: Coll | E51: P | F51: R | G51: United States | H51: Kansas | I51: Nebraska | J51: 21 | N51: sa3037493 | P51: 0 | Q51: 0 | R51: 1 | S51: =YEAR(B51) -> 2025 | T51: =MONTH(B51) -> 4 | U51: =DAY(B51) -> 1
A52: Blake Walston | B52: 45742 | C52: ARI | D52: MLB | E52: P | F52: L | G52: United States | H52: North Carolina | J52: 24 | M52: 686796 | N52: 26270 | P52: 0 | Q52: 0 | R52: 1 | S52: =YEAR(B52) -> 2025 | T52: =MONTH(B52) -> 3 | U52: =DAY(B52) -> 26
A53: Gerrit Cole | B53: 45727 | C53: NYY | D53: MLB | E53: P | F53: R | G53: United States | H53: California | I53: UCLA | J53: 34 | M53: 543037 | N53: 13125 | O53: Dr. Neal ElAttrache | P53: 0 | Q53: 0 | R53: 1 | S53: =YEAR(B53) -> 2025 | T53: =MONTH(B53) -> 3 | U53: =DAY(B53) -> 11 | V53: 45880
A54: Jeff Criswell | B54: 45730 | C54: COL | D54: MLB | E54: P | F54: R | G54: United States | H54: Michigan | I54: Michigan | J54: 26 | M54: 676105 | N54: 27608 | O54: Dr. Keith Meister | P54: 0 | Q54: 0 | R54: 1 | S54: =YEAR(B54) -> 2025 | T54: =MONTH(B54) -> 3 | U54: =DAY(B54) -> 14
A55: Matt Duffy | B55: 45721 | C55: BOS | D55: A | E55: P | F55: R | G55: Canada | J55: 23 | M55: 683314 | N55: sa3023272 | P55: 0 | Q55: 0 | R55: 1 | S55: =YEAR(B55) -> 2025 | T55: =MONTH(B55) -> 3 | U55: =DAY(B55) -> 5
A56: Cole Tolbert | B56: 45721 | C56: BOS | D56: A | E56: P | F56: R | G56: United States | H56: Mississippi | I56: Mississippi | J56: 22 | M56: 824613 | N56: sa3025352 | P56: 0 | Q56: 0 | R56: 1 | S56: =YEAR(B56) -> 2025 | T56: =MONTH(B56) -> 3 | U56: =DAY(B56) -> 5
A57: Thyago Vieira | B57: 45717 | C57: ARI | D57: MLB | E57: P | F57: R | G57: Brazil | J57: 32 | M57: 600986 | N57: 14510 | P57: 0 | Q57: 0 | R57: 1 | S57: =YEAR(B57) -> 2025 | T57: =MONTH(B57) -> 3 | U57: =DAY(B57) -> 1
A58: Josh Winder | B58: 45717 | C58: ARI | D58: AAA | E58: P | F58: R | G58: United States | H58: Virginia | I58: Virginia Military | J58: 28 | M58: 680739 | N58: 24606 | P58: 0 | Q58: 0 | R58: 1 | S58: =YEAR(B58) -> 2025 | T58: =MONTH(B58) -> 3 | U58: =DAY(B58) -> 1
A59: Prelander Berroa | B59: 45717 | C59: CHW | D59: MLB | E59: P | F59: R | G59: Domincan | J59: 25 | M59: 672860 | N59: 22932 | O59: Dr. Keith Meister | P59: 0 | Q59: 0 | R59: 1 | S59: =YEAR(B59) -> 2025 | T59: =MONTH(B59) -> 3 | U59: =DAY(B59) -> 1
A60: Juan Carela | B60: 45717 | C60: CHW | D60: AA | E60: P | F60: R | G60: Domincan | J60: 23 | M60: 683636 | N60: 22932 | O60: Dr. Keith Meister | P60: 0 | Q60: 0 | R60: 1 | S60: =YEAR(B60) -> 2025 | T60: =MONTH(B60) -> 3 | U60: =DAY(B60) -> 1
A61: Drew Thorpe | B61: 45717 | C61: CHW | D61: MLB | E61: P | F61: R | G61: United States | H61: Utah | I61: Cal State Poly, San Luis Obispo | J61: 24 | M61: 689672 | N61: 31967 | O61: Dr. Keith Meister | P61: 0 | Q61: 0 | R61: 1 | S61: =YEAR(B61) -> 2025 | T61: =MONTH(B61) -> 3 | U61: =DAY(B61) -> 1
A62: Chase Hampton | B62: 45709 | C62: NYY | D62: AA | E62: P | F62: R | G62: United States | H62: Texas | I62: Texas Tech | J62: 23 | M62: 694633 | N62: sa3020682 | P62: 0 | Q62: 0 | R62: 1 | S62: =YEAR(B62) -> 2025 | T62: =MONTH(B62) -> 2 | U62: =DAY(B62) -> 21
A63: Ky Bush | B63: 45700 | C63: CHW | D63: AAA | E63: P | F63: L | G63: United States | H63: Utah | I63: Saint Mary's, Washington State | J63: 25 | M63: 681066 | N63: 29823 | P63: 0 | Q63: 0 | R63: 1 | S63: =YEAR(B63) -> 2025 | T63: =MONTH(B63) -> 2 | U63: =DAY(B63) -> 12
A64: Blake Larson | B64: 45689 | C64: CHW | D64: HS | E64: P | F64: L | G64: United States | H64: Florida | J64: 19 | M64: 820836 | P64: 0 | Q64: 0 | R64: 1 | S64: =YEAR(B64) -> 2025 | T64: =MONTH(B64) -> 2 | U64: =DAY(B64) -> 1
A65: Thatcher Hurd | B65: 45689 | C65: NYY | D65: Coll | E65: P | F65: R | G65: United States | H65: California | I65: LSU, UCLA | J65: 22 | M65: 695765 | N65: sa3034340 | O65: Dr. Keith Meister | P65: 0 | Q65: 0 | R65: 1 | S65: =YEAR(B65) -> 2025 | T65: =MONTH(B65) -> 2 | U65: =DAY(B65) -> 1
A66: Justin Henschel | B66: 45658 | C66: CIN | D66: Coll | E66: P | F66: R | G66: United States | H66: Florida | I66: Florida Gulf Coast | J66: 21 | N66: sa3033637 | P66: 0 | Q66: 0 | R66: 1 | S66: =YEAR(B66) -> 2025 | T66: =MONTH(B66) -> 1 | U66: =DAY(B66) -> 1
A67: Jacob Remily | B67: 45658 | C67: CLE | D67: Rk | E67: P | F67: R | G67: United States | H67: Hawaii | J67: 19 | M67: 825757 | N67: sa3067386 | P67: 0 | Q67: 0 | R67: 1 | S67: =YEAR(B67) -> 2025 | T67: =MONTH(B67) -> 1 | U67: =DAY(B67) -> 1
A68: Joseph Montalvo | B68: 45658 | C68: DET | D68: AA | E68: P | F68: R | G68: Puerto Rico | J68: 23 | M68: 702477 | N68: sa3018802 | P68: 0 | Q68: 0 | R68: 1 | S68: =YEAR(B68) -> 2025 | T68: =MONTH(B68) -> 1 | U68: =DAY(B68) -> 1
A69: Josh Knoth | B69: 45658 | C69: MIL | D69: A | E69: P | F69: R | G69: United States | H69: New York | J69: 19 | M69: 805807 | N69: sa3023420 | P69: 0 | Q69: 0 | R69: 1 | S69: =YEAR(B69) -> 2025 | T69: =MONTH(B69) -> 1 | U69: =DAY(B69) -> 1
A70: Grant Knipp | B70: 45658 | C70: SEA | D70: Coll | E70: P | F70: R | G70: United States | H70: Kentucky | I70: Campbell, Alabama | J70: 23 | M70: 694840 | N70: sa3035555 | P70: 0 | Q70: 0 | R70: 1 | S70: =YEAR(B70) -> 2025 | T70: =MONTH(B70) -> 1 | U70: =DAY(B70) -> 1
A71: T.J. Brock | B71: 45658 | C71: TOR | D71: AA | E71: P | F71: R | G71: United States | H71: Ohio | I71: Ohio State | J71: 25 | M71: 697813 | N71: sa3020079 | P71: 0 | Q71: 0 | R71: 1 | S71: =YEAR(B71) -> 2025 | T71: =MONTH(B71) -> 1 | U71: =DAY(B71) -> 1
A72: Connor Cooke | B72: 45658 | C72: TOR | D72: AAA | E72: P | F72: R | G72: United States | H72: Louisiana | I72: Louisiana | J72: 25 | M72: 701566 | N72: sa3017822 | P72: 0 | Q72: 0 | R72: 1 | S72: =YEAR(B72) -> 2025 | T72: =MONTH(B72) -> 1 | U72: =DAY(B72) -> 1
A73: Braxton Garrett | B73: 45640 | C73: MIA | D73: AAA | E73: P | F73: L | G73: United States | H73: Alabama | J73: 26 | M73: 666129 | N73: 21844 | P73: 0 | Q73: 0 | R73: 1 | S73: =YEAR(B73) -> 2024 | T73: =MONTH(B73) -> 12 | U73: =DAY(B73) -> 14
A74: Wen-Hui Pan | B74: 45597 | C74: PHI | D74: A+ | E74: P | F74: R | G74: Taiwan | J74: 21 | M74: 808207 | N74: sa3020878 | P74: 0 | Q74: 0 | R74: 1 | S74: =YEAR(B74) -> 2024 | T74: =MONTH(B74) -> 11 | U74: =DAY(B74) -> 1
A75: Julian Aguiar | B75: 45576 | C75: CIN | D75: MLB | E75: P | F75: R | G75: United States | H75: California | I75: Cypress | J75: 23 | M75: 687924 | N75: 30031 | O75: Dr. Keith Meister | P75: 0 | Q75: 0 | R75: 1 | S75: =YEAR(B75) -> 2024 | T75: =MONTH(B75) -> 10 | U75: =DAY(B75) -> 11
A76: Joe Musgrove | B76: 45576 | C76: SD | D76: MLB | E76: P | F76: R | G76: United States | H76: California | J76: 31 | M76: 605397 | N76: 12970 | O76: Dr. Keith Meister | P76: 0 | Q76: 0 | R76: 1 | S76: =YEAR(B76) -> 2024 | T76: =MONTH(B76) -> 10 | U76: =DAY(B76) -> 11 | V76: 45754
A77: Cade Feeney | B77: 45566 | C77: BOS | D77: A+ | E77: P | F77: R | G77: United States | H77: North Dakota | I77: North Dakota State | J77: 22 | M77: 814366 | N77: sa3023228 | P77: 0 | Q77: 0 | R77: 1 | S77: =YEAR(B77) -> 2024 | T77: =MONTH(B77) -> 10 | U77: =DAY(B77) -> 1
A78: Yujanyer Herrera | B78: 45566 | C78: COL | D78: A+ | E78: P | F78: R | G78: Venezuela | J78: 20 | M78: 692632 | N78: sa3015370 | P78: 0 | Q78: 0 | R78: 1 | S78: =YEAR(B78) -> 2024 | T78: =MONTH(B78) -> 10 | U78: =DAY(B78) -> 1
A79: Christian Scott | B79: 45560 | C79: NYM | D79: MLB | E79: P | F79: R | G79: United States | H79: Florida | I79: Florida | J79: 25 | M79: 681035 | N79: 30107 | O79: Dr. Keith Meister | P79: 0 | Q79: 0 | R79: 1 | S79: =YEAR(B79) -> 2024 | T79: =MONTH(B79) -> 9 | U79: =DAY(B79) -> 25
A80: Brandon Williamson | B80: 45536 | C80: CIN | D80: MLB | E80: P | F80: L | G80: United States | H80: Minnesota | I80: Texas Christian | J80: 26 | M80: 682227 | N80: 25463 | P80: 0 | Q80: 0 | R80: 1 | S80: =YEAR(B80) -> 2024 | T80: =MONTH(B80) -> 9 | U80: =DAY(B80) -> 1
A81: Bryce Montes de Oca | B81: 45536 | C81: NYM | D81: AAA | E81: P | F81: R | G81: United States | H81: Kansas | I81: Missouri | J81: 29 | M81: 656755 | N81: 21319 | P81: 0 | Q81: 0 | R81: 1 | S81: =YEAR(B81) -> 2024 | T81: =MONTH(B81) -> 9 | U81: =DAY(B81) -> 1
A82: Chad Dallas | B82: 45536 | C82: TOR | D82: AAA | E82: P | F82: R | G82: United States | H82: Texas | I82: Tennessee | J82: 24 | M82: 689149 | N82: sa3018180 | P82: 0 | Q82: 0 | R82: 1 | S82: =YEAR(B82) -> 2024 | T82: =MONTH(B82) -> 9 | U82: =DAY(B82) -> 1
A83: Nolan Perry | B83: 45536 | C83: TOR | D83: A | E83: P | F83: R | G83: United States | H83: New Mexico | J83: 20 | M83: 804526 | N83: sa3021476 | P83: 0 | Q83: 0 | R83: 1 | S83: =YEAR(B83) -> 2024 | T83: =MONTH(B83) -> 9 | U83: =DAY(B83) -> 1
A84: Carson Pierce | B84: 45536 | C84: TOR | D84: A+ | E84: P | F84: R | G84: United States | H84: Oklahoma | I84: Oklahoma | J84: 22 | M84: 804544 | N84: sa3023179 | P84: 0 | Q84: 0 | R84: 1 | S84: =YEAR(B84) -> 2024 | T84: =MONTH(B84) -> 9 | U84: =DAY(B84) -> 1
A85: Jorge Mateo | B85: 45532 | C85: BAL | D85: MLB | E85: 2B | F85: R* | G85: Dominican | J85: 29 | K85: 45743 | L85: =ROUND(((K85-B85)/365)*12,0) -> 7 | M85: 622761 | N85: 17273 | O85: Dr. Keith Meister | P85: 0 | Q85: 0 | R85: 1 | S85: =YEAR(B85) -> 2024 | T85: =MONTH(B85) -> 8 | U85: =DAY(B85) -> 28 | Z85: 45743
A86: Adbert Alzolay | B86: 45511 | C86: CHC | D86: AAA | E86: P | F86: R | G86: Venezuela | J86: 29 | M86: 640470 | N86: 17859 | O86: Dr. Keith Meister | P86: 0 | Q86: 0 | R86: 1 | S86: =YEAR(B86) -> 2024 | T86: =MONTH(B86) -> 8 | U86: =DAY(B86) -> 7
A87: Luis Medina | B87: 45511 | C87: OAK | D87: MLB | E87: P | F87: R | G87: Dominican | J87: 25 | M87: 665622 | N87: 21649 | O87: Dr. Keith Meister | P87: 0 | Q87: 0 | R87: 1 | S87: =YEAR(B87) -> 2024 | T87: =MONTH(B87) -> 8 | U87: =DAY(B87) -> 7
A88: Matt Donlan | B88: 45505 | C88: BOS | D88: AA | E88: P | F88: R | G88: United States | H88: Connecticut | I88: Connecticut | J88: 24 | M88: 804596 | N88: sa3020107 | P88: 0 | Q88: 0 | R88: 1 | S88: =YEAR(B88) -> 2024 | T88: =MONTH(B88) -> 8 | U88: =DAY(B88) -> 1
A89: Cole Mathis | B89: 45505 | C89: CHC | D89: Coll | E89: 3B | F89: R | G89: United States | H89: Georgia | I89: Charleston | J89: 20 | K89: 45751 | L89: =ROUND(((K89-B89)/365)*12,0) -> 8 | M89: 695573 | N89: sa3037300 | O89: Dr. Stephen Gryzlo | P89: 0 | Q89: 0 | R89: 1 | S89: =YEAR(B89) -> 2024 | T89: =MONTH(B89) -> 8 | U89: =DAY(B89) -> 1 | Z89: 45751
A90: River Ryan | B90: 45505 | C90: LAD | D90: MLB | E90: P | F90: R | G90: United States | H90: North Carolina | I90: North Carolina | J90: 25 | M90: 689981 | N90: 29514 | O90: Dr. Neal ElAttrache | P90: 0 | Q90: 0 | R90: 1 | S90: =YEAR(B90) -> 2024 | T90: =MONTH(B90) -> 8 | U90: =DAY(B90) -> 1
A91: Luke Keaschall | B91: 45505 | C91: MIN | D91: AA | E91: 2B | F91: R | G91: United States | H91: California | I91: San Francisco, Arizona State | J91: 21 | K91: 45744 | L91: =ROUND(((K91-B91)/365)*12,0) -> 8 | M91: 807712 | N91: 33321 | P91: 0 | Q91: 0 | R91: 1 | S91: =YEAR(B91) -> 2024 | T91: =MONTH(B91) -> 8 | U91: =DAY(B91) -> 1 | Z91: 45744
A92: Kyle Hurt | B92: 45503 | C92: LAD | D92: AAA | E92: P | F92: R | G92: United States | H92: California | I92: USC | J92: 26 | K92: 45902 | L92: =ROUND(((K92-B92)/365)*12,0) -> 13 | M92: 669165 | N92: 27514 | O92: Dr. Neal ElAttrache | P92: 0 | Q92: 0 | R92: 1 | S92: =YEAR(B92) -> 2024 | T92: =MONTH(B92) -> 7 | U92: =DAY(B92) -> 30 | Z92: 45902
A93: Ricky Tiedemann | B93: 45503 | C93: TOR | D93: AAA | E93: P | F93: L | G93: United States | H93: California | I93: Golden West | J93: 21 | M93: 694357 | N93: sa3018096 | O93: Dr. Neal ElAttrache | P93: 0 | Q93: 0 | R93: 1 | S93: =YEAR(B93) -> 2024 | T93: =MONTH(B93) -> 7 | U93: =DAY(B93) -> 30
A94: Josiah Gray | B94: 45497 | C94: WAS | D94: AAA | E94: P | F94: R | G94: United States | H94: New York | I94: Le Moyne | J94: 26 | M94: 680686 | N94: 24580 | O94: Dr. Keith Meister | P94: 0 | Q94: 0 | R94: 1 | S94: =YEAR(B94) -> 2024 | T94: =MONTH(B94) -> 7 | U94: =DAY(B94) -> 24 | Z94: 45907
A95: Drew Smith | B95: 45485 | C95: NYM | D95: MLB | E95: P | F95: R | G95: United States | H95: Texas | I95: Dallas Baptist | J95: 30 | M95: 622098 | N95: 17755 | O95: Dr. Keith Meister | P95: 0 | Q95: 0 | R95: 1 | S95: =YEAR(B95) -> 2024 | T95: =MONTH(B95) -> 7 | U95: =DAY(B95) -> 12
A96: Luis Oritz | B96: 45484 | C96: PHI | D96: AAA | E96: P | F96: R | G96: United States | H96: California | J96: 28 | M96: 656814 | N96: 16942 | P96: 0 | Q96: 0 | R96: 1 | S96: =YEAR(B96) -> 2024 | T96: =MONTH(B96) -> 7 | U96: =DAY(B96) -> 11
A97: Kiefer Lord | B97: 45476 | C97: BAL | D97: Rk | E97: P | F97: R | G97: United States | H97: California | I97: Washington, Carleton | J97: 21 | K97: 45889 | L97: =ROUND(((K97-B97)/365)*12,0) -> 14 | M97: 811296 | N97: sa3023135 | O97: Dr. Keith Meister | P97: 0 | Q97: 0 | R97: 1 | S97: =YEAR(B97) -> 2024 | T97: =MONTH(B97) -> 7 | U97: =DAY(B97) -> 3 | Z97: 45889
A98: Joey Broughton | B98: 45475 | C98: MIL | D98: Coll | E98: P | F98: L | G98: United States | H98: Michigan | P98: 0 | Q98: 0 | R98: 1 | S98: =YEAR(B98) -> 2024 | T98: =MONTH(B98) -> 7 | U98: =DAY(B98) -> 2
A99: Ray Kerr | B99: 45474 | C99: ATL | D99: MLB | E99: P | F99: L | G99: United States | H99: Nevada | I99: Lassen | J99: 29 | M99: 678061 | N99: 23809 | P99: 0 | Q99: 0 | R99: 1 | S99: =YEAR(B99) -> 2024 | T99: =MONTH(B99) -> 7 | U99: =DAY(B99) -> 1
A100: Cade Kuehler | B100: 45474 | C100: ATL | D100: A+ | E100: P | F100: R | G100: United States | H100: North Carolina | I100: Campbell | J100: 22 | M100: 805780 | N100: sa3023306 | P100: 0 | Q100: 0 | R100: 1 | S100: =YEAR(B100) -> 2024 | T100: =MONTH(B100) -> 7 | U100: =DAY(B100) -> 1
...

Sheet How To Use
A1: Important usage notes:
A2: - Creating and maintaining this database has required thousands of hours of work since 2012. I am committed to keeping it publically available for free.
A3: - If you have benefitted from using the database and wish to make a donation, you may do so at https://paypal.me/mlbplayeranalys?country.x=CA&locale.x=en_US
A4: - This list is *not* a complete list of *all* Tommy John surgeries. The list contains entries for all Tommy John surgeries of MLB and MiLB players that have been confirmed through media reports of some kind.
A5: - Some teams are much more guarded in releasing information about Tommy John surgeries than other teams. Some teams have beat writers or prospect writers who dig for MiLB injury statuses more than other teams.
A6: - Some Tommy John surgeries go completely unreported by the media and will not appear in this list.
A7: - Additional player information comes from Baseball Reference, Fangraphs, Baseball Cube, MiLB.com.
A8: - When the month of the surgery is known but not the exact date, MM/1/YYYY is used for the surgery date.
A9: - When the year of the surgery is known but not the month or date, 1/1/YYYY is used for the surgery date.
A10: - 'Level' is the level of baseball in which the player played his last game prior to having Tommy John surgery. Some players listed with an MiLB level have had previous MLB experience.
A11: - After the MLB Draft in June, players who sign who have had Tommy John surgery are added to the TJ List. Unsigned drafted players remain in the Unsigned Draftees list.
A12: - UCL PRP tracks players who had PRP/stem cell injections specifically due to UCL damage (i.e. not flexor tendon).
... A14: - UCL InternalBrace was developed by Dr. Jeffrey Dugas at ASMI.

Sheet Pending
A1: Player | B1: Notes
A2: Vinny Nittoli | B2: SEA, MiLB, RHP, one reference had it in 2014, can't confirm
A3: Bryan Blanton | B3: NYY, MiLB, RHP, unconfirmed that he had TJ surgery | C3: https://twitter.com/jeremyarroyo/status/1371651765528113153?s=11
A4: Rodney Theophile | B4: WAS, MiLB, RHP, unconfirmed that he had TJ surgery | C4: https://twitter.com/nicabeis/status/1389778623608012801?s=11
A5: Dane Acker | B5: TEX, MiLB, RHP, elbow surgery 5/26, either TJ or InternalBrace
A6: Angel Benitez | B6: NYY, MiLB, had TJ surgery but was it 2022 or early 2023 | C6: https://twitter.com/NYY_Prospects/status/1617992159097151489
A7: Hunter Bishop | B7: SF, MiLB, A+, OF, had UCL surgery 4/1, not sure which kind
A8: Brandon White | B8: PIT, MiLB, need to confirm had TJ
A9: Yoelvis Sanchez | B9: PIT, MiLB, need to confirm had TJ
A10: Julio Mendez | B10: PIT, MiLB, need to confirm had TJ
A11: Hayden Robinson | B11: MIL, MiLB, needs surgery, either TJ or internal brace
A12: Alejandro Rosario | B12: TEX, MiLB, needs second TJ surgery? | C12: https://x.com/picksshelf/status/1893419808869294186?s=43&t=NO0hlvLBbI0JRudVD13oLg
A13: Alex Young | B13: CIN, LHP, may need TJ surgery
A14: Jake Bloss | B14: TOR, MiLB, RHP, having some form of UCL surgery with Dr. Meister
A15: Nick Judice | B15: BOS, had some arm surgery, maybe TJ | C15: https://x.com/ByAndrewParker/status/1946640944582864933
A16: Carson Spiers | B16: CIN, MLB. had UCL surgery with Dr. Meister, either TJ or IB
A17: Manuel Rodriguez | B17: TB, MLB, had surgery 8/8, were going to look at UCL, Dr. Meister

Sheet UCL PRP
A1: Player | B1: PRP Injection Date | C1: Stem Cell? | D1: Team | E1: Level | F1: Return Date (same level) | G1: Recovery Time (months) | H1: TJ Surgery Date | I1: UCL Damage Description
A2: Graham Ashcraft | B2: 45483 | D2: CIN | E2: MLB
A3: Jeff McNeil | B3: 45200 | D3: NYM | E3: MLB
A4: Ryan Weber | B4: 45078 | D4: NYY | E4: MLB
A5: Bryce Harper | B5: 44696 | D5: PHI | E5: MLB | H5: 44888
A6: Chris Paddack | B6: 44466 | D6: SD | E6: MLB | F6: 44664 | G6: =ROUND(((F6-B6)/365)*12,0) -> 7 | H6: 44699
A7: Nick Burdi | B7: 44044 | D7: PIT | E7: MLB | H7: 44118
A8: Griffin Canning | B8: 43896 | D8: LAA | E8: MLB | F8: 44294 | G8: =ROUND(((F8-B8)/365)*12,0) -> 13
A9: John Brebbia | B9: 43891 | D9: STL | E9: MLB | H9: 43990
A10: Kent Emanuel | B10: 43831 | D10: HOU | E10: AAA | F10: 44310
A11: Tommy Pham | B11: 43831 | C11: Y | D11: TB | E11: MLB | F11: 44287
A12: Steven Wright | B12: 43678 | D12: BOS | E12: MLB | H12: 43760
A13: Blaine Hardy | B13: 43678 | D13: DET | E13: MLB | H13: 43910
A14: Seranthony Dominguez | B14: 43630 | D14: PHI | E14: MLB | H14: 44042
A15: T.J. Rivera | B15: 43297 | D15: NYM | E15: MLB
A16: Shohei Ohtani | B16: 43258 | C16: Y | D16: LAA | E16: MLB | F16: 43345 | G16: =ROUND(((F16-B16)/365)*12,0) -> 3 | H16: 43374 | I16: 2nd-grade tear (unrelated to previous tear)
A17: Shohei Ohtani | B17: 43009 | D17: LAA | E17: MLB | F17: 43188 | G17: =ROUND(((F17-B17)/365)*12,0) -> 6 | H17: 43374 | I17: 1st-degree tear
A18: Matt Givin | B18: 43009 | D18: MIA | E18: Rk | H18: 43207
A19: Wei-Yin Chen | B19: 43005 | D19: MIA | E19: MLB | F19: 43218 | G19: =ROUND(((F19-B19)/365)*12,0) -> 7
A20: JC Ramirez | B20: 42971 | C20: Y | D20: LAA | E20: MLB | F20: 43192 | G20: =ROUND(((F20-B20)/365)*12,0) -> 7 | H20: 43207 | I20: partial tear
A21: T.J. Rivera | B21: 42944 | D21: NYM | E21: MLB | H21: 42992
A22: Anthony Santander | B22: 42864 | D22: BAL | E22: A+ | F22: 42943 | G22: =ROUND(((F22-B22)/365)*12,0) -> 3
A23: Branden Kline | B23: 42840 | D23: BAL | E23: AA | F23: 43240 | G23: =ROUND(((F23-B23)/365)*12,0) -> 13
A24: Seth Lugo | B24: 42829 | D24: NYM | E24: MLB | F24: 42897 | G24: =ROUND(((F24-B24)/365)*12,0) -> 2 | I24: slight tear
A25: Chi Chi Gonzalez | B25: 42815 | D25: TEX | E25: AAA | H25: 42917 | I25: partial tear (10%)
A26: Victor Arano | B26: 42788 | D26: PHI | E26: AA | F26: 42886 | G26: =ROUND(((F26-B26)/365)*12,0) -> 3
A27: Keston Hiura | B27: 42736 | D27: MIL | E27: Coll | F27: 42784 | G27: =ROUND(((F27-B27)/365)*12,0) -> 2
A28: Yimmi Brasoban | B28: 42675 | C28: Y | D28: SD | E28: AA | F28: 42899 | G28: =ROUND(((F28-B28)/365)*12,0) -> 7
A29: Rubby De La Rosa | B29: 42640 | C29: Y | D29: ARI | E29: MLB | F29: 42909 | G29: =ROUND(((F29-B29)/365)*12,0) -> 9 | H29: 42969 | I29: stretch (tried PRP earlier in summer too)
A30: Colin Rea | B30: 42600 | D30: SD | E30: MLB | H30: 42684 | I30: partial tear
A31: Aaron Nola | B31: 42599 | D31: PHI | E31: MLB | F31: 42833 | G31: =ROUND(((F31-B31)/365)*12,0) -> 8 | I31: low-grade tear
A32: Wei-Yin Chen | B32: 42583 | D32: MIA | E32: MLB | F32: 42632 | G32: =ROUND(((F32-B32)/365)*12,0) -> 2 | I32: slight tear
A33: Jon Edwards | B33: 42522 | D33: SD | E33: MLB | F33: 43344 | G33: =ROUND(((F33-B33)/365)*12,0) -> 27 | I33: wear
A34: Garrett Richards | B34: 42506 | C34: Y | D34: LAA | E34: MLB | F34: 42830 | G34: =ROUND(((F34-B34)/365)*12,0) -> 11 | H34: 43305 | I34: lengthwise tear down middle (20-25%)
A35: Sean Nolin | B35: 42491 | D35: MIL | E35: MLB | H35: 42583 | I35: partial tear
A36: Andrew Heaney | B36: 42491 | C36: Y | D36: LAA | E36: MLB | H36: 42552 | I36: some degree of tear
A37: Michael Lorenzen | B37: 42461 | D37: CIN | E37: MLB | F37: 42545 | G37: =ROUND(((F37-B37)/365)*12,0) -> 3 | I37: mild tear
A38: Connor Strain | B38: 42370 | D38: LAD | E38: Coll | F38: 42783
A39: Casey Sadler | B39: 42211 | D39: PIT | E39: AAA | H39: 42278 | I39: unknown
A40: Alex Cobb | B40: 42130 | D40: TB | E40: MLB | H40: 42138 | I40: partial tear
A41: Brandon Workman | B41: 42109 | D41: BOS | E41: MLB | H41: 42170 | I41: partial tear
A42: Tyler Thornburg | B42: 41852 | D42: MIL | E42: MLB | F42: 42101 | G42: =ROUND(((F42-B42)/365)*12,0) -> 8 | I42: weakness, slight tear (may be from 2004)
A43: Masahiro Tanaka | B43: 41834 | D43: NYY | E43: MLB | F43: 41903 | G43: =ROUND(((F43-B43)/365)*12,0) -> 2 | I43: partial tear (10%)
A44: Jonny Venters | B44: 41791 | D44: ATL | E44: MLB | H44: 41899 | I44: soreness during TJ surgery rehab
A45: Tom Robson | B45: 41760 | D45: TOR | E45: A | H45: 41835 | I45: partial tear
A46: Burch Smith | B46: 41640 | D46: SD | E46: AAA | H46: 42101
A47: Jonny Venters | B47: 41366 | D47: ATL | E47: MLB | H47: 41410
A48: Chad Billingsley | B48: 41153 | D48: LAD | E48: MLB | F48: 41374 | G48: =ROUND(((F48-B48)/365)*12,0) -> 7 | H48: 41388 | I48: partial tear
A49: Carl Crawford | B49: 41000 | D49: BOS | E49: MLB | F49: 41106 | G49: =ROUND(((F49-B49)/365)*12,0) -> 3 | H49: 41144 | I49: partial tear
A50: Takashi Saito | B50: 39630 | D50: LAD | E50: MLB | F50: 39706 | G50: =ROUND(((F50-B50)/365)*12,0) -> 2 | I50: partial tear, starting to come off bone

Sheet UCL InternalBrace
A1: Player | B1: UCL primary repair with internal brace construction Date | C1: Team | D1: Level | E1: Return Date (same level) | F1: Recovery Time (months) | G1: Return Date (any level) | H1: TJ Surgery Date | I1: Surgeon(s) | J1: Recovery Schedule
A2: Humberto Cruz | B2: 45870 | C2: SD | D2: A
A3: Trevor Williams | B3: 45855 | C3: WAS | D3: MLB | I3: Dr. Jeffrey Dugas
A4: Connor Thomas | B4: 45854 | C4: MIL | D4: Rk
A5: Clarke Schmidt | B5: 45849 | C5: NYY | D5: MLB | I5: Dr. Keith Meister
A6: Cody Bradford | B6: 45833 | C6: TEX | D6: MLB | I6: Dr. Keith Meister
A7: A.J. Puk | B7: 45828 | C7: ARI | D7: MLB | I7: Dr. Neal ElAttrache
A8: Jared Jones | B8: 45798 | C8: PIT | D8: MLB | I8: Dr. Keith Meister
A9: Ben Abeldt | B9: 45689 | C9: TEX | D9: Coll | I9: Dr. Keith Meister
A10: Trei Cruz | B10: 45505 | C10: DET | D10: AA
A11: Patrick Sandoval | B11: 45469 | C11: LAA | D11: MLB
A12: Tyler Wells | B12: 45460 | C12: BAL | D12: MLB | E12: 45902 | F12: =ROUND(((E12-B12)/365)*12,0) -> 15 | I12: Dr. Keith Meister
A13: Garrett Whitlock | B13: 45442 | C13: BOS | D13: MLB | E13: 45743 | F13: =ROUND(((E13-B13)/365)*12,0) -> 10 | G13: 45743 | I13: Dr. Jeffrey Dugas
A14: Nate Lavender | B14: 45413 | C14: NYM | D14: AAA
A15: Landen Maroudis | B15: 45413 | C15: TOR | D15: A | G15: 45780
A16: Spencer Strider | B16: 45394 | C16: ATL | D16: MLB | E16: 45762 | F16: =ROUND(((E16-B16)/365)*12,0) -> 12 | G16: 45745 | I16: Dr. Keith Meister
A17: Jonathan Loaisiga | B17: 45394 | C17: NYY | D17: MLB | E17: 45793 | F17: =ROUND(((E17-B17)/365)*12,0) -> 13 | G17: 45773 | I17: Dr. Keith Meister
A18: Tejay Antone | B18: 45383 | C18: CIN | D18: MLB | I18: Dr. Timonthy Kremchek
A19: Lucas Giolito | B19: 45363 | C19: BOS | D19: MLB | E19: 45777 | F19: =ROUND(((E19-B19)/365)*12,0) -> 14 | G19: 45749 | I19: Dr. Jeffrey Dugas
A20: Brendan Donovan | B20: 45140 | C20: STL | D20: MLB | E20: 45379 | F20: =ROUND(((E20-B20)/365)*12,0) -> 8 | G20: 45379 | I20: Dr. Keith Meister
A21: Drew Rasmussen | B21: 45131 | C21: TB | D21: MLB | E21: 45511 | F21: =ROUND(((E21-B21)/365)*12,0) -> 12 | I21: Dr. Keith Meister
A22: Connor Prielipp | B22: 45124 | C22: MIN | D22: Rk | I22: Dr. Keith Meister
A23: Vince Velasquez | B23: 45086 | C23: PIT | D23: MLB | I23: Dr. Neal ElAttrache
A24: Trevor Story | B24: 44935 | C24: BOS | D24: MLB | E24: 45146 | F24: =ROUND(((E24-B24)/365)*12,0) -> 7 | G24: 45128 | I24: Dr. Keith Meister
A25: Eduardo Valencia | B25: 44927 | C25: DET | D25: A+ | G25: 45389
A26: Talon Haley | B26: 44927 | C26: LAA | D26: HS
A27: Isaac Ayon | B27: 44866 | C27: LAD | D27: Coll | H27: 45292
A28: Aaron Zavala | B28: 44866 | C28: TEX | D28: AA | E28: 45063 | F28: =ROUND(((E28-B28)/365)*12,0) -> 6 | G28: 45063
A29: Sean Doolittle | B29: 44743 | C29: WAS | D29: MLB | G29: 45073
A30: Adam Meier | B30: 44652 | C30: ATL | D30: Coll
A31: Will Kincanon | B31: 44628 | C31: CHW | D31: AA | G31: 45063 | I31: Dr. Lyle Cain
A32: Nick Conte | B32: 44562 | C32: KC | D32: Coll | G32: 45356
A33: Nick Anderson | B33: 44470 | C33: TB | D33: MLB | E33: 45017 | F33: =ROUND(((E33-B33)/365)*12,0) -> 18 | G33: 44764
A34: Zach Britton | B34: 44447 | C34: NYY | D34: MLB | E34: 44828 | F34: =ROUND(((E34-B34)/365)*12,0) -> 13 | G34: 44797 | I34: Dr. Neal ElAttrache
A35: Eli White | B35: 44447 | C35: TEX | D35: MLB | E35: 44660 | F35: =ROUND(((E35-B35)/365)*12,0) -> 7 | G35: 44695 | I35: Dr. Keith Meister
A36: Garrett Cooper | B36: 44409 | C36: MIA | D36: MLB | E36: 44659 | F36: =ROUND(((E36-B36)/365)*12,0) -> 8 | G36: 44659
A37: Tyree Thompson | B37: 44375 | C37: TEX | D37: A | E37: 44675 | F37: =ROUND(((E37-B37)/365)*12,0) -> 10 | G37: 44675 | I37: Dr. Keith Meister
A38: Kent Emanuel | B38: 44350 | C38: HOU | D38: MLB | G38: 44721 | I38: Dr. Jeffrey Dugas
A39: Bryan Woo | B39: 44287 | C39: SEA | D39: Coll | E39: 44718 | F39: =ROUND(((E39-B39)/365)*12,0) -> 14 | G39: 44718
A40: Lazaro Estrada | B40: 44197 | C40: TOR | D40: A | E40: 44778 | G40: 44757
A41: Nick Frasso | B41: 44197 | C41: TOR | D41: A | E41: 44695 | G41: 44695
A42: Ryan Bergert | B42: 44136 | C42: SD | D42: Coll | G42: 44421
A43: Rhys Hoskins | B43: 44106 | C43: PHI | D43: MLB | E43: 44287 | F43: =ROUND(((E43-B43)/365)*12,0) -> 6 | G43: 44287 | I43: Dr. Steve Cohen | J43: Surgery on non-throwing arm
A44: Danny Santana | B44: 44083 | C44: TEX | D44: MLB | E44: 44337 | F44: =ROUND(((E44-B44)/365)*12,0) -> 8 | G44: 44321
A45: Yadiel Rivera | B45: 44075 | C45: TEX | D45: MLB | G45: 44325
A46: Rich Hill | B46: 43739 | C46: LAD | D46: MLB | E46: 44041 | F46: =ROUND(((E46-B46)/365)*12,0) -> 10 | G46: 44041
A47: Drew Robinson | B47: 43692 | C47: STL | D47: AAA | E47: 44322 | F47: =ROUND(((E47-B47)/365)*12,0) -> 21 | G47: 44322 | I47: Dr. George Paletta
A48: Matt Bush | B48: 43344 | C48: TEX | D48: MLB | G48: 43624 | H48: 43647
A49: Jesse Hahn | B49: 43313 | C49: KC | D49: AAA | E49: 43713 | F49: =ROUND(((E49-B49)/365)*12,0) -> 13 | G49: 43698
A50: Ronnie Williams | B50: 43221 | C50: STL | D50: AA | E50: 43591 | F50: =ROUND(((E50-B50)/365)*12,0) -> 12 | G50: 43559
A51: Kyle Marman | B51: 43191 | C51: CLE | D51: Coll | E51: 43609 | F51: =ROUND(((E51-B51)/365)*12,0) -> 14 | G51: 43609
A52: Rick Ankiel | B52: 43101 | C52: STL | D52: MLB
A53: Skylar Szynski | B53: 42954 | C53: OAK | D53: Rk | H53: 43249 | J53: 11/27/2017: Started throwing baseball again
A54: Shea Murray | B54: 42948 | C54: PIT | D54: Coll | E54: 43268 | F54: =ROUND(((E54-B54)/365)*12,0) -> 11 | G54: 43268
A55: Gunner Leger | B55: 42929 | C55: ULL | D55: Coll | E55: 43511 | F55: =ROUND(((E55-B55)/365)*12,0) -> 19 | G55: 43511 | I55: Dr. Jeffrey Dugas
A56: John Fasola | B56: 42842 | C56: TEX | D56: AAA | E56: 43563 | G56: 43218 | H56: 43606 | I56: Dr. Keith Meister
A57: Jordan Schafer | B57: 42811 | C57: STL | D57: AAA | E57: 43237 | F57: =ROUND(((E57-B57)/365)*12,0) -> 14 | G57: 42856 | I57: Dr. George Paletta
A58: CJ Eldred | B58: 42736 | C58: Iowa | D58: Coll | E58: 43257 | G58: 43257
A59: Seth Maness | B59: 42598 | C59: STL | D59: MLB | E59: 42868 | F59: =ROUND(((E59-B59)/365)*12,0) -> 9 | G59: 42856 | I59: Dr. George Paletta | J59: 6 weeks: keep in brace, getting range of motion back
A60: Mitch Harris | B60: 42536 | C60: STL | D60: MLB | G60: 42838 | I60: Dr. George Paletta | J60: 4 weeks: plyometrics, two-handed then one-handed with operative arm
J62: 6-7 months total recovery

Sheet Repeat TJ List
A1: Player | B1: TJ Surgery Date | C1: Back to Playing? | D1: Years Between | E1: Surgeon | F1: 2nd Surgeon | G1: Same? | H1: Multiple TJ | I1: Count
A2: Adam Choplick | B2: 40544 | C2: Back | D2: =MAX((B2-B3)/365, 1) -> 1 | H2: Same Surgeon | I2: =COUNTIF(G:G,1) -> 30
A3: Adam Choplick | B3: 40280 | E3: Unknown | H3: Diff Suregon | I3: =COUNTIF(G:G,0) -> 28
A4: Adam Parks | B4: 42544 | C4: Back | D4: =MAX((B4-B5)/365, 1) -> 4.4794521
A5: Adam Parks | B5: 40909 | E5: Unknown
A6: Al Reyes | B6: 38643 | C6: Back | D6: =MAX((B6-B7)/365, 1) -> 10.221918
A7: Al Reyes | B7: 34912 | E7: Unknown
A8: Alfredo Silverio | B8: 41451 | C8: Back | D8: =MAX((B8-B9)/365, 1) -> 1.1315068
A9: Alfredo Silverio | B9: 41038 | E9: Unknown
A10: Anderson Espinoza | B10: 43577 | C10: Back | D10: =MAX((B10-B11)/365, 1) -> 1.7260274 | F10: Dr. Keith Meister | G10: 1
A11: Anderson Espinoza | B11: 42947 | E11: Dr. Keith Meister
A12: Andrew Lee | B12: 42580 | C12: Back | D12: =MAX((B12-B13)/365, 1) -> 4.5780822
A13: Andrew Lee | B13: 40909 | E13: Unknown
A14: Andrew McKirahan | B14: 42439 | C14: Not back | D14: =MAX((B14-B15)/365, 1) -> 3.660274 | F14: Dr. James Andrews | G14: 0
A15: Andrew McKirahan | B15: 41103 | E15: Dr. Stephen Gryzlo
A16: Artie Lewicki | B16: 43313 | C16: Back | D16: =MAX((B16-B17)/365, 1) -> 6.0027397
A17: Artie Lewicki | B17: 41122 | E17: Dr. Christopher Ahmad
A18: Ben Leeper | B18: 45017 | C18: Not yet | D18: =MAX((B18-B19)/365, 1) -> 7.2520548
A19: Ben Leeper | B19: 42370 | C19: Back | D19: =MAX((B19-B20)/365, 1) -> 1.5041096 | E19: Unknown
A20: Ben Leeper | B20: 41821 | E20: Unknown
A21: Blaine Howell | B21: 41275 | C21: Back | D21: =MAX((B21-B22)/365, 1) -> 1.0027397
A22: Blaine Howell | B22: 40909 | E22: Unknown
A23: Blake Wood | B23: 43250 | C23: Not back | D23: =MAX((B23-B24)/365, 1) -> 6.0164384 | F23: Dr. Neal ElAttrache | G23: 0
A24: Blake Wood | B24: 41054 | E24: {=INDEX('TJ List'!O:O,MATCH(A24&B24,'TJ List'!A:A&'TJ List'!B:B,0))} -> Dr. Lewis Yocum
A25: Blayne Enlow | B25: 45383 | C25: Not yet | D25: =MAX((B25-B26)/365, 1) -> 2.8136986
A26: Blayne Enlow | B26: 44356 | E26: Unknown
A27: Brad Wieck | B27: 44762 | C27: Not yet | D27: =MAX((B27-B28)/365, 1) -> 11.394521
A28: Brad Wieck | B28: 40603 | E28: Unknown
A29: Brandon Bailey | B29: 44228 | C29: Not back | D29: =MAX((B29-B30)/365, 1) -> 8.5342466
A30: Brandon Bailey | B30: 41113 | E30: Unknown
A31: Brandon Beachy | B31: 41719 | C31: Back | D31: =MAX((B31-B32)/365, 1) -> 1.7479452 | F31: Dr. Neal ElAttrache | G31: 0
A32: Brandon Beachy | B32: 41081 | E32: {=INDEX('TJ List'!O:O,MATCH(A32&B32,'TJ List'!A:A&'TJ List'!B:B,0))} -> Dr. James Andrews
A33: Brandon Young | B33: 44562 | C33: Back | D33: =MAX((B33-B34)/365, 1) -> 8.0054795
A34: Brandon Young | B34: 41640 | E34: Unknown
A35: Braxton Garrett | B35: 45640 | C35: Not yet | D35: =MAX((B35-B36)/365, 1) -> 7.490411
A36: Braxton Garrett | B36: 42906 | E36: {=INDEX('TJ List'!O:O,MATCH(A36&B36,'TJ List'!A:A&'TJ List'!B:B,0))} -> Dr. James Andrews
A37: Brian Anderson | B37: 38718 | C37: Not back | D37: =MAX((B37-B38)/365, 1) -> 1 | F37: Dr. Timothy Kremchek | G37: 1
A38: Brian Anderson | B38: 38554 | E38: {=INDEX('TJ List'!O:O,MATCH(A38&B38,'TJ List'!A:A&'TJ List'!B:B,0))} -> Dr. Timothy Kremchek
A39: Brian Wilson | B39: 41018 | C39: Back | D39: =MAX((B39-B40)/365, 1) -> 9.3041096
A40: Brian Wilson | B40: 37622 | E40: Unknown
A41: Brock Bell | B41: 44317 | C41: Back | D41: =MAX((B41-B42)/365, 1) -> 3.3315068
A42: Brock Bell | B42: 43101 | E42: Unknown
A43: Bryce Montes de Oca | B43: 45901 | C43: Not yet | D43: =MAX((B43-B44)/365, 1) -> 2.430137
A44: Bryce Montes de Oca | B44: 45014 | C44: Back | D44: =MAX((B44-B45)/365, 1) -> 10.969863 | E44: Unknown
A45: Bryce Montes de Oca | B45: 41010 | E45: Unknown
A46: Caleb Ferguson | B46: 44096 | C46: Back | D46: =MAX((B46-B47)/365, 1) -> 6.3205479
A47: Caleb Ferguson | B47: 41789 | E47: Unknown
A48: Carlos Almanzar | B48: 38899 | C48: Not back | D48: =MAX((B48-B49)/365, 1) -> 1.139726
A49: Carlos Almanzar | B49: 38483 | E49: {=INDEX('TJ List'!O:O,MATCH(A49&B49,'TJ List'!A:A&'TJ List'!B:B,0))} -> Dr. Lewis Yocum
A50: Chad Fox | B50: 36368 | C50: Back | D50: =MAX((B50-B51)/365, 1) -> 3.0712329 | F50: Dr. James Andrews | G50: 1
A51: Chad Fox | B51: 35247 | E51: {=INDEX('TJ List'!O:O,MATCH(A51&B51,'TJ List'!A:A&'TJ List'!B:B,0))} -> Dr. James Andrews
A52: Chang-Yong Lim | B52: 41091 | C52: Back | D52: =MAX((B52-B53)/365, 1) -> 7.5013699
A53: Chang-Yong Lim | B53: 38353 | E53: Unknown
A54: Chris Capuano | B54: 39583 | C54: Back | D54: =MAX((B54-B55)/365, 1) -> 6 | F54: Dr. James Andrews | G54: 1
A55: Chris Capuano | B55: 37393 | E55: {=INDEX('TJ List'!O:O,MATCH(A55&B55,'TJ List'!A:A&'TJ List'!B:B,0))} -> Dr. James Andrews
A56: Chris Paddack | B56: 44699 | C56: Back | D56: =MAX((B56-B57)/365, 1) -> 5.7589041 | F56: Dr. Keith Meister | G56: 1
A57: Chris Paddack | B57: 42597 | E57: Dr. Keith Meister
A58: Christian Garcia | B58: 40288 | C58: Back | D58: =MAX((B58-B59)/365, 1) -> 4.3013699
A59: Christian Garcia | B59: 38718 | E59: Unknown
A60: Cole Phillips | B60: 45292 | C60: Not yet | D60: =MAX((B60-B61)/365, 1) -> 1.7534247
A61: Cole Phillips | B61: 44652 | E61: Unknown
A62: Cole Ragans | B62: 43600 | C62: Back | D62: =MAX((B62-B63)/365, 1) -> 1.1315068 | F62: Dr. Keith Meister | G62: 1
A63: Cole Ragans | B63: 43187 | E63: Dr. Keith Meister
A64: Cole Sulser | B64: 42005 | C64: Back | D64: =MAX((B64-B65)/365, 1) -> 3.7561644
A65: Cole Sulser | B65: 40634 | E65: Unknown
A66: Colin Poche | B66: 44041 | C66: Back | D66: =MAX((B66-B67)/365, 1) -> 6.1643836
A67: Colin Poche | B67: 41791 | E67: Unknown
A68: Connor Curry | B68: 43831 | C68: Not back | D68: =MAX((B68-B69)/365, 1) -> 2.2520548
A69: Connor Curry | B69: 43009 | E69: Unknown
A70: Connor Sadzeck | B70: 43741 | C70: Back | D70: =MAX((B70-B71)/365, 1) -> 5.5260274
A71: Connor Sadzeck | B71: 41724 | E71: Dr. Keith Meister
A72: Corey Black | B72: 43564 | C72: Not back | D72: =MAX((B72-B73)/365, 1) -> 2.1835616
A73: Corey Black | B73: 42767 | C73: Not back | D73: =MAX((B73-B74)/365, 1) -> 6.090411 | E73: Unknown
A74: Corey Black | B74: 40544 | E74: Unknown
A75: Cory Luebke | B75: 41688 | C75: Back | D75: =MAX((B75-B76)/365, 1) -> 1.7424658 | F75: Dr. James Andrews | G75: 0
A76: Cory Luebke | B76: 41052 | E76: {=INDEX('TJ List'!O:O,MATCH(A76&B76,'TJ List'!A:A&'TJ List'!B:B,0))} -> Dr. Lewis Yocum
A77: Daniel Hudson | B77: 41443 | C77: Back | D77: =MAX((B77-B78)/365, 1) -> 1 | F77: Dr. James Andrews | G77: 0
A78: Daniel Hudson | B78: 41099 | E78: {=INDEX('TJ List'!O:O,MATCH(A78&B78,'TJ List'!A:A&'TJ List'!B:B,0))} -> Dr. Lewis Yocum
A79: Daniel Missaki | B79: 42453 | C79: Not back | D79: =MAX((B79-B80)/365, 1) -> 1
A80: Daniel Missaki | B80: 42136 | E80: Unknown
A81: Darren Dreifort | B81: 37081 | C81: Back | D81: =MAX((B81-B82)/365, 1) -> 6.3260274 | F81: Dr. Frank Jobe | G81: 1
A82: Darren Dreifort | B82: 34772 | E82: {=INDEX('TJ List'!O:O,MATCH(A82&B82,'TJ List'!A:A&'TJ List'!B:B,0))} -> Dr. Frank Jobe
A83: Daulton Jefferies | B83: 44813 | C83: Not yet | D83: =MAX((B83-B84)/365, 1) -> 5.3753425
A84: Daulton Jefferies | B84: 42851 | E84: Unknown
A85: David Fry | B85: 45292 | C85: Back | D85: =MAX((B85-B86)/365, 1) -> 7.0027397
A86: David Fry | B86: 42736 | E86: Unknown
A87: Dax Fulton | B87: 45090 | C87: Not yet | D87: =MAX((B87-B88)/365, 1) -> 3.7835616
A88: Dax Fulton | B88: 43709 | E88: Unknown
A89: Dave Eiland | B89: 37370 | C89: Not back | D89: =MAX((B89-B90)/365, 1) -> 1 | F89: Dr. Koco Eaton | G89: 0
A90: Dave Eiland | B90: 37012 | E90: {=INDEX('TJ List'!O:O,MATCH(A90&B90,'TJ List'!A:A&'TJ List'!B:B,0))} -> Dr. James Andrews
A91: Dedniel Nunez | B91: 45852 | C91: Not yet | D91: =MAX((B91-B92)/365, 1) -> 4.2931507 | F91: Dr. Keith Meister | G91: 0
A92: Dedniel Nunez | B92: 44285 | E92: Dr. Neal ElAttrache
A93: Denny Stark | B93: 39083 | C93: Back | D93: =MAX((B93-B94)/365, 1) -> 1
A94: Denny Stark | B94: 38718 | E94: Unknown
A95: Derek Thompson | B95: 38534 | C95: Not back | D95: =MAX((B95-B96)/365, 1) -> 2.3260274
A96: Derek Thompson | B96: 37685 | E96: Unknown
A97: Doug Brocail | B97: 37500 | C97: Back | D97: =MAX((B97-B98)/365, 1) -> 1.3479452 | F97: Dr. Thomas Mehlhoff | G97: 1
A98: Doug Brocail | B98: 37008 | E98: {=INDEX('TJ List'!O:O,MATCH(A98&B98,'TJ List'!A:A&'TJ List'!B:B,0))} -> Dr. Thomas Mehlhoff
A99: Drew Rasmussen | B99: 42970 | C99: Back | D99: =MAX((B99-B100)/365, 1) -> 1.4027397 | F99: Dr. Keith Meister | G99: 0
A100: Drew Rasmussen | B100: 42458 | E100: Dr. Luis Vela
...

Sheet MLB 2024
A1: 2024 MLB Pitchers Who Have Had TJ Surgery, By Team & Usage | G1: Pitcher Used in 2024 | H1: Team | I1: playerid | J1: TJ | L1: Pitcher on IL | M1: Team | N1: City | O1: playerid | P1: TJ | Q1: Already | S1: Position Player | T1: Team | U1: playerid | W1: Pitcher Used in 2024 | X1: Team | Y1: playerid | Z1: TJ
A2: Team | B2: Pitchers Used | C2: Pitchers | D2: Pitchers Not Used, on IL | E2: Pitchers on IL | G2: Yusei Kikuchi | H2: - - - | I2: 20633 | J2: {=INDEX('TJ List'!B:B,MATCH(I2,'TJ List'!N:N,0),0)} -> #N/A | L2: Drey Jameson | M2: ARI | N2: Arizona | O2: 26260 | P2: {=INDEX('TJ List'!B:B,MATCH(O2,'TJ List'!N:N,0),0)} -> 45170 | Q2: {=IFERROR(INDEX(I:I,MATCH(O2,I:I,0),0),0)} -> 0 | S2: Eddy Alvarez | T2: NYM | U2: 16959 | W2: Andrew Chafin | X2: - - - | Y2: 12988 | Z2: 39973
A3: LAD | B3: =COUNTIFS(H:H,A3,J:J,">0") -> 18 | C3: =IFERROR(__xludf.DUMMYFUNCTION("IF(B3>0,JOIN("", "",TRANSPOSE(INDIRECT(ADDRESS(MATCH(A3,H:H,0),7)&"":""&ADDRESS(MATCH(A3,H:H,0)+B3-1,7)))),"""")"),"Daniel Hudson, Ryan Brasier, Brusdar Graterol, Michael Grove, Brent Honeywell, Dinelson Lamet, Anthony Banda, Michael Kopech, Gus Varland, Ricky Vanasco, James Paxton, Justin Wrobleski, Tyler Glasnow, Edgardo Henriquez, Walker Buehler, Kyle Hurt, River Ry"&"an, Yoshinobu Yamamoto") -> Daniel Hudson, Ryan Brasier, Brusdar Graterol, Michael Grove, Brent Honeywell, Dinelson Lamet, Anthony Banda, Michael Kopech, Gus Varland, Ricky Vanasco, James Paxton, Justin Wrobleski, Tyler Glasnow, Edgardo Henriquez, Walker Buehler, Kyle Hurt, River Ryan, Yoshinobu Yamamoto | D3: =COUNTIFS(M:M,A3,P:P,">0",Q:Q,0) -> 3 | E3: =IFERROR(__xludf.DUMMYFUNCTION("IF(D3>0,JOIN("", "",TRANSPOSE(INDIRECT(ADDRESS(MATCH(A3,M:M,0),12)&"":""&ADDRESS(MATCH(A3,M:M,0)+D3-1,12)))),"""")"),"Dustin May, Tony Gonsolin, Emmet Sheehan") -> Dustin May, Tony Gonsolin, Emmet Sheehan | G3: Jack Flaherty | H3: - - - | I3: 17479 | J3: {=INDEX('TJ List'!B:B,MATCH(I3,'TJ List'!N:N,0),0)} -> #N/A | L3: Huascar Ynoa | M3: ATL | N3: Atlanta | O3: 20468 | P3: {=INDEX('TJ List'!B:B,MATCH(O3,'TJ List'!N:N,0),0)} -> 44811 | Q3: {=IFERROR(INDEX(I:I,MATCH(O3,I:I,0),0),0)} -> 0 | S3: Tucker Barnhart | T3: ARI | U3: 10200 | W3: JT Chargois | X3: - - - | Y3: 13767 | Z3: 41534
A4: NYY | B4: =COUNTIFS(H:H,A4,J:J,">0") -> 18 | C4: =IFERROR(__xludf.DUMMYFUNCTION("IF(B4>0,JOIN("", "",TRANSPOSE(INDIRECT(ADDRESS(MATCH(A4,H:H,0),7)&"":""&ADDRESS(MATCH(A4,H:H,0)+B4-1,7)))),"""")"),"Ron Marinaccio, Clay Holmes, Jonathan Loáisiga, Victor González, Clarke Schmidt, Clayton Beeter, Mark Leiter Jr., Carlos Rodón, Tim Mayza, Tommy Kahnle, Caleb Ferguson, Nick Burdi, Yoendrys Gómez, Luis Gil, Cody Poteet, Scott Effross, Nestor Cortes, Gerri"&"t Cole") -> Ron Marinaccio, Clay Holmes, Jonathan Loáisiga, Victor González, Clarke Schmidt, Clayton Beeter, Mark Leiter Jr., Carlos Rodón, Tim Mayza, Tommy Kahnle, Caleb Ferguson, Nick Burdi, Yoendrys Gómez, Luis Gil, Cody Poteet, Scott Effross, Nestor Cortes, Gerrit Cole | D4: =COUNTIFS(M:M,A4,P:P,">0",Q:Q,0) -> 2 | E4: =IFERROR(__xludf.DUMMYFUNCTION("IF(D4>0,JOIN("", "",TRANSPOSE(INDIRECT(ADDRESS(MATCH(A4,M:M,0),12)&"":""&ADDRESS(MATCH(A4,M:M,0)+D4-1,12)))),"""")"),"JT Brubaker, Lou Trivino") -> JT Brubaker, Lou Trivino | G4: Zach Eflin | H4: - - - | I4: 13774 | J4: {=INDEX('TJ List'!B:B,MATCH(I4,'TJ List'!N:N,0),0)} -> #N/A | L4: Angel Perdomo | M4: ATL | N4: Atlanta | O4: 17759 | P4: {=INDEX('TJ List'!B:B,MATCH(O4,'TJ List'!N:N,0),0)} -> 45205 | Q4: {=IFERROR(INDEX(I:I,MATCH(O4,I:I,0),0),0)} -> 0 | S4: Jake Bauers | T4: MIL | U4: 15194 | W4: Mitch White | X4: - - - | Y4: 19225 | Z4: 41579
A5: COL | B5: =COUNTIFS(H:H,A5,J:J,">0") -> 16 | C5: =IFERROR(__xludf.DUMMYFUNCTION("IF(B5>0,JOIN("", "",TRANSPOSE(INDIRECT(ADDRESS(MATCH(A5,H:H,0),7)&"":""&ADDRESS(MATCH(A5,H:H,0)+B5-1,7)))),"""")"),"Cal Quantrill, Noah Davis, Seth Halvorsen, Josh Rogers, Matt Carasiti, Ty Blach, Peter Lambert, Jalen Beeks, Dakota Hudson, Jaden Hill, John Curtiss, Bradley Blalock, Lucas Gilbreath, Germán Márquez, Antonio Senzatela, Ryan Feltner") -> Cal Quantrill, Noah Davis, Seth Halvorsen, Josh Rogers, Matt Carasiti, Ty Blach, Peter Lambert, Jalen Beeks, Dakota Hudson, Jaden Hill, John Curtiss, Bradley Blalock, Lucas Gilbreath, Germán Márquez, Antonio Senzatela, Ryan Feltner | D5: =COUNTIFS(M:M,A5,P:P,">0",Q:Q,0) -> 0 | E5: =IFERROR(__xludf.DUMMYFUNCTION("IF(D5>0,JOIN("", "",TRANSPOSE(INDIRECT(ADDRESS(MATCH(A5,M:M,0),12)&"":""&ADDRESS(MATCH(A5,M:M,0)+D5-1,12)))),"""")"),"") | G5: Lucas Erceg | H5: - - - | I5: 19360 | J5: {=INDEX('TJ List'!B:B,MATCH(I5,'TJ List'!N:N,0),0)} -> #N/A | L5: Félix Bautista | M5: BAL | N5: Baltimore | O5: 20666 | P5: {=INDEX('TJ List'!B:B,MATCH(O5,'TJ List'!N:N,0),0)} -> 45208 | Q5: {=IFERROR(INDEX(I:I,MATCH(O5,I:I,0),0),0)} -> 0 | S5: David Bote | T5: CHC | U5: 14593 | W5: Cole Irvin | X5: - - - | Y5: 19244 | Z5: 41673
A6: DET | B6: =COUNTIFS(H:H,A6,J:J,">0") -> 16 | C6: =IFERROR(__xludf.DUMMYFUNCTION("IF(B6>0,JOIN("", "",TRANSPOSE(INDIRECT(ADDRESS(MATCH(A6,H:H,0),7)&"":""&ADDRESS(MATCH(A6,H:H,0)+B6-1,7)))),"""")"),"Andrew Chafin, Will Vest, Tarik Skubal, Shelby Miller, Jason Foley, Tyler Holton, Mason Englert, Brant Hurter, Joey Wentz, Ricky Vanasco, Alex Faedo, Brenan Hanifee, Kenta Maeda, Sean Guenther, Casey Mize, Reese Olson") -> Andrew Chafin, Will Vest, Tarik Skubal, Shelby Miller, Jason Foley, Tyler Holton, Mason Englert, Brant Hurter, Joey Wentz, Ricky Vanasco, Alex Faedo, Brenan Hanifee, Kenta Maeda, Sean Guenther, Casey Mize, Reese Olson | D6: =COUNTIFS(M:M,A6,P:P,">0",Q:Q,0) -> 1 | E6: =IFERROR(__xludf.DUMMYFUNCTION("IF(D6>0,JOIN("", "",TRANSPOSE(INDIRECT(ADDRESS(MATCH(A6,M:M,0),12)&"":""&ADDRESS(MATCH(A6,M:M,0)+D6-1,12)))),"""")"),"Sawyer Gipson-Long") -> Sawyer Gipson-Long | G6: Tanner Scott | H6: - - - | I6: 17586 | J6: {=INDEX('TJ List'!B:B,MATCH(I6,'TJ List'!N:N,0),0)} -> #N/A | L6: Lucas Giolito | M6: BOS | N6: Boston | O6: 15474 | P6: {=INDEX('TJ List'!B:B,MATCH(O6,'TJ List'!N:N,0),0)} -> 41152 | Q6: {=IFERROR(INDEX(I:I,MATCH(O6,I:I,0),0),0)} -> 0 | S6: Vidal Bruján | T6: MIA | U6: 20536 | W6: Martín Pérez | X6: - - - | Y6: 6902 | Z6: 41778
A7: CHW | B7: =COUNTIFS(H:H,A7,J:J,">0") -> 17 | C7: =IFERROR(__xludf.DUMMYFUNCTION("IF(B7>0,JOIN("", "",TRANSPOSE(INDIRECT(ADDRESS(MATCH(A7,H:H,0),7)&"":""&ADDRESS(MATCH(A7,H:H,0)+B7-1,7)))),"""")"),"Erick Fedde, Chris Flexen, Steven Wilson, Sean Burke, Michael Kopech, Chad Kuhl, Gus Varland, John Brebbia, Justin Anderson, Mike Clevinger, Jake Eder, Garrett Crochet, Matt Foster, Davis Martin, Jonathan Cannon, Michael Soroka, Jared Shuster") -> Erick Fedde, Chris Flexen, Steven Wilson, Sean Burke, Michael Kopech, Chad Kuhl, Gus Varland, John Brebbia, Justin Anderson, Mike Clevinger, Jake Eder, Garrett Crochet, Matt Foster, Davis Martin, Jonathan Cannon, Michael Soroka, Jared Shuster | D7: =COUNTIFS(M:M,A7,P:P,">0",Q:Q,0) -> 2 | E7: =IFERROR(__xludf.DUMMYFUNCTION("IF(D7>0,JOIN("", "",TRANSPOSE(INDIRECT(ADDRESS(MATCH(A7,M:M,0),12)&"":""&ADDRESS(MATCH(A7,M:M,0)+D7-1,12)))),"""")"),"Jimmy Lambert, Jesse Scholtens") -> Jimmy Lambert, Jesse Scholtens | G7: Frankie Montas | H7: - - - | I7: 14309 | J7: {=INDEX('TJ List'!B:B,MATCH(I7,'TJ List'!N:N,0),0)} -> 45909 | L7: Bryan Mata | M7: BOS | N7: Boston | O7: sa917784 | P7: {=INDEX('TJ List'!B:B,MATCH(O7,'TJ List'!N:N,0),0)} -> 44299 | Q7: {=IFERROR(INDEX(I:I,MATCH(O7,I:I,0),0),0)} -> 0 | S7: Oswaldo Cabrera | T7: NYY | U7: 21707 | W7: Erick Fedde | X7: - - - | Y7: 17425 | Z7: 41793
A8: PIT | B8: =COUNTIFS(H:H,A8,J:J,">0") -> 14 | C8: =IFERROR(__xludf.DUMMYFUNCTION("IF(B8>0,JOIN("", "",TRANSPOSE(INDIRECT(ADDRESS(MATCH(A8,H:H,0),7)&"":""&ADDRESS(MATCH(A8,H:H,0)+B8-1,7)))),"""")"),"Ryan Borucki, Justin Bruihl, Martín Pérez, Domingo Germán, Brady Feigl, Marco Gonzales, Brent Honeywell, Colin Holderman, Ben Heller, Jose E. Hernandez, Joey Wentz, Jalen Beeks, Daulton Jefferies, Mike Burrows") -> Ryan Borucki, Justin Bruihl, Martín Pérez, Domingo Germán, Brady Feigl, Marco Gonzales, Brent Honeywell, Colin Holderman, Ben Heller, Jose E. Hernandez, Joey Wentz, Jalen Beeks, Daulton Jefferies, Mike Burrows | D8: =COUNTIFS(M:M,A8,P:P,">0",Q:Q,0) -> 2 | E8: =IFERROR(__xludf.DUMMYFUNCTION("IF(D8>0,JOIN("", "",TRANSPOSE(INDIRECT(ADDRESS(MATCH(A8,M:M,0),12)&"":""&ADDRESS(MATCH(A8,M:M,0)+D8-1,12)))),"""")"),"Johan Oviedo, Dauri Moreta") -> Johan Oviedo, Dauri Moreta | G8: Jason Adam | H8: - - - | I8: 11861 | J8: {=INDEX('TJ List'!B:B,MATCH(I8,'TJ List'!N:N,0),0)} -> #N/A | L8: Liam Hendriks | M8: BOS | N8: Boston | O8: 3548 | P8: {=INDEX('TJ List'!B:B,MATCH(O8,'TJ List'!N:N,0),0)} -> 45140 | Q8: {=IFERROR(INDEX(I:I,MATCH(O8,I:I,0),0),0)} -> 0 | S8: Diego Castillo | T8: MIN | U8: 17496 | W8: Cole Sulser | X8: - - - | Y8: 15256 | Z8: 42005
A9: TEX | B9: =COUNTIFS(H:H,A9,J:J,">0") -> 14 | C9: =IFERROR(__xludf.DUMMYFUNCTION("IF(B9>0,JOIN("", "",TRANSPOSE(INDIRECT(ADDRESS(MATCH(A9,H:H,0),7)&"":""&ADDRESS(MATCH(A9,H:H,0)+B9-1,7)))),"""")"),"Andrew Chafin, Andrew Heaney, Nathan Eovaldi, Daniel Robert, Dane Dunning, Owen White, David Robertson, Matt Festa, Kirby Yates, José Leclerc, Jonathan Hernández, Tyler Mahle, Kumar Rocker, Jacob deGrom") -> Andrew Chafin, Andrew Heaney, Nathan Eovaldi, Daniel Robert, Dane Dunning, Owen White, David Robertson, Matt Festa, Kirby Yates, José Leclerc, Jonathan Hernández, Tyler Mahle, Kumar Rocker, Jacob deGrom | D9: =COUNTIFS(M:M,A9,P:P,">0",Q:Q,0) -> 1 | E9: =IFERROR(__xludf.DUMMYFUNCTION("IF(D9>0,JOIN("", "",TRANSPOSE(INDIRECT(ADDRESS(MATCH(A9,M:M,0),12)&"":""&ADDRESS(MATCH(A9,M:M,0)+D9-1,12)))),"""")"),"Carson Coleman") -> Carson Coleman | G9: Dennis Santana | H9: - - - | I9: 17878 | J9: {=INDEX('TJ List'!B:B,MATCH(I9,'TJ List'!N:N,0),0)} -> #N/A | L9: Chris Murphy | M9: BOS | N9: Boston | O9: 26214 | P9: {=INDEX('TJ List'!B:B,MATCH(O9,'TJ List'!N:N,0),0)} -> 45392 | Q9: {=IFERROR(INDEX(I:I,MATCH(O9,I:I,0),0),0)} -> 0 | S9: Willi Castro | T9: MIN | U9: 17338 | W9: Burch Smith | X9: - - - | Y9: 12784 | Z9: 42101
A10: ATL | B10: =COUNTIFS(H:H,A10,J:J,">0") -> 13 | C10: =IFERROR(__xludf.DUMMYFUNCTION("IF(B10>0,JOIN("", "",TRANSPOSE(INDIRECT(ADDRESS(MATCH(A10,H:H,0),7)&"":""&ADDRESS(MATCH(A10,H:H,0)+B10-1,7)))),"""")"),"Charlie Morton, Max Fried, A.J. Minter, Aaron Bummer, Spencer Strider, Chris Sale, John Brebbia, Spencer Schwellenbach, Daysbel Hernández, Luke Jackson, Tyler Matzek, Ray Kerr, Reynaldo López") -> Charlie Morton, Max Fried, A.J. Minter, Aaron Bummer, Spencer Strider, Chris Sale, John Brebbia, Spencer Schwellenbach, Daysbel Hernández, Luke Jackson, Tyler Matzek, Ray Kerr, Reynaldo López | D10: =COUNTIFS(M:M,A10,P:P,">0",Q:Q,0) -> 2 | E10: =IFERROR(__xludf.DUMMYFUNCTION("IF(D10>0,JOIN("", "",TRANSPOSE(INDIRECT(ADDRESS(MATCH(A10,M:M,0),12)&"":""&ADDRESS(MATCH(A10,M:M,0)+D10-1,12)))),"""")"),"Huascar Ynoa, Angel Perdomo") -> Huascar Ynoa, Angel Perdomo | G10: Carlos Estévez | H10: - - - | I10: 14542 | J10: {=INDEX('TJ List'!B:B,MATCH(I10,'TJ List'!N:N,0),0)} -> #N/A | L10: Jimmy Lambert | M10: CHW | N10: Chicago | O10: 19541 | P10: {=INDEX('TJ List'!B:B,MATCH(O10,'TJ List'!N:N,0),0)} -> 43641 | Q10: {=IFERROR(INDEX(I:I,MATCH(O10,I:I,0),0),0)} -> 0 | S10: Kody Clemens | T10: PHI | U10: 20572 | W10: Bryan Hoeing | X10: - - - | Y10: 26304 | Z10: 42156
A11: CIN | B11: =COUNTIFS(H:H,A11,J:J,">0") -> 12 | C11: =IFERROR(__xludf.DUMMYFUNCTION("IF(B11>0,JOIN("", "",TRANSPOSE(INDIRECT(ADDRESS(MATCH(A11,H:H,0),7)&"":""&ADDRESS(MATCH(A11,H:H,0)+B11-1,7)))),"""")"),"Casey Kelly, Alexis Díaz, Brandon Leibrandt, Brent Suter, Yosver Zulueta, Hunter Greene, Casey Legumina, Lyon Richardson, Tejay Antone, Justin Wilson, Brandon Williamson, Julian Aguiar") -> Casey Kelly, Alexis Díaz, Brandon Leibrandt, Brent Suter, Yosver Zulueta, Hunter Greene, Casey Legumina, Lyon Richardson, Tejay Antone, Justin Wilson, Brandon Williamson, Julian Aguiar | D11: =COUNTIFS(M:M,A11,P:P,">0",Q:Q,0) -> 0 | E11: =IFERROR(__xludf.DUMMYFUNCTION("IF(D11>0,JOIN("", "",TRANSPOSE(INDIRECT(ADDRESS(MATCH(A11,M:M,0),12)&"":""&ADDRESS(MATCH(A11,M:M,0)+D11-1,12)))),"""")"),"") | G11: Tanner Banks | H11: - - - | I11: 16990 | J11: {=INDEX('TJ List'!B:B,MATCH(I11,'TJ List'!N:N,0),0)} -> #N/A | L11: Jesse Scholtens | M11: CHW | N11: Chicago | O11: 19205 | P11: {=INDEX('TJ List'!B:B,MATCH(O11,'TJ List'!N:N,0),0)} -> 45352 | Q11: {=IFERROR(INDEX(I:I,MATCH(O11,I:I,0),0),0)} -> 0 | S11: Ernie Clement | T11: TOR | U11: 20352 | W11: Hunter Harvey | X11: - - - | Y11: 15507 | Z11: 42577
A12: LAA | B12: =COUNTIFS(H:H,A12,J:J,">0") -> 12 | C12: =IFERROR(__xludf.DUMMYFUNCTION("IF(B12>0,JOIN("", "",TRANSPOSE(INDIRECT(ADDRESS(MATCH(A12,H:H,0),7)&"":""&ADDRESS(MATCH(A12,H:H,0)+B12-1,7)))),"""")"),"Hunter Strickland, Matt Moore, José Cisnero, Ryan Miller, Zach Plesac, Johnny Cueto, Davis Daniel, Aaron Hicks, Ben Joyce, José Soriano, José Quijada, Zac Kristofak") -> Hunter Strickland, Matt Moore, José Cisnero, Ryan Miller, Zach Plesac, Johnny Cueto, Davis Daniel, Aaron Hicks, Ben Joyce, José Soriano, José Quijada, Zac Kristofak | D12: =COUNTIFS(M:M,A12,P:P,">0",Q:Q,0) -> 1 | E12: =IFERROR(__xludf.DUMMYFUNCTION("IF(D12>0,JOIN("", "",TRANSPOSE(INDIRECT(ADDRESS(MATCH(A12,M:M,0),12)&"":""&ADDRESS(MATCH(A12,M:M,0)+D12-1,12)))),"""")"),"Robert Stephenson") -> Robert Stephenson | G12: Aaron Civale | H12: - - - | I12: 19479 | J12: {=INDEX('TJ List'!B:B,MATCH(I12,'TJ List'!N:N,0),0)} -> #N/A | L12: Christian Roa | M12: CIN | N12: Cincinnati | O12: sa3014477 | P12: {=INDEX('TJ List'!B:B,MATCH(O12,'TJ List'!N:N,0),0)} -> #N/A | Q12: {=IFERROR(INDEX(I:I,MATCH(O12,I:I,0),0),0)} -> 0 | S12: Brandon Crawford | T12: STL | U12: 5343 | W12: Yimi García | X12: - - - | Y12: 12095 | Z12: 42668
A13: MIA | B13: =COUNTIFS(H:H,A13,J:J,">0") -> 13 | C13: =IFERROR(__xludf.DUMMYFUNCTION("IF(B13>0,JOIN("", "",TRANSPOSE(INDIRECT(ADDRESS(MATCH(A13,H:H,0),7)&"":""&ADDRESS(MATCH(A13,H:H,0)+B13-1,7)))),"""")"),"JT Chargois, Burch Smith, Bryan Hoeing, Kent Emanuel, Jesús Luzardo, Braxton Garrett, A.J. Puk, Yonny Chirinos, Lake Bachar, Vladimir Gutierrez, Max Meyer, Anthony Bender, Calvin Faucher") -> JT Chargois, Burch Smith, Bryan Hoeing, Kent Emanuel, Jesús Luzardo, Braxton Garrett, A.J. Puk, Yonny Chirinos, Lake Bachar, Vladimir Gutierrez, Max Meyer, Anthony Bender, Calvin Faucher | D13: =COUNTIFS(M:M,A13,P:P,">0",Q:Q,0) -> 2 | E13: =IFERROR(__xludf.DUMMYFUNCTION("IF(D13>0,JOIN("", "",TRANSPOSE(INDIRECT(ADDRESS(MATCH(A13,M:M,0),12)&"":""&ADDRESS(MATCH(A13,M:M,0)+D13-1,12)))),"""")"),"Sandy Alcantara, Eury Pérez") -> Sandy Alcantara, Eury Pérez | G13: Trevor Rogers | H13: - - - | I13: 22286 | J13: {=INDEX('TJ List'!B:B,MATCH(I13,'TJ List'!N:N,0),0)} -> #N/A | L13: Trevor Stephan | M13: CLE | N13: Cleveland | O13: 19932 | P13: {=INDEX('TJ List'!B:B,MATCH(O13,'TJ List'!N:N,0),0)} -> 45378 | Q13: {=IFERROR(INDEX(I:I,MATCH(O13,I:I,0),0),0)} -> 0 | S13: Kyle Farmer | T13: MIN | U13: 14813 | W13: Nick Robertson | X13: - - - | Y13: 26226 | Z13: 42736
A14: NYM | B14: =COUNTIFS(H:H,A14,J:J,">0") -> 15 | C14: =IFERROR(__xludf.DUMMYFUNCTION("IF(B14>0,JOIN("", "",TRANSPOSE(INDIRECT(ADDRESS(MATCH(A14,H:H,0),7)&"":""&ADDRESS(MATCH(A14,H:H,0)+B14-1,7)))),"""")"),"Cole Sulser, Adam Ottavino, Adrian Houser, Luis Severino, Matt Festa, Dedniel Núñez, Ty Adcock, Joey Lucchesi, Sean Reid-Foley, Brooks Raley, Drew Smith, Christian Scott, Sean Manaea, David Peterson, Tylor Megill") -> Cole Sulser, Adam Ottavino, Adrian Houser, Luis Severino, Matt Festa, Dedniel Núñez, Ty Adcock, Joey Lucchesi, Sean Reid-Foley, Brooks Raley, Drew Smith, Christian Scott, Sean Manaea, David Peterson, Tylor Megill | D14: =COUNTIFS(M:M,A14,P:P,">0",Q:Q,0) -> 0 | E14: =IFERROR(__xludf.DUMMYFUNCTION("IF(D14>0,JOIN("", "",TRANSPOSE(INDIRECT(ADDRESS(MATCH(A14,M:M,0),12)&"":""&ADDRESS(MATCH(A14,M:M,0)+D14-1,12)))),"""")"),"") | G14: Jakob Junis | H14: - - - | I14: 13619 | J14: {=INDEX('TJ List'!B:B,MATCH(I14,'TJ List'!N:N,0),0)} -> #N/A | L14: James Karinchak | M14: CLE | N14: Cleveland | O14: 20151 | P14: {=INDEX('TJ List'!B:B,MATCH(O14,'TJ List'!N:N,0),0)} -> #N/A | Q14: {=IFERROR(INDEX(I:I,MATCH(O14,I:I,0),0),0)} -> 0 | S14: Tyler Fitzgerald | T14: SFG | U14: 26208 | W14: Brent Honeywell | X14: - - - | Y14: 16466 | Z14: 43158
A15: BAL | B15: =COUNTIFS(H:H,A15,J:J,">0") -> 12 | C15: =IFERROR(__xludf.DUMMYFUNCTION("IF(B15>0,JOIN("", "",TRANSPOSE(INDIRECT(ADDRESS(MATCH(A15,H:H,0),7)&"":""&ADDRESS(MATCH(A15,H:H,0)+B15-1,7)))),"""")"),"Albert Suárez, Danny Coulombe, Cole Irvin, Matt Krook, Jacob Webb, Burch Smith, Tyler Wells, Seranthony Domínguez, Matt Bowman, John Means, Kyle Bradish, Corbin Burnes") -> Albert Suárez, Danny Coulombe, Cole Irvin, Matt Krook, Jacob Webb, Burch Smith, Tyler Wells, Seranthony Domínguez, Matt Bowman, John Means, Kyle Bradish, Corbin Burnes | D15: =COUNTIFS(M:M,A15,P:P,">0",Q:Q,0) -> 1 | E15: =IFERROR(__xludf.DUMMYFUNCTION("IF(D15>0,JOIN("", "",TRANSPOSE(INDIRECT(ADDRESS(MATCH(A15,M:M,0),12)&"":""&ADDRESS(MATCH(A15,M:M,0)+D15-1,12)))),"""")"),"Félix Bautista") -> Félix Bautista | G15: Nick Mears | H15: - - - | I15: 25376 | J15: {=INDEX('TJ List'!B:B,MATCH(I15,'TJ List'!N:N,0),0)} -> #N/A | L15: Daniel Bard | M15: COL | N15: Colorado | O15: 7115 | P15: {=INDEX('TJ List'!B:B,MATCH(O15,'TJ List'!N:N,0),0)} -> #N/A | Q15: {=IFERROR(INDEX(I:I,MATCH(O15,I:I,0),0),0)} -> 0 | S15: Luis Guillorme | T15: - - - | U15: 16451 | W15: A.J. Puk | X15: - - - | Y15: 19343 | Z15: 43200
A16: CHC | B16: =COUNTIFS(H:H,A16,J:J,">0") -> 12 | C16: =IFERROR(__xludf.DUMMYFUNCTION("IF(B16>0,JOIN("", "",TRANSPOSE(INDIRECT(ADDRESS(MATCH(A16,H:H,0),7)&"":""&ADDRESS(MATCH(A16,H:H,0)+B16-1,7)))),"""")"),"Keegan Thompson, Drew Smyly, Justin Steele, Julian Merryweather, Mark Leiter Jr., Ben Brown, Jameson Taillon, Trey Wingenter, Richard Lovelady, Ethan Roberts, Adbert Alzolay, Shota Imanaga") -> Keegan Thompson, Drew Smyly, Justin Steele, Julian Merryweather, Mark Leiter Jr., Ben Brown, Jameson Taillon, Trey Wingenter, Richard Lovelady, Ethan Roberts, Adbert Alzolay, Shota Imanaga | D16: =COUNTIFS(M:M,A16,P:P,">0",Q:Q,0) -> 0 | E16: =IFERROR(__xludf.DUMMYFUNCTION("IF(D16>0,JOIN("", "",TRANSPOSE(INDIRECT(ADDRESS(MATCH(A16,M:M,0),12)&"":""&ADDRESS(MATCH(A16,M:M,0)+D16-1,12)))),"""")"),"") | G16: Michael Lorenzen | H16: - - - | I16: 14843 | J16: {=INDEX('TJ List'!B:B,MATCH(I16,'TJ List'!N:N,0),0)} -> #N/A | L16: Sawyer Gipson-Long | M16: DET | N16: Detroit | O16: 26048 | P16: {=INDEX('TJ List'!B:B,MATCH(O16,'TJ List'!N:N,0),0)} -> 45404 | Q16: {=IFERROR(INDEX(I:I,MATCH(O16,I:I,0),0),0)} -> 0 | S16: Garrett Hampson | T16: KCR | U16: 19262 | W16: Michael Kopech | X16: - - - | Y16: 17282 | Z16: 43361
A17: CLE | B17: =COUNTIFS(H:H,A17,J:J,">0") -> 12 | C17: =IFERROR(__xludf.DUMMYFUNCTION("IF(B17>0,JOIN("", "",TRANSPOSE(INDIRECT(ADDRESS(MATCH(A17,H:H,0),7)&"":""&ADDRESS(MATCH(A17,H:H,0)+B17-1,7)))),"""")"),"Carlos Carrasco, Scott Barlow, Alex Cobb, Peter Strzelecki, Sam Hentges, Pedro Avila, Tyler Beede, Erik Sabrowski, Anthony Gose, Matthew Boyd, Shane Bieber, Tanner Bibee") -> Carlos Carrasco, Scott Barlow, Alex Cobb, Peter Strzelecki, Sam Hentges, Pedro Avila, Tyler Beede, Erik Sabrowski, Anthony Gose, Matthew Boyd, Shane Bieber, Tanner Bibee | D17: =COUNTIFS(M:M,A17,P:P,">0",Q:Q,0) -> 1 | E17: =IFERROR(__xludf.DUMMYFUNCTION("IF(D17>0,JOIN("", "",TRANSPOSE(INDIRECT(ADDRESS(MATCH(A17,M:M,0),12)&"":""&ADDRESS(MATCH(A17,M:M,0)+D17-1,12)))),"""")"),"Trevor Stephan") -> Trevor Stephan | G17: Jesus Tinoco | H17: - - - | I17: 16300 | J17: {=INDEX('TJ List'!B:B,MATCH(I17,'TJ List'!N:N,0),0)} -> #N/A | L17: Brendan White | M17: DET | N17: Detroit | O17: 26024 | P17: {=INDEX('TJ List'!B:B,MATCH(O17,'TJ List'!N:N,0),0)} -> #N/A | Q17: {=IFERROR(INDEX(I:I,MATCH(O17,I:I,0),0),0)} -> 0 | S17: Austin Hedges | T17: CLE | U17: 12976 | W17: Mark Leiter Jr. | X17: - - - | Y17: 15551 | Z17: 43536
A18: PHI | B18: =COUNTIFS(H:H,A18,J:J,">0") -> 11 | C18: =IFERROR(__xludf.DUMMYFUNCTION("IF(B18>0,JOIN("", "",TRANSPOSE(INDIRECT(ADDRESS(MATCH(A18,H:H,0),7)&"":""&ADDRESS(MATCH(A18,H:H,0)+B18-1,7)))),"""")"),"Matt Strahm, Jeff Hoffman, Zack Wheeler, Taijuan Walker, Michael Mercado, Seranthony Domínguez, Max Lazar, Spencer Turnbull, Tyler Phillips, Seth Johnson, Luis F. Ortiz") -> Matt Strahm, Jeff Hoffman, Zack Wheeler, Taijuan Walker, Michael Mercado, Seranthony Domínguez, Max Lazar, Spencer Turnbull, Tyler Phillips, Seth Johnson, Luis F. Ortiz | D18: =COUNTIFS(M:M,A18,P:P,">0",Q:Q,0) -> 0 | E18: =IFERROR(__xludf.DUMMYFUNCTION("IF(D18>0,JOIN("", "",TRANSPOSE(INDIRECT(ADDRESS(MATCH(A18,M:M,0),12)&"":""&ADDRESS(MATCH(A18,M:M,0)+D18-1,12)))),"""")"),"") | G18: Shawn Armstrong | H18: - - - | I18: 12857 | J18: {=INDEX('TJ List'!B:B,MATCH(I18,'TJ List'!N:N,0),0)} -> #N/A | L18: Kendall Graveman | M18: HOU | N18: Houston | O18: 15514 | P18: {=INDEX('TJ List'!B:B,MATCH(O18,'TJ List'!N:N,0),0)} -> 43311 | Q18: {=IFERROR(INDEX(I:I,MATCH(O18,I:I,0),0),0)} -> 0 | S18: Tyler Heineman | T18: TOR | U18: 13897 | W18: Gus Varland | X18: - - - | Y18: 24737 | Z18: 43678
A19: SDP | B19: =COUNTIFS(H:H,A19,J:J,">0") -> 11 | C19: =IFERROR(__xludf.DUMMYFUNCTION("IF(B19>0,JOIN("", "",TRANSPOSE(INDIRECT(ADDRESS(MATCH(A19,H:H,0),7)&"":""&ADDRESS(MATCH(A19,H:H,0)+B19-1,7)))),"""")"),"Martín Pérez, Dylan Cease, Yu Darvish, Bryan Hoeing, Jhony Brito, Robert Suarez, Jeremiah Estrada, Tom Cosgrove, Pedro Avila, Adrian Morejon, Joe Musgrove") -> Martín Pérez, Dylan Cease, Yu Darvish, Bryan Hoeing, Jhony Brito, Robert Suarez, Jeremiah Estrada, Tom Cosgrove, Pedro Avila, Adrian Morejon, Joe Musgrove | D19: =COUNTIFS(M:M,A19,P:P,">0",Q:Q,0) -> 1 | E19: =IFERROR(__xludf.DUMMYFUNCTION("IF(D19>0,JOIN("", "",TRANSPOSE(INDIRECT(ADDRESS(MATCH(A19,M:M,0),12)&"":""&ADDRESS(MATCH(A19,M:M,0)+D19-1,12)))),"""")"),"Luis Patiño") -> Luis Patiño | G19: Huascar Brazobán | H19: - - - | I19: 6107 | J19: {=INDEX('TJ List'!B:B,MATCH(I19,'TJ List'!N:N,0),0)} -> #N/A | L19: Lance McCullers Jr. | M19: HOU | N19: Houston | O19: 14120 | P19: {=INDEX('TJ List'!B:B,MATCH(O19,'TJ List'!N:N,0),0)} -> 43410 | Q19: {=IFERROR(INDEX(I:I,MATCH(O19,I:I,0),0),0)} -> 0 | S19: David Hensley | T19: MIA | U19: 25111 | W19: Pedro Avila | X19: - - - | Y19: 18864 | Z19: 43709
A20: TOR | B20: =COUNTIFS(H:H,A20,J:J,">0") -> 11 | C20: =IFERROR(__xludf.DUMMYFUNCTION("IF(B20>0,JOIN("", "",TRANSPOSE(INDIRECT(ADDRESS(MATCH(A20,H:H,0),7)&"":""&ADDRESS(MATCH(A20,H:H,0)+B20-1,7)))),"""")"),"Tommy Nance, Mitch White, Jordan Romano, Chris Bassitt, Yimi García, Nick Robertson, Zach Pop, Ryan Burr, Tim Mayza, Chad Green, Alek Manoah") -> Tommy Nance, Mitch White, Jordan Romano, Chris Bassitt, Yimi García, Nick Robertson, Zach Pop, Ryan Burr, Tim Mayza, Chad Green, Alek Manoah | D20: =COUNTIFS(M:M,A20,P:P,">0",Q:Q,0) -> 0 | E20: =IFERROR(__xludf.DUMMYFUNCTION("IF(D20>0,JOIN("", "",TRANSPOSE(INDIRECT(ADDRESS(MATCH(A20,M:M,0),12)&"":""&ADDRESS(MATCH(A20,M:M,0)+D20-1,12)))),"""")"),"") | G20: Michael Tonkin | H20: - - - | I20: 10315 | J20: {=INDEX('TJ List'!B:B,MATCH(I20,'TJ List'!N:N,0),0)} -> #N/A | L20: Luis Garcia | M20: HOU | N20: Houston | O20: 23735 | P20: {=INDEX('TJ List'!B:B,MATCH(O20,'TJ List'!N:N,0),0)} -> 45931 | Q20: {=IFERROR(INDEX(I:I,MATCH(O20,I:I,0),0),0)} -> 0 | S20: Enrique Hernández | T20: LAD | U20: 10472 | W20: Tim Mayza | X20: - - - | Y20: 15042 | Z20: 43726
A21: HOU | B21: =COUNTIFS(H:H,A21,J:J,">0") -> 11 | C21: =IFERROR(__xludf.DUMMYFUNCTION("IF(B21>0,JOIN("", "",TRANSPOSE(INDIRECT(ADDRESS(MATCH(A21,H:H,0),7)&"":""&ADDRESS(MATCH(A21,H:H,0)+B21-1,7)))),"""")"),"J.P. France, Nick Hernandez, Rafael Montero, Alex Speas, Caleb Ferguson, Justin Verlander, Blair Henley, Forrest Whitley, Bryan King, Cristian Javier, Framber Valdez") -> J.P. France, Nick Hernandez, Rafael Montero, Alex Speas, Caleb Ferguson, Justin Verlander, Blair Henley, Forrest Whitley, Bryan King, Cristian Javier, Framber Valdez | D21: =COUNTIFS(M:M,A21,P:P,">0",Q:Q,0) -> 5 | E21: =IFERROR(__xludf.DUMMYFUNCTION("IF(D21>0,JOIN("", "",TRANSPOSE(INDIRECT(ADDRESS(MATCH(A21,M:M,0),12)&"":""&ADDRESS(MATCH(A21,M:M,0)+D21-1,12)))),"""")"),"Kendall Graveman, Lance McCullers Jr., Luis Garcia, Penn Murfee, José Urquidy") -> Kendall Graveman, Lance McCullers Jr., Luis Garcia, Penn Murfee, José Urquidy | G21: Dylan Floro | H21: - - - | I21: 13394 | J21: {=INDEX('TJ List'!B:B,MATCH(I21,'TJ List'!N:N,0),0)} -> #N/A | L21: Penn Murfee | M21: HOU | N21: Houston | O21: 25174 | P21: {=INDEX('TJ List'!B:B,MATCH(O21,'TJ List'!N:N,0),0)} -> 45108 | Q21: {=IFERROR(INDEX(I:I,MATCH(O21,I:I,0),0),0)} -> 0 | S21: Aaron Hicks | T21: LAA | U21: 5297 | W21: Matt Festa | X21: - - - | Y21: 19330 | Z21: 43895
A22: ARI | B22: =COUNTIFS(H:H,A22,J:J,">0") -> 11 | C22: =IFERROR(__xludf.DUMMYFUNCTION("IF(B22>0,JOIN("", "",TRANSPOSE(INDIRECT(ADDRESS(MATCH(A22,H:H,0),7)&"":""&ADDRESS(MATCH(A22,H:H,0)+B22-1,7)))),"""")"),"Scott McGough, Ryan Thompson, Joe Mantiply, A.J. Puk, Jordan Montgomery, Matt Bowman, Andrew Saalfrank, Justin Martinez, Humberto Castellanos, Brandon Pfaadt, Zac Gallen") -> Scott McGough, Ryan Thompson, Joe Mantiply, A.J. Puk, Jordan Montgomery, Matt Bowman, Andrew Saalfrank, Justin Martinez, Humberto Castellanos, Brandon Pfaadt, Zac Gallen | D22: =COUNTIFS(M:M,A22,P:P,">0",Q:Q,0) -> 1 | E22: =IFERROR(__xludf.DUMMYFUNCTION("IF(D22>0,JOIN("", "",TRANSPOSE(INDIRECT(ADDRESS(MATCH(A22,M:M,0),12)&"":""&ADDRESS(MATCH(A22,M:M,0)+D22-1,12)))),"""")"),"Drey Jameson") -> Drey Jameson | G22: Tyson Miller | H22: - - - | I22: 19976 | J22: {=INDEX('TJ List'!B:B,MATCH(I22,'TJ List'!N:N,0),0)} -> #N/A | L22: José Urquidy | M22: HOU | N22: Houston | O22: 18413 | P22: {=INDEX('TJ List'!B:B,MATCH(O22,'TJ List'!N:N,0),0)} -> 45448 | Q22: {=IFERROR(INDEX(I:I,MATCH(O22,I:I,0),0),0)} -> 0 | S22: Grae Kessinger | T22: HOU | U22: 25813 | W22: Joey Wentz | X22: - - - | Y22: 19962 | Z22: 43907
A23: BOS | B23: =COUNTIFS(H:H,A23,J:J,">0") -> 10 | C23: =IFERROR(__xludf.DUMMYFUNCTION("IF(B23>0,JOIN("", "",TRANSPOSE(INDIRECT(ADDRESS(MATCH(A23,H:H,0),7)&"":""&ADDRESS(MATCH(A23,H:H,0)+B23-1,7)))),"""")"),"Cam Booser, Rich Hill, Bailey Horn, Zach Penrod, Garrett Whitlock, Kutter Crawford, Zack Kelly, Trey Wingenter, James Paxton, Tanner Houck") -> Cam Booser, Rich Hill, Bailey Horn, Zach Penrod, Garrett Whitlock, Kutter Crawford, Zack Kelly, Trey Wingenter, James Paxton, Tanner Houck | D23: =COUNTIFS(M:M,A23,P:P,">0",Q:Q,0) -> 4 | E23: =IFERROR(__xludf.DUMMYFUNCTION("IF(D23>0,JOIN("", "",TRANSPOSE(INDIRECT(ADDRESS(MATCH(A23,M:M,0),12)&"":""&ADDRESS(MATCH(A23,M:M,0)+D23-1,12)))),"""")"),"Lucas Giolito, Bryan Mata, Liam Hendriks, Chris Murphy") -> Lucas Giolito, Bryan Mata, Liam Hendriks, Chris Murphy | G23: Tim Hill | H23: - - - | I23: 16814 | J23: {=INDEX('TJ List'!B:B,MATCH(I23,'TJ List'!N:N,0),0)} -> #N/A | L23: Bennett Sousa | M23: HOU | N23: Houston | O23: 21345 | P23: {=INDEX('TJ List'!B:B,MATCH(O23,'TJ List'!N:N,0),0)} -> #N/A | Q23: {=IFERROR(INDEX(I:I,MATCH(O23,I:I,0),0),0)} -> 0 | S23: Isiah Kiner-Falefa | T23: TOR | U23: 16512 | W23: John Brebbia | X23: - - - | Y23: 12777 | Z23: 43990
A24: MIL | B24: =COUNTIFS(H:H,A24,J:J,">0") -> 9 | C24: =IFERROR(__xludf.DUMMYFUNCTION("IF(B24>0,JOIN("", "",TRANSPOSE(INDIRECT(ADDRESS(MATCH(A24,H:H,0),7)&"":""&ADDRESS(MATCH(A24,H:H,0)+B24-1,7)))),"""")"),"Trevor Megill, Mitch White, Colin Rea, Devin Williams, Kevin Herget, Bradley Blalock, Joe Ross, Wade Miley, Robert Gasser") -> Trevor Megill, Mitch White, Colin Rea, Devin Williams, Kevin Herget, Bradley Blalock, Joe Ross, Wade Miley, Robert Gasser | D24: =COUNTIFS(M:M,A24,P:P,">0",Q:Q,0) -> 0 | E24: =IFERROR(__xludf.DUMMYFUNCTION("IF(D24>0,JOIN("", "",TRANSPOSE(INDIRECT(ADDRESS(MATCH(A24,M:M,0),12)&"":""&ADDRESS(MATCH(A24,M:M,0)+D24-1,12)))),"""")"),"") | G24: Gregory Soto | H24: - - - | I24: 19677 | J24: {=INDEX('TJ List'!B:B,MATCH(I24,'TJ List'!N:N,0),0)} -> #N/A | L24: Oliver Ortega | M24: HOU | N24: Houston | O24: 21025 | P24: {=INDEX('TJ List'!B:B,MATCH(O24,'TJ List'!N:N,0),0)} -> #N/A | Q24: {=IFERROR(INDEX(I:I,MATCH(O24,I:I,0),0),0)} -> 0 | S24: Andrew Knizner | T24: TEX | U24: 19514 | W24: Trey Wingenter | X24: - - - | Y24: 17793 | Z24: 44029
A25: SFG | B25: =COUNTIFS(H:H,A25,J:J,">0") -> 10 | C25: =IFERROR(__xludf.DUMMYFUNCTION("IF(B25>0,JOIN("", "",TRANSPOSE(INDIRECT(ADDRESS(MATCH(A25,H:H,0),7)&"":""&ADDRESS(MATCH(A25,H:H,0)+B25-1,7)))),"""")"),"Mitch White, Logan Webb, Raymond Burgos, Jordan Hicks, Keaton Winn, Luke Jackson, Daulton Jefferies, Robbie Ray, Austin Warren, Blake Snell") -> Mitch White, Logan Webb, Raymond Burgos, Jordan Hicks, Keaton Winn, Luke Jackson, Daulton Jefferies, Robbie Ray, Austin Warren, Blake Snell | D25: =COUNTIFS(M:M,A25,P:P,">0",Q:Q,0) -> 0 | E25: =IFERROR(__xludf.DUMMYFUNCTION("IF(D25>0,JOIN("", "",TRANSPOSE(INDIRECT(ADDRESS(MATCH(A25,M:M,0),12)&"":""&ADDRESS(MATCH(A25,M:M,0)+D25-1,12)))),"""")"),"") | G25: Paul Blackburn | H25: - - - | I25: 14739 | J25: {=INDEX('TJ List'!B:B,MATCH(I25,'TJ List'!N:N,0),0)} -> #N/A | L25: Josh Taylor | M25: KCR | N25: Kansas City | O25: 17359 | P25: {=INDEX('TJ List'!B:B,MATCH(O25,'TJ List'!N:N,0),0)} -> #N/A | Q25: {=IFERROR(INDEX(I:I,MATCH(O25,I:I,0),0),0)} -> 0 | S25: Nick Loftin | T25: KCR | U25: 27630 | W25: Seranthony Domínguez | X25: - - - | Y25: 19249 | Z25: 44042
A26: STL | B26: =COUNTIFS(H:H,A26,J:J,">0") -> 9 | C26: =IFERROR(__xludf.DUMMYFUNCTION("IF(B26>0,JOIN("", "",TRANSPOSE(INDIRECT(ADDRESS(MATCH(A26,H:H,0),7)&"":""&ADDRESS(MATCH(A26,H:H,0)+B26-1,7)))),"""")"),"Steven Matz, Giovanny Gallegos, Kyle Gibson, Erick Fedde, Lance Lynn, John King, Nick Robertson, JoJo Romero, Andrew Kittredge") -> Steven Matz, Giovanny Gallegos, Kyle Gibson, Erick Fedde, Lance Lynn, John King, Nick Robertson, JoJo Romero, Andrew Kittredge | D26: =COUNTIFS(M:M,A26,P:P,">0",Q:Q,0) -> 1 | E26: =IFERROR(__xludf.DUMMYFUNCTION("IF(D26>0,JOIN("", "",TRANSPOSE(INDIRECT(ADDRESS(MATCH(A26,M:M,0),12)&"":""&ADDRESS(MATCH(A26,M:M,0)+D26-1,12)))),"""")"),"Keynan Middleton") -> Keynan Middleton | G26: Brock Burke | H26: - - - | I26: 17968 | J26: {=INDEX('TJ List'!B:B,MATCH(I26,'TJ List'!N:N,0),0)} -> #N/A | L26: Kyle Wright | M26: KCR | N26: Kansas City | O26: 19665 | P26: {=INDEX('TJ List'!B:B,MATCH(O26,'TJ List'!N:N,0),0)} -> #N/A | Q26: {=IFERROR(INDEX(I:I,MATCH(O26,I:I,0),0),0)} -> 0 | S26: Luke Maile | T26: CIN | U26: 13355 | W26: Matt Bowman | X26: - - - | Y26: 13528 | Z26: 44075
A27: TBR | B27: =COUNTIFS(H:H,A27,J:J,">0") -> 9 | C27: =IFERROR(__xludf.DUMMYFUNCTION("IF(B27>0,JOIN("", "",TRANSPOSE(INDIRECT(ADDRESS(MATCH(A27,H:H,0),7)&"":""&ADDRESS(MATCH(A27,H:H,0)+B27-1,7)))),"""")"),"Cole Sulser, Pete Fairbanks, Drew Rasmussen, Colin Poche, Jacob Lopez, Chris Devenski, Richard Lovelady, Shane Baz, Jeffrey Springs") -> Cole Sulser, Pete Fairbanks, Drew Rasmussen, Colin Poche, Jacob Lopez, Chris Devenski, Richard Lovelady, Shane Baz, Jeffrey Springs | D27: =COUNTIFS(M:M,A27,P:P,">0",Q:Q,0) -> 1 | E27: =IFERROR(__xludf.DUMMYFUNCTION("IF(D27>0,JOIN("", "",TRANSPOSE(INDIRECT(ADDRESS(MATCH(A27,M:M,0),12)&"":""&ADDRESS(MATCH(A27,M:M,0)+D27-1,12)))),"""")"),"Shane McClanahan") -> Shane McClanahan | G27: Luis García | H27: - - - | I27: 6984 | J27: {=INDEX('TJ List'!B:B,MATCH(I27,'TJ List'!N:N,0),0)} -> #N/A | L27: Robert Stephenson | M27: LAA | N27: Los Angeles | O27: 13594 | P27: {=INDEX('TJ List'!B:B,MATCH(O27,'TJ List'!N:N,0),0)} -> 45412 | Q27: {=IFERROR(INDEX(I:I,MATCH(O27,I:I,0),0),0)} -> 0 | S27: James McCann | T27: BAL | U27: 12859 | W27: Jalen Beeks | X27: - - - | Y27: 17192 | Z27: 44076
A28: MIN | B28: =COUNTIFS(H:H,A28,J:J,">0") -> 10 | C28: =IFERROR(__xludf.DUMMYFUNCTION("IF(B28>0,JOIN("", "",TRANSPOSE(INDIRECT(ADDRESS(MATCH(A28,H:H,0),7)&"":""&ADDRESS(MATCH(A28,H:H,0)+B28-1,7)))),"""")"),"Pablo López, Cole Irvin, Bailey Ober, Justin Topa, Matt Bowman, Brock Stewart, Chris Paddack, Daniel Duarte, Joe Ryan, Griffin Jax") -> Pablo López, Cole Irvin, Bailey Ober, Justin Topa, Matt Bowman, Brock Stewart, Chris Paddack, Daniel Duarte, Joe Ryan, Griffin Jax | D28: =COUNTIFS(M:M,A28,P:P,">0",Q:Q,0) -> 0 | E28: =IFERROR(__xludf.DUMMYFUNCTION("IF(D28>0,JOIN("", "",TRANSPOSE(INDIRECT(ADDRESS(MATCH(A28,M:M,0),12)&"":""&ADDRESS(MATCH(A28,M:M,0)+D28-1,12)))),"""")"),"") | G28: Hunter Bigge | H28: - - - | I28: 26259 | J28: {=INDEX('TJ List'!B:B,MATCH(I28,'TJ List'!N:N,0),0)} -> #N/A | L28: Kelvin Caceres | M28: LAA | N28: Los Angeles | O28: 24681 | P28: {=INDEX('TJ List'!B:B,MATCH(O28,'TJ List'!N:N,0),0)} -> #N/A | Q28: {=IFERROR(INDEX(I:I,MATCH(O28,I:I,0),0),0)} -> 0 | S28: Zach McKinstry | T28: DET | U28: 19392 | W28: Ricky Vanasco | X28: - - - | Y28: 23391 | Z28: 44095
A29: KCR | B29: =COUNTIFS(H:H,A29,J:J,">0") -> 7 | C29: =IFERROR(__xludf.DUMMYFUNCTION("IF(B29>0,JOIN("", "",TRANSPOSE(INDIRECT(ADDRESS(MATCH(A29,H:H,0),7)&"":""&ADDRESS(MATCH(A29,H:H,0)+B29-1,7)))),"""")"),"Hunter Harvey, Will Smith, Matt Sauer, Cole Ragans, Jonathan Bowlan, Dan Altavilla, Kris Bubic") -> Hunter Harvey, Will Smith, Matt Sauer, Cole Ragans, Jonathan Bowlan, Dan Altavilla, Kris Bubic | D29: =COUNTIFS(M:M,A29,P:P,">0",Q:Q,0) -> 0 | E29: =IFERROR(__xludf.DUMMYFUNCTION("IF(D29>0,JOIN("", "",TRANSPOSE(INDIRECT(ADDRESS(MATCH(A29,M:M,0),12)&"":""&ADDRESS(MATCH(A29,M:M,0)+D29-1,12)))),"""")"),"") | G29: Enoli Paredes | H29: - - - | I29: 20447 | J29: {=INDEX('TJ List'!B:B,MATCH(I29,'TJ List'!N:N,0),0)} -> #N/A | L29: Dustin May | M29: LAD | N29: Los Angeles | O29: 19716 | P29: {=INDEX('TJ List'!B:B,MATCH(O29,'TJ List'!N:N,0),0)} -> 45125 | Q29: {=IFERROR(INDEX(I:I,MATCH(O29,I:I,0),0),0)} -> 0 | S29: Danny Mendick | T29: CHW | U29: 18889 | W29: Caleb Ferguson | X29: - - - | Y29: 19349 | Z29: 44096
A30: OAK | B30: =COUNTIFS(H:H,A30,J:J,">0") -> 7 | C30: =IFERROR(__xludf.DUMMYFUNCTION("IF(B30>0,JOIN("", "",TRANSPOSE(INDIRECT(ADDRESS(MATCH(A30,H:H,0),7)&"":""&ADDRESS(MATCH(A30,H:H,0)+B30-1,7)))),"""")"),"Alex Wood, Ross Stripling, Hogan Harris, J.T. Ginn, Gerardo Reyes, Brady Basso, Luis Medina") -> Alex Wood, Ross Stripling, Hogan Harris, J.T. Ginn, Gerardo Reyes, Brady Basso, Luis Medina | D30: =COUNTIFS(M:M,A30,P:P,">0",Q:Q,0) -> 2 | E30: =IFERROR(__xludf.DUMMYFUNCTION("IF(D30>0,JOIN("", "",TRANSPOSE(INDIRECT(ADDRESS(MATCH(A30,M:M,0),12)&"":""&ADDRESS(MATCH(A30,M:M,0)+D30-1,12)))),"""")"),"Trevor Gott, Ken Waldichuk") -> Trevor Gott, Ken Waldichuk | G30: Dillon Tate | H30: - - - | I30: 17796 | J30: {=INDEX('TJ List'!B:B,MATCH(I30,'TJ List'!N:N,0),0)} -> #N/A | L30: Tony Gonsolin | M30: LAD | N30: Los Angeles | O30: 19388 | P30: {=INDEX('TJ List'!B:B,MATCH(O30,'TJ List'!N:N,0),0)} -> 45170 | Q30: {=IFERROR(INDEX(I:I,MATCH(O30,I:I,0),0),0)} -> 0 | S30: Matt Mervis | T30: CHC | U30: 27845 | W30: Jonathan Hernández | X30: - - - | Y30: 17464 | Z30: 44298
A31: WSN | B31: =COUNTIFS(H:H,A31,J:J,">0") -> 8 | C31: =IFERROR(__xludf.DUMMYFUNCTION("IF(B31>0,JOIN("", "",TRANSPOSE(INDIRECT(ADDRESS(MATCH(A31,H:H,0),7)&"":""&ADDRESS(MATCH(A31,H:H,0)+B31-1,7)))),"""")"),"Patrick Corbin, Derek Law, Hunter Harvey, Jake Irvin, Tanner Rainey, Zach Brzykcy, Josiah Gray, MacKenzie Gore") -> Patrick Corbin, Derek Law, Hunter Harvey, Jake Irvin, Tanner Rainey, Zach Brzykcy, Josiah Gray, MacKenzie Gore | D31: =COUNTIFS(M:M,A31,P:P,">0",Q:Q,0) -> 2 | E31: =IFERROR(__xludf.DUMMYFUNCTION("IF(D31>0,JOIN("", "",TRANSPOSE(INDIRECT(ADDRESS(MATCH(A31,M:M,0),12)&"":""&ADDRESS(MATCH(A31,M:M,0)+D31-1,12)))),"""")"),"Cade Cavalli, Mason Thompson") -> Cade Cavalli, Mason Thompson | G31: Jorge López | H31: - - - | I31: 14527 | J31: {=INDEX('TJ List'!B:B,MATCH(I31,'TJ List'!N:N,0),0)} -> #N/A | L31: Emmet Sheehan | M31: LAD | N31: Los Angeles | O31: 29839 | P31: {=INDEX('TJ List'!B:B,MATCH(O31,'TJ List'!N:N,0),0)} -> 45427 | Q31: {=IFERROR(INDEX(I:I,MATCH(O31,I:I,0),0),0)} -> 0 | S31: Owen Miller | T31: MIL | U31: 24655 | W31: James Paxton | X31: - - - | Y31: 11828 | Z31: 44300
A32: SEA | B32: =COUNTIFS(H:H,A32,J:J,">0") -> 6 | C32: =IFERROR(__xludf.DUMMYFUNCTION("IF(B32>0,JOIN("", "",TRANSPOSE(INDIRECT(ADDRESS(MATCH(A32,H:H,0),7)&"":""&ADDRESS(MATCH(A32,H:H,0)+B32-1,7)))),"""")"),"Gabe Speier, JT Chargois, Yimi García, Andrés Muñoz, Matt Bowman, Jonathan Hernández") -> Gabe Speier, JT Chargois, Yimi García, Andrés Muñoz, Matt Bowman, Jonathan Hernández | D32: =COUNTIFS(M:M,A32,P:P,">0",Q:Q,0) -> 2 | E32: =IFERROR(__xludf.DUMMYFUNCTION("IF(D32>0,JOIN("", "",TRANSPOSE(INDIRECT(ADDRESS(MATCH(A32,M:M,0),12)&"":""&ADDRESS(MATCH(A32,M:M,0)+D32-1,12)))),"""")"),"Jackson Kowar, Matt Brash") -> Jackson Kowar, Matt Brash | G32: Eduardo Salazar | H32: - - - | I32: 23135 | J32: {=INDEX('TJ List'!B:B,MATCH(I32,'TJ List'!N:N,0),0)} -> #N/A | L32: Sandy Alcantara | M32: MIA | N32: Miami | O32: 18684 | P32: {=INDEX('TJ List'!B:B,MATCH(O32,'TJ List'!N:N,0),0)} -> 45205 | Q32: {=IFERROR(INDEX(I:I,MATCH(O32,I:I,0),0),0)} -> 0 | S32: Jhonny Pereda | T32: MIA | U32: 19802 | W32: Richard Lovelady | X32: - - - | Y32: 19337 | Z32: 44468
A33: Total | B33: =SUM(B3:B32)-COUNTIFS(Y:Y,">0") -> 317 | D33: =SUM(D3:D32) -> 37 | G33: Anthony Veneziano | H33: - - - | I33: 27453 | J33: {=INDEX('TJ List'!B:B,MATCH(I33,'TJ List'!N:N,0),0)} -> #N/A | L33: Eury Pérez | M33: MIA | N33: Miami | O33: 27768 | P33: {=INDEX('TJ List'!B:B,MATCH(O33,'TJ List'!N:N,0),0)} -> 45390 | Q33: {=IFERROR(INDEX(I:I,MATCH(O33,I:I,0),0),0)} -> 0 | S33: Nick Pratto | T33: KCR | U33: 22117 | W33: Bradley Blalock | X33: - - - | Y33: 26419 | Z33: 44621
A34: Percentage | B34: =(COUNTIFS(J:J,">0")-COUNTIFS(Y:Y,">0"))/((COUNTIFS(I:I,">0")-COUNTIFS(U:U,">0")-COUNTIFS(Y:Y,">0"))) -> 0.39825218 | D34: =D33/COUNTIFS(O:O,"<>0",Q:Q,0) -> 0.75510204 | G34: Quinn Priester | H34: - - - | I34: 25977 | J34: {=INDEX('TJ List'!B:B,MATCH(I34,'TJ List'!N:N,0),0)} -> #N/A | L34: Brandon Woodruff | M34: MIL | N34: Milwaukee | O34: 16162 | P34: {=INDEX('TJ List'!B:B,MATCH(O34,'TJ List'!N:N,0),0)} -> #N/A | Q34: {=IFERROR(INDEX(I:I,MATCH(O34,I:I,0),0),0)} -> 0 | S34: Pablo Reyes | T34: BOS | U34: 16357 | W34: Luke Jackson | X34: - - - | Y34: 11752 | Z34: 44664
A35: Games Ended | B35: 45565 | D35: 45565 | G35: Yohan Ramírez | H35: - - - | I35: 19444 | J35: {=INDEX('TJ List'!B:B,MATCH(I35,'TJ List'!N:N,0),0)} -> #N/A | L35: Anthony DeSclafani | M35: MIN | N35: Minnesota | O35: 13050 | P35: {=INDEX('TJ List'!B:B,MATCH(O35,'TJ List'!N:N,0),0)} -> #N/A | Q35: {=IFERROR(INDEX(I:I,MATCH(O35,I:I,0),0),0)} -> 0 | S35: Leo Rivas | T35: SEA | U35: 21009 | W35: Daulton Jefferies | X35: - - - | Y35: 19345 | Z35: 44813
G36: Phil Maton | H36: - - - | I36: 18064 | J36: {=INDEX('TJ List'!B:B,MATCH(I36,'TJ List'!N:N,0),0)} -> #N/A | L36: JT Brubaker | M36: NYY | N36: New York | O36: 17578 | P36: {=INDEX('TJ List'!B:B,MATCH(O36,'TJ List'!N:N,0),0)} -> 45028 | Q36: {=IFERROR(INDEX(I:I,MATCH(O36,I:I,0),0),0)} -> 0 | S36: Emmanuel Rivera | T36: MIA | U36: 19890 | W36: Mitch White | X36: - - - | Y36: 19225 | Z36: 41579
A37: Overall | B37: =(B33+D33)/((COUNTIFS(I:I,">0")+COUNTIFS(O:O,"<>0",Q:Q,0)-COUNTIFS(U:U,">0")-COUNTIFS(Y:Y,">0"))) -> 0.41647059 | G37: Nate Pearson | H37: - - - | I37: 20160 | J37: {=INDEX('TJ List'!B:B,MATCH(I37,'TJ List'!N:N,0),0)} -> #N/A | L37: Lou Trivino | M37: NYY | N37: New York | O37: 15043 | P37: {=INDEX('TJ List'!B:B,MATCH(O37,'TJ List'!N:N,0),0)} -> 45049 | Q37: {=IFERROR(INDEX(I:I,MATCH(O37,I:I,0),0),0)} -> 0 | S37: Josh Rojas | T37: SEA | U37: 19734 | W37: Matt Bowman | X37: - - - | Y37: 13528 | Z37: 44075
A38: Games Ended | B38: 45565 | G38: Joel Kuhnel | H38: - - - | I38: 19995 | J38: {=INDEX('TJ List'!B:B,MATCH(I38,'TJ List'!N:N,0),0)} -> #N/A | L38: Trevor Gott | M38: OAK | N38: Oakland | O38: 15046 | P38: {=INDEX('TJ List'!B:B,MATCH(O38,'TJ List'!N:N,0),0)} -> 45385 | Q38: {=IFERROR(INDEX(I:I,MATCH(O38,I:I,0),0),0)} -> 0 | S38: Miguel Rojas | T38: LAD | U38: 7802 | W38: Matt Bowman | X38: - - - | Y38: 13528 | Z38: 44075
G39: Vinny Nittoli | H39: - - - | I39: 16754 | J39: {=INDEX('TJ List'!B:B,MATCH(I39,'TJ List'!N:N,0),0)} -> #N/A | L39: Ken Waldichuk | M39: OAK | N39: Oakland | O39: 27681 | P39: {=INDEX('TJ List'!B:B,MATCH(O39,'TJ List'!N:N,0),0)} -> 45424 | Q39: {=IFERROR(INDEX(I:I,MATCH(O39,I:I,0),0),0)} -> 0 | S39: Ben Rortvedt | T39: TBR | U39: 20287
G40: Trevor Richards | H40: - - - | I40: 19309 | J40: {=INDEX('TJ List'!B:B,MATCH(I40,'TJ List'!N:N,0),0)} -> #N/A | L40: Johan Oviedo | M40: PIT | N40: Pittsburgh | O40: 22487 | P40: {=INDEX('TJ List'!B:B,MATCH(O40,'TJ List'!N:N,0),0)} -> 45261 | Q40: {=IFERROR(INDEX(I:I,MATCH(O40,I:I,0),0),0)} -> 0 | S40: Miguel Sanó | T40: LAA | U40: 12164
G41: Jake Woodford | H41: - - - | I41: 18674 | J41: {=INDEX('TJ List'!B:B,MATCH(I41,'TJ List'!N:N,0),0)} -> #N/A | L41: Dauri Moreta | M41: PIT | N41: Pittsburgh | O41: 21101 | P41: {=INDEX('TJ List'!B:B,MATCH(O41,'TJ List'!N:N,0),0)} -> 45352 | Q41: {=IFERROR(INDEX(I:I,MATCH(O41,I:I,0),0),0)} -> 0 | S41: Dominic Smith | T41: BOS | U41: 15653
G42: Brett de Geus | H42: - - - | I42: 23592 | J42: {=INDEX('TJ List'!B:B,MATCH(I42,'TJ List'!N:N,0),0)} -> #N/A | L42: Luis Patiño | M42: SDP | N42: San Diego | O42: 22815 | P42: {=INDEX('TJ List'!B:B,MATCH(O42,'TJ List'!N:N,0),0)} -> 45412 | Q42: {=IFERROR(INDEX(I:I,MATCH(O42,I:I,0),0),0)} -> 0 | S42: Pavin Smith | T42: ARI | U42: 19892
G43: Shaun Anderson | H43: - - - | I43: 19453 | J43: {=INDEX('TJ List'!B:B,MATCH(I43,'TJ List'!N:N,0),0)} -> #N/A | L43: Jackson Kowar | M43: SEA | N43: Seattle | O43: 21549 | P43: {=INDEX('TJ List'!B:B,MATCH(O43,'TJ List'!N:N,0),0)} -> 45352 | Q43: {=IFERROR(INDEX(I:I,MATCH(O43,I:I,0),0),0)} -> 0 | S43: Michael Stefanic | T43: LAA | U43: 25353
G44: Xzavion Curry | H44: - - - | I44: 25595 | J44: {=INDEX('TJ List'!B:B,MATCH(I44,'TJ List'!N:N,0),0)} -> #N/A | L44: Matt Brash | M44: SEA | N44: Seattle | O44: 25756 | P44: {=INDEX('TJ List'!B:B,MATCH(O44,'TJ List'!N:N,0),0)} -> 45420 | Q44: {=IFERROR(INDEX(I:I,MATCH(O44,I:I,0),0),0)} -> 0 | S44: Garrett Stubbs | T44: PHI | U44: 18067
G45: Colin Selby | H45: - - - | I45: 24986 | J45: {=INDEX('TJ List'!B:B,MATCH(I45,'TJ List'!N:N,0),0)} -> #N/A | L45: Keynan Middleton | M45: STL | N45: St. Louis | O45: 15264 | P45: {=INDEX('TJ List'!B:B,MATCH(O45,'TJ List'!N:N,0),0)} -> 43242 | Q45: {=IFERROR(INDEX(I:I,MATCH(O45,I:I,0),0),0)} -> 0 | S45: Rowdy Tellez | T45: PIT | U45: 15679
G46: Will Klein | H46: - - - | I46: 27787 | J46: {=INDEX('TJ List'!B:B,MATCH(I46,'TJ List'!N:N,0),0)} -> #N/A | L46: Drew Rom | M46: STL | N46: St. Louis | O46: 24602 | P46: {=INDEX('TJ List'!B:B,MATCH(O46,'TJ List'!N:N,0),0)} -> #N/A | Q46: {=IFERROR(INDEX(I:I,MATCH(O46,I:I,0),0),0)} -> 0 | S46: Luis Torrens | T46: NYM | U46: 15905
G47: Héctor Neris | H47: - - - | I47: 11804 | J47: {=INDEX('TJ List'!B:B,MATCH(I47,'TJ List'!N:N,0),0)} -> #N/A | L47: Shane McClanahan | M47: TBR | N47: Tampa Bay | O47: 21483 | P47: {=INDEX('TJ List'!B:B,MATCH(O47,'TJ List'!N:N,0),0)} -> 45159 | Q47: {=IFERROR(INDEX(I:I,MATCH(O47,I:I,0),0),0)} -> 0 | S47: Jose Trevino | T47: NYY | U47: 16725
G48: Walter Pennington | H48: - - - | I48: 27624 | J48: {=INDEX('TJ List'!B:B,MATCH(I48,'TJ List'!N:N,0),0)} -> #N/A | L48: Carson Coleman | M48: TEX | N48: Texas | O48: sa3014857 | P48: {=INDEX('TJ List'!B:B,MATCH(O48,'TJ List'!N:N,0),0)} -> 45017 | Q48: {=IFERROR(INDEX(I:I,MATCH(O48,I:I,0),0),0)} -> 0 | S48: Cole Tucker | T48: LAA | U48: 17326
G49: Tyler Jay | H49: - - - | I49: 17952 | J49: {=INDEX('TJ List'!B:B,MATCH(I49,'TJ List'!N:N,0),0)} -> #N/A | L49: Cade Cavalli | M49: WSN | N49: Washington | O49: 27473 | P49: {=INDEX('TJ List'!B:B,MATCH(O49,'TJ List'!N:N,0),0)} -> 45007 | Q49: {=IFERROR(INDEX(I:I,MATCH(O49,I:I,0),0),0)} -> 0 | S49: Ildemaro Vargas | T49: WSN | U49: 13324
G50: Alex Young | H50: - - - | I50: 18333 | J50: {=INDEX('TJ List'!B:B,MATCH(I50,'TJ List'!N:N,0),0)} -> #N/A | L50: Mason Thompson | M50: WSN | N50: Washington | O50: 21850 | P50: {=INDEX('TJ List'!B:B,MATCH(O50,'TJ List'!N:N,0),0)} -> 45352 | Q50: {=IFERROR(INDEX(I:I,MATCH(O50,I:I,0),0),0)} -> 0 | S50: Matt Wallner | T50: MIN | U50: 26466
G51: Ryne Stanek | H51: - - - | I51: 15947 | J51: {=INDEX('TJ List'!B:B,MATCH(I51,'TJ List'!N:N,0),0)} -> #N/A | S51: Donovan Walton | T51: SFG | U51: 19314
G52: Wes Parsons | H52: - - - | I52: 14764 | J52: {=INDEX('TJ List'!B:B,MATCH(I52,'TJ List'!N:N,0),0)} -> #N/A | S52: Luke Williams | T52: ATL | U52: 19931
G53: Janson Junk | H53: - - - | I53: 23301 | J53: {=INDEX('TJ List'!B:B,MATCH(I53,'TJ List'!N:N,0),0)} -> #N/A | S53: Weston Wilson | T53: PHI | U53: 19358
G54: Ryan Yarbrough | H54: - - - | I54: 16502 | J54: {=INDEX('TJ List'!B:B,MATCH(I54,'TJ List'!N:N,0),0)} -> #N/A | S54: Patrick Wisdom | T54: CHC | U54: 13602
G55: Joe Jacques | H55: - - - | I55: 25178 | J55: {=INDEX('TJ List'!B:B,MATCH(I55,'TJ List'!N:N,0),0)} -> #N/A | S55: Mike Yastrzemski | T55: SFG | U55: 14854
G56: Spencer Howard | H56: - - - | I56: 23252 | J56: {=INDEX('TJ List'!B:B,MATCH(I56,'TJ List'!N:N,0),0)} -> #N/A
G57: Luis Guillorme | H57: - - - | I57: 16451 | J57: {=INDEX('TJ List'!B:B,MATCH(I57,'TJ List'!N:N,0),0)} -> #N/A
G58: Easton Lucas | H58: - - - | I58: 26058 | J58: {=INDEX('TJ List'!B:B,MATCH(I58,'TJ List'!N:N,0),0)} -> #N/A
G59: Luis Frías | H59: - - - | I59: 21997 | J59: {=INDEX('TJ List'!B:B,MATCH(I59,'TJ List'!N:N,0),0)} -> #N/A
G60: Michael Petersen | H60: - - - | I60: 20827 | J60: {=INDEX('TJ List'!B:B,MATCH(I60,'TJ List'!N:N,0),0)} -> #N/A
G61: Elieser Hernández | H61: - - - | I61: 16933 | J61: {=INDEX('TJ List'!B:B,MATCH(I61,'TJ List'!N:N,0),0)} -> #N/A
G62: Lucas Sims | H62: - - - | I62: 13470 | J62: {=INDEX('TJ List'!B:B,MATCH(I62,'TJ List'!N:N,0),0)} -> #N/A
G63: Brandon Bielak | H63: - - - | I63: 19866 | J63: {=INDEX('TJ List'!B:B,MATCH(I63,'TJ List'!N:N,0),0)} -> #N/A
G64: Brad Keller | H64: - - - | I64: 15734 | J64: {=INDEX('TJ List'!B:B,MATCH(I64,'TJ List'!N:N,0),0)} -> #N/A
G65: Jose Cuas | H65: - - - | I65: 17701 | J65: {=INDEX('TJ List'!B:B,MATCH(I65,'TJ List'!N:N,0),0)} -> #N/A
G66: Thyago Vieira | H66: - - - | I66: 14510 | J66: {=INDEX('TJ List'!B:B,MATCH(I66,'TJ List'!N:N,0),0)} -> 45717
G67: Mike Baumann | H67: - - - | I67: 20206 | J67: {=INDEX('TJ List'!B:B,MATCH(I67,'TJ List'!N:N,0),0)} -> #N/A
... G100: Bryce Jarvis | H100: ARI | I100: 27477 | J100: {=INDEX('TJ List'!B:B,MATCH(I100,'TJ List'!N:N,0),0)} -> #N/A
G101: Pavin Smith | H101: ARI | I101: 19892
G102: Charlie Morton | H102: ATL | I102: 4676 | J102: {=INDEX('TJ List'!B:B,MATCH(I102,'TJ List'!N:N,0),0)} -> 41074
G103: Max Fried | H103: ATL | I103: 13743 | J103: {=INDEX('TJ List'!B:B,MATCH(I103,'TJ List'!N:N,0),0)} -> 41871
G104: A.J. Minter | H104: ATL | I104: 18655 | J104: {=INDEX('TJ List'!B:B,MATCH(I104,'TJ List'!N:N,0),0)} -> 42083
G105: Aaron Bummer | H105: ATL | I105: 16258 | J105: {=INDEX('TJ List'!B:B,MATCH(I105,'TJ List'!N:N,0),0)} -> 42227
G106: Spencer Strider | H106: ATL | I106: 27498 | J106: {=INDEX('TJ List'!B:B,MATCH(I106,'TJ List'!N:N,0),0)} -> 43497
G107: Chris Sale | H107: ATL | I107: 10603 | J107: {=INDEX('TJ List'!B:B,MATCH(I107,'TJ List'!N:N,0),0)} -> 43920
G108: John Brebbia | H108: ATL | I108: 12777 | J108: {=INDEX('TJ List'!B:B,MATCH(I108,'TJ List'!N:N,0),0)} -> 43990
G109: Spencer Schwellenbach | H109: ATL | I109: 31846 | J109: {=INDEX('TJ List'!B:B,MATCH(I109,'TJ List'!N:N,0),0)} -> 44409
G110: Daysbel Hernández | H110: ATL | I110: 20271 | J110: {=INDEX('TJ List'!B:B,MATCH(I110,'TJ List'!N:N,0),0)} -> 44600
G111: Luke Jackson | H111: ATL | I111: 11752 | J111: {=INDEX('TJ List'!B:B,MATCH(I111,'TJ List'!N:N,0),0)} -> 44664
G112: Tyler Matzek | H112: ATL | I112: 10058 | J112: {=INDEX('TJ List'!B:B,MATCH(I112,'TJ List'!N:N,0),0)} -> 44846
G113: Ray Kerr | H113: ATL | I113: 23809 | J113: {=INDEX('TJ List'!B:B,MATCH(I113,'TJ List'!N:N,0),0)} -> 45474
... G435: Guillo Zuñiga | H435: LAA | I435: 19588 | J435: {=INDEX('TJ List'!B:B,MATCH(I435,'TJ List'!N:N,0),0)} -> #N/A
G436: Miguel Sanó | H436: LAA | I436: 12164
G437: Daniel Hudson | H437: LAD | I437: 7146 | J437: {=INDEX('TJ List'!B:B,MATCH(I437,'TJ List'!N:N,0),0)} -> 41443
G438: Ryan Brasier | H438: LAD | I438: 5615 | J438: {=INDEX('TJ List'!B:B,MATCH(I438,'TJ List'!N:N,0),0)} -> 41800
G439: Brusdar Graterol | H439: LAD | I439: 20367 | J439: {=INDEX('TJ List'!B:B,MATCH(I439,'TJ List'!N:N,0),0)} -> 42217
G440: Michael Grove | H440: LAD | I440: 23221 | J440: {=INDEX('TJ List'!B:B,MATCH(I440,'TJ List'!N:N,0),0)} -> 42856
G441: Brent Honeywell | H441: LAD | I441: 16466 | J441: {=INDEX('TJ List'!B:B,MATCH(I441,'TJ List'!N:N,0),0)} -> 43158
G442: Dinelson Lamet | H442: LAD | I442: 17186 | J442: {=INDEX('TJ List'!B:B,MATCH(I442,'TJ List'!N:N,0),0)} -> 43210
G443: Anthony Banda | H443: LAD | I443: 14706 | J443: {=INDEX('TJ List'!B:B,MATCH(I443,'TJ List'!N:N,0),0)} -> 43265
G444: Michael Kopech | H444: LAD | I444: 17282 | J444: {=INDEX('TJ List'!B:B,MATCH(I444,'TJ List'!N:N,0),0)} -> 43361
G445: Gus Varland | H445: LAD | I445: 24737 | J445: {=INDEX('TJ List'!B:B,MATCH(I445,'TJ List'!N:N,0),0)} -> 43678
G446: Ricky Vanasco | H446: LAD | I446: 23391 | J446: {=INDEX('TJ List'!B:B,MATCH(I446,'TJ List'!N:N,0),0)} -> 44095
G447: James Paxton | H447: LAD | I447: 11828 | J447: {=INDEX('TJ List'!B:B,MATCH(I447,'TJ List'!N:N,0),0)} -> 44300
G448: Justin Wrobleski | H448: LAD | I448: 31204 | J448: {=INDEX('TJ List'!B:B,MATCH(I448,'TJ List'!N:N,0),0)} -> 44317
... G642: Aaron Brooks | H642: OAK | I642: 12272 | J642: {=INDEX('TJ List'!B:B,MATCH(I642,'TJ List'!N:N,0),0)} -> #N/A
A643: **** | G643: Sean Newcomb | H643: OAK | I643: 16943 | J643: {=INDEX('TJ List'!B:B,MATCH(I643,'TJ List'!N:N,0),0)} -> #N/A
G644: Dany Jiménez | H644: OAK | I644: 21170 | J644: {=INDEX('TJ List'!B:B,MATCH(I644,'TJ List'!N:N,0),0)} -> #N/A
G645: Matt Strahm | H645: PHI | I645: 13799 | J645: {=INDEX('TJ List'!B:B,MATCH(I645,'TJ List'!N:N,0),0)} -> 41466
G646: Jeff Hoffman | H646: PHI | I646: 17432 | J646: {=INDEX('TJ List'!B:B,MATCH(I646,'TJ List'!N:N,0),0)} -> 41773
...

Sheet MLB 2023
A1: 2023 MLB Pitchers Who Have Had TJ Surgery, By Team & Usage
A2: Team | B2: Pitchers Used | C2: Pitchers | D2: Pitchers Not Used, on IL | E2: Pitchers on IL
A3: LAD | B3: 15 | C3: Daniel Hudson, Justin Bruihl, Ryan Brasier, Brusdar Graterol, Lance Lynn, Andre Jackson, Nick Robertson, Victor González, Michael Grove, Shelby Miller, Gus Varland, Noah Syndergaard, Caleb Ferguson, Dustin May, Tony Gonsolin | D3: 3 | E3: Alex Reyes, Jimmy Nelson, Walker Buehler
A4: CIN | B4: 14 | C4: Alec Mills, Derek Law, Alexis Díaz, Levi Stoudt, Kevin Herget, Silvino Bracho, Hunter Greene, Ricky Karcher, Casey Legumina, Jake Wong, Lyon Richardson, Tejay Antone, Connor Overton, Reiver Sanmartin | D4: 1 | E4: Vladimir Gutierrez
A5: NYY | B5: 14 | C5: Ron Marinaccio, Clay Holmes, Matt Krook, Domingo Germán, Jonathan Loáisiga, Jhony Brito, Clarke Schmidt, Keynan Middleton, Carlos Rodón, Luis Severino, Tommy Kahnle, Matt Bowman, Jimmy Cordero, Yoendrys Gómez | D5: 3 | E5: Luis Gil, Scott Effross, Lou Trivino
A6: CHW | B6: 13 | C6: Lucas Giolito, Dylan Cease, Nicholas Padilla, Aaron Bummer, Lance Lynn, Brent Honeywell, Keynan Middleton, Kendall Graveman, Michael Kopech, Jimmy Lambert, Mike Clevinger, Garrett Crochet, Liam Hendriks | D6: 1 | E6: Matt Foster
A7: DET | B7: 13 | C7: José Cisnero, Will Vest, Garrett Hill, Tarik Skubal, Jason Foley, Tyler Holton, Mason Englert, Joey Wentz, Trey Wingenter, Alex Faedo, Brenan Hanifee, Spencer Turnbull, Matthew Boyd | D7: 2 | E7: Casey Mize, Freddy Pacheco
A8: TBR | B8: 13 | C8: Zack Burdi, Pete Fairbanks, Drew Rasmussen, Ryan Thompson, Colin Poche, Yonny Chirinos, Jalen Beeks, Jacob Lopez, Chris Devenski, Tyler Glasnow, Andrew Kittredge, Jeffrey Springs, Shane McClanahan | D8: 1 | E8: Shane Baz
A9: TEX | B9: 13 | C9: Martín Pérez, Andrew Heaney, Nathan Eovaldi, John King, Will Smith, Jordan Montgomery, Alex Speas, Dane Dunning, Owen White, Cole Ragans, José Leclerc, Jonathan Hernández, Jacob deGrom | D9: 0
A10: BOS | B10: 12 | C10: Ryan Brasier, Justin Garza, Nick Robertson, Brandon Walter, Dinelson Lamet, Matt Dermody, Ryan Sherriff, Garrett Whitlock, Kutter Crawford, Zack Kelly, Chris Sale, James Paxton | D10: 1 | E10: Wyatt Mills
A11: LAA | B11: 12 | C11: Lucas Giolito, Reyes Moronta, Matt Moore, Jacob Webb, Shohei Ohtani, Davis Daniel, Ben Joyce, Gerardo Reyes, Chris Devenski, José Soriano, José Quijada, Austin Warren | D11: 0
A12: SDP | B12: 12 | C12: Rich Hill, Scott Barlow, Yu Darvish, Domingo Tapia, Steven Wilson, Robert Suarez, Nick Hernandez, Brent Honeywell, Pedro Avila, Tom Cosgrove, José Castillo, Adrian Morejon | D12: 0
A13: ARI | B13: 11 | C13: Andrew Chafin, Scott McGough, Cole Sulser, Peter Strzelecki, Ryan Thompson, Joe Mantiply, Peter Solomon, Carlos Vargas, Andrew Saalfrank, Justin Martinez, Drey Jameson | D13: 2 | E13: Mark Melancon, Corbin Martin
A14: CHC | B14: 11 | C14: Shane Greene, Keegan Thompson, Anthony Kay, Drew Smyly, Justin Steele, Julian Merryweather, Mark Leiter Jr., Michael Fulmer, Jameson Taillon, Jeremiah Estrada, Nick Burdi | D14: 2 | E14: Codi Heuer, Ethan Roberts
A15: COL | B15: 11 | C15: Justin Bruihl, Chris Flexen, Blair Calvo, Noah Davis, Dinelson Lamet, Brent Suter, Matt Carasiti, Ty Blach, Peter Lambert, Germán Márquez, Antonio Senzatela | D15: 1 | E15: Lucas Gilbreath
A16: MIA | B16: 11 | C16: JT Chargois, Matt Moore, Bryan Hoeing, Jesús Luzardo, Sean Nolin, Braxton Garrett, Chi Chi González, A.J. Puk, Johnny Cueto, David Robertson, Sandy Alcantara | D16: 3 | E16: Tommy Nance, Max Meyer, Anthony Bender
A17: NYM | B17: 11 | C17: Carlos Carrasco, Jeff Brigham, Adam Ottavino, Anthony Kay, Sam Coonrod, David Robertson, Justin Verlander, Joey Lucchesi, John Curtiss, Sean Reid-Foley, Drew Smith | D17: 1 | E17: Bryce Montes de Oca
A18: STL | B18: 11 | C18: Drew VerHagen, Steven Matz, Giovanny Gallegos, Adam Wainwright, Packy Naughton, James Naile, John King, Jordan Montgomery, Jordan Hicks, Dakota Hudson, JoJo Romero | D18: 0
A19: SEA | B19: 10 | C19: Gabe Speier, Chris Flexen, Justin Topa, Marco Gonzales, Matt Festa, Andrés Muñoz, Ty Adcock, Easton McGee, Robbie Ray, Penn Murfee | D19: 0
A20: WSN | B20: 10 | C20: Patrick Corbin, Andrés Machado, Hunter Harvey, Anthony Banda, Chad Kuhl, Jake Irvin, Rico Garcia, Thaddeus Ward, Tanner Rainey, Mason Thompson | D20: 0
A21: ATL | B21: 9 | C21: Charlie Morton, Max Fried, A.J. Minter, Lucas Luetge, Ben Heller, Spencer Strider, Yonny Chirinos, Kirby Yates, Daysbel Hernández | D21: 2 | E21: Huascar Ynoa, Tyler Matzek
A22: MIL | B22: 9 | C22: Andrew Chafin, Trevor Megill, Peter Strzelecki, Ethan Small, Adrian Houser, Colin Rea, Devin Williams, Matt Bush, Gus Varland | D22: 1 | E22: Justin Wilson
A23: PIT | B23: 9 | C23: Vince Velasquez, Rich Hill, Ryan Borucki, Yerry De Los Santos, Wil Crowe, Andre Jackson, Colin Holderman, Jose Hernandez, Angel Perdomo | D23: 1 | E23: JT Brubaker
A24: TOR | B24: 9 | C24: Mitch White, Jordan Romano, Chris Bassitt, Yimi García, Zach Pop, Jordan Hicks, Tim Mayza, Chad Green, Hyun Jin Ryu | D24: 0
A25: SFG | B25: 8 | C25: Alex Wood, Ross Stripling, Alex Cobb, Logan Webb, John Brebbia, Keaton Winn, Luke Jackson, Cole Waites | D25: 1 | E25: Thomas Szapucki
A26: BAL | B26: 7 | C26: Danny Coulombe, Kyle Gibson, Cole Irvin, Jacob Webb, Tyler Wells, Félix Bautista, John Means | D26: 0
A27: CLE | B27: 7 | C27: Lucas Giolito, Matt Moore, Cal Quantrill, Cody Morris, Zach Plesac, Sam Hentges, Noah Syndergaard | D27: 0
A28: MIN | B28: 7 | C28: Pablo López, Bailey Ober, Brock Stewart, Kenta Maeda, Chris Paddack, Tyler Mahle, José De León | D28: 0
A29: OAK | B29: 7 | C29: Adrián Martínez, Trevor May, James Kaprielian, Hogan Harris, Rico Garcia, Richard Lovelady, Garrett Acton | D29: 0
A30: HOU | B30: 6 | C30: J.P. France, Rafael Montero, Kendall Graveman, Justin Verlander, Luis Garcia, José Urquidy | D30: 1 | E30: Lance McCullers Jr.
A31: KCR | B31: 6 | C31: Scott Barlow, Taylor Clarke, Brooks Kriske, Cole Ragans, Jonathan Bowlan, Kris Bubic | D31: 1 | E31: Jake Brentz
A32: PHI | B32: 6 | C32: Matt Strahm, Jeff Hoffman, Zack Wheeler, Andrew Bellatti, Taijuan Walker, Seranthony Domínguez | D32: 0
A33: Total | B33: 275 | D33: 28
A34: Percentage | B34: 0.34246575 | D34: 0.62222222
A35: Games Ended | B35: 45200 | D35: 45200
A37: Overall | B37: 0.35731132
A38: Games Ended | B38: 10/1/1023

Sheet MLB 2022
A1: 2022 MLB Pitchers Who Have Had TJ Surgery, By Team & Usage
A2: Team | B2: Pitchers Used | C2: Pitchers | D2: Pitchers Not Used, on IL | E2: Pitchers on IL
A3: NYY | B3: 16 | C3: Shane Greene, Manny Banuelos, Ron Marinaccio, Clay Holmes, Domingo German, Jonathan Loaisiga, Clarke Schmidt, Lucas Luetge, Chi Chi Gonzalez, Jordan Montgomery, Anthony Banda, Jameson Taillon, Luis Severino, Luis Gil, Chad Green, Scott Effross | D3: 0
A4: DET | B4: 15 | C4: Wily Peralta, Andrew Chafin, Drew Hutchison, Jose Cisnero, Derek Law, Will Vest, Garrett Hill, Tarik Skubal, Jason Foley, Michael Pineda, Bryan Garcia, Michael Fulmer, Joey Wentz, Alex Faedo, Casey Mize | D4: 1 | E4: Spencer Turnbull
A5: CHC | B5: 14 | C5: Adrian Sampson, Alec Mills, Nicholas Padilla, Keegan Thompson, Kervin Castro, Drew Smyly, Justin Steele, Matt Dermody, Mark Leiter, Anderson Espinoza, David Robertson, Jeremiah Estrada, Ethan Roberts, Scott Effross | D5: 1 | E5: Codi Heuer
A6: LAD | B6: 14 | C6: Shane Greene, Reyes Moronta, Daniel Hudson, Mitch White, Justin Bruihl, Brusdar Graterol, Robbie Erlin, Andrew Heaney, Andre Jackson, Michael Grove, Tommy Kahnle, Caleb Ferguson, Dustin May, Walker Buehler | D6: 0
A7: MIL | B7: 14 | C7: Jake McGee, Jason Alexander, Justin Topa, Peter Strzelecki, Ethan Small, Adrian Houser, Devin Williams, Jandel Gustave, Chi Chi Gonzalez, Brent Suter, Matt Bush, Connor Sadzeck, Luis Perdomo, Luke Barker | D7: 0
A8: MIA | B8: 13 | C8: Jeff Brigham, Tommy Nance, Pablo Lopez, Cole Sulser, Bryan Hoeing, Jesus Luzardo, Jordan Holloway, Braxton Garrett, A.J. Ladwig, Zach Pop, Max Meyer, Cody Poteet, Anthony Bender | D8: 0
A9: TOR | B9: 13 | C9: Ryan Borucki, Mitch White, Ross Stripling, Jordan Romano, Anthony Kay, Yimi Garcia, Julian Merryweather, David Phelps, Anthony Banda, Zach Pop, Tim Mayza, Foster Griffin, Hyun-Jin Ryu | D9: 0
A10: CIN | B10: 12 | C10: Hunter Strickland, Kyle Dowdy, Art Warren, Jeff Hoffman, Derek Law, Alexis Diaz, Connor Overton, Hunter Greene, Raynel Espinal, Jared Solomon, Justin Wilson, Vladimir Gutierrez | D10: 1 | E10: Tejay Antone
A11: NYM | B11: 12 | C11: Jacob deGrom, Carlos Carrasco, Bryce Montes de Oca, Adam Ottavino, Nate Fisher, Chris Bassitt, Trevor May, Thomas Szapucki, Colin Holderman, Taijuan Walker, Drew Smith, Sean Reid-Foley | D11: 3 | E11: Stephen Ridings, Joey Lucchesi, John Curtiss
A12: SFG | B12: 12 | C12: Jake McGee, Alex Wood, Alex Cobb, Logan Webb, Kervin Castro, Shelby Miller, Thomas Szapucki, Jharel Cotton, Carlos Rodon, Tyler Beede, John Brebbia, Jose Alvarez | D12: 0
A13: STL | B13: 12 | C13: Drew VerHagen, Steven Matz, Giovanny Gallegos, Adam Wainwright, Packy Naughton, James Naile, Kodi Whitley, Jordan Montgomery, Jordan Hicks, Jake Walsh, Dakota Hudson, JoJo Romero | D13: 0
A14: PHI | B14: 11 | C14: Kyle Gibson, Zack Wheeler, Nick Duron, Sam Coonrod, Andrew Bellatti, Corey Knebel, David Robertson, Noah Syndergaard, Seranthony Dominguez, JoJo Romero, Chris Devenski | D14: 0
A15: TBR | B15: 11 | C15: JT Chargois, Pete Fairbanks, Drew Rasmussen, Ryan Thompson, Kevin Herget, Colin Poche, Yonny Chirinos, Jalen Beeks, Tyler Glasnow, Andrew Kittredge, Shane Baz | D15: 0
A16: TEX | B16: 11 | C16: Matt Moore, Martin Perez, Greg Holland, John King, Garrett Richards, Dane Dunning, Cole Ragans, Matt Bush, Nicklaus Snyder, Jose Leclerc, Jonathan Hernandez | D16: 0
A17: WSN | B17: 11 | C17: Anibal Sanchez, Jake McGee, Stephen Strasburg, Patrick Murphy, Patrick Corbin, Erick Fedde, Andres Machado, Mason Thompson, Hunter Harvey, Josh Rogers, Tanner Rainey | D17: 0
A18: ATL | B18: 10 | C18: Charlie Morton, Max Fried, A.J. Minter, Will Smith, Spencer Strider, Silvino Bracho, Tyler Thornburg, Kirby Yates, Huascar Ynoa, Tyler Matzek | D18: 0
A19: CHW | B19: 10 | C19: Vince Velasquez, Lucas Giolito, Dylan Cease, Aaron Bummer, Lance Lynn, Kendall Graveman, Johnny Cueto, Michael Kopech, Jimmy Lambert, Ryan Burr | D19: 1 | E19: Garrett Crochet
A20: MIN | B20: 10 | C20: Danny Coulombe, Trevor Megill, Dylan Bundy, Bailey Ober, Chi Chi Gonzalez, Jharel Cotton, Jhon Romero, Michael Fulmer, Tyler Thornburg, Chris Paddack | D20: 1 | E20: Kenta Maeda
A21: PIT | B21: 10 | C21: Manny Banuelos, Dillon Peters, Beau Sulser, Yerry De Los Santos, Wil Crowe, Miguel Yajure, Colin Holderman, Anthony Banda, Tyler Beede, Max Kranick | D21: 0
A22: ARI | B22: 9 | C22: Mark Melancon, Reyes Moronta, J.B. Wendelken, Tyler Holton, Joe Mantiply, Keynan Middleton, Corbin Martin, Chris Devenski, Humberto Castellanos | D22: 0
A23: SDP | B23: 9 | C23: Yu Darvish, Steven Wilson, Robert Suarez, Dinelson Lamet, Pedro Avila, Mike Clevinger, Jose Castillo, Michel Baez, Adrian Morejon | D23: 0
A24: BOS | B24: 8 | C24: Rich Hill, Matt Strahm, Ryan Brasier, Nathan Eovaldi, Garrett Whitlock, Kutter Crawford, Zack Kelly, Chris Sale | D24: 1 | E24: James Paxton
A25: OAK | B25: 8 | C25: Zach Jackson, Cole Irvin, Domingo Tapia, Adrian Martinez, James Kaprielian, A.J. Puk, Collin Wiles, Daulton Jefferies | D25: 0
A26: SEA | B26: 8 | C26: Ryan Borucki, Drew Steckenrider, Chris Flexen, Marco Gonzales, Matthew Festa, Andres Munoz, Ken Giles, Roenis Elias | D26: 0
A27: CLE | B27: 6 | C27: Cal Quantrill, Anthony Castro, Cody Morris, Zach Plesac, Sam Hentges, Anthony Gose | D27: 0
A28: HOU | B28: 6 | C28: Blake Taylor, Jose Urquidy, Will Smith, Rafael Montero, Lance McCullers Jr., Justin Verlander | D28: 0
A29: KCR | B29: 6 | C29: Arodys Vizcaino, Scott Barlow, Taylor Clarke, Gabe Speier, Foster Griffin, Jake Brentz | D29: 0
A30: COL | B30: 5 | C30: Jordan Sheffield, Noah Davis, Dinelson Lamet, Chad Kuhl, Ty Blach | D30: 0
A31: LAA | B31: 5 | C31: Brian Moran, Nash Walters, Shohei Ohtani, Noah Syndergaard, Gerardo Reyes | D31: 0
A32: BAL | B32: 4 | C32: Beau Sulser, Tyler Wells, Rico Garcia, John Means | D32: 0
A33: Total | B33: 274 | D33: 9
A34: Percentage | B34: 0.34 | D34: 0.529
A35: Games Ended | B35: 44839 | D35: 44839
A37: Overall | B37: 0.344
A38: Games Ended | B38: 44839

Sheet MLB 2021
A1: 2021 MLB Pitchers Who Have Had TJ Surgery, By Team & Usage
A2: Team | B2: Pitchers Used | C2: Pitchers | D2: Pitchers Not Used, on IL | E2: Pitchers on IL
A3: TOR | B3: 17 | C3: Hyun-Jin Ryu, Rafael Dolis, Steven Matz, Joakim Soria, Patrick Murphy, Ryan Borucki, Ross Stripling, Tyler Chatwood, Jordan Romano, Anthony Castro, Travis Bergen, Nick Allgeyer, Anthony Kay, Connor Overton, Julian Merryweather, David Phelps, Tim Mayza | D3: 1 | E3: Kirby Yates
A4: WSN | B4: 16 | C4: Javy Guerra, Will Harris, Stephen Strasburg, Justin Miller, Patrick Murphy, Daniel Hudson, Patrick Corbin, Erick Fedde, Andres Machado, Mason Thompson, Sean Nolin, Joe Ross, Gabe Klobosits, Jhon Romero, Josh Rogers, Luis Avilan | D4: 0
A5: MIL | B5: 14 | C5: John Axford, Jordan Zimmermann, Brett Anderson, Hunter Strickland, Justin Topa, Adrian Houser, Colin Rea, Devin Williams, Jandel Gustave, Patrick Weigel, Drew Rasmussen, Brent Suter, Blaine Hardy, John Curtiss | D5: 0
A6: ATL | B6: 13 | C6: Shane Greene, Charlie Morton, Josh Tomlin, Nate Jones, Max Fried, A.J. Minter, Jacob Webb, Jesse Biddle, Will Smith, Drew Smyly, Grant Dayton, Edgar Santana, Spencer Strider | D6: 0
A7: SDP | B7: 13 | C7: Mark Melancon, Vince Velasquez, Daniel Hudson, Matt Strahm, Yu Darvish, Mason Thompson, Taylor Williams, Chris Paddack, Dinelson Lamet, Pedro Avila, Adrian Morejon, Keone Kela, Dan Altavilla | D7: 4 | E7: Trey Wingenter, Mike Clevinger, Jose Castillo, Michel Baez
A8: SEA | B8: 13 | C8: Drew Steckenrider, JT Chargois, Chris Flexen, Domingo Tapia, Casey Sadler, Will Vest, Marco Gonzales, Rafael Montero, Keynan Middleton, Kendall Graveman, Andres Munoz, Ljay Newsome, James Paxton | D8: 1 | E8: Ken Giles
A9: CHC | B9: 12 | C9: Andrew Chafin, Adrian Sampson, Joe Biagini, Brad Wieck, Tommy Nance, Trevor Megill, Alec Mills, Dan Winkler, Brandon Workman, Keegan Thompson, Shelby Miller, Justin Steele | D9: 0
A10: LAD | B10: 12 | C10: Shane Greene, Neftali Feliz, Mitch White, Justin Bruihl, Nate Jones, Brusdar Graterol, Walker Buehler, Andre Jackson, Victor Gonzalez, Corey Knebel, Dustin May, Jimmy Nelson | D10: 2 | E10: Tommy Kahnle, Caleb Ferguson
A11: BOS | B11: 11 | C11: Brandon Brennan, Martin Perez, Ryan Brasier, Adam Ottavino, Brandon Workman, Nathan Eovaldi, Garrett Richards, Garrett Whitlock, Raynel Espinal, Kutter Crawford, Chris Sale | D11: 0
A12: NYM | B12: 11 | C12: Jacob deGrom, Rich Hill, Carlos Carrasco, Nick Tropeano, Trevor May, Thomas Szapucki, Taijuan Walker, Anthony Banda, Drew Smith, Noah Syndergaard, Joey Lucchesi | D12: 0
A13: NYY | B13: 11 | C13: Clay Holmes, Domingo German, Jonathan Loaisiga, Andrew Heaney, Stephen Ridings, Brooks Kriske, Clarke Schmidt, Lucas Luetge, Jordan Montgomery, Jameson Taillon, Luis Severino | D13: 0
A14: TBR | B14: 11 | C14: Rich Hill, Hunter Strickland, JT Chargois, Dietrich Enns, Pete Fairbanks, Drew Rasmussen, Ryan Thompson, Brent Honeywell, Ryan Sherriff, David Robertson, Tyler Glasnow | D14: 3 | E14: Colin Poche, Yonny Chirinos, Jalen Beeks
A15: CHW | B15: 10 | C15: Lucas Giolito, Dylan Cease, Jace Fry, Aaron Bummer, Lance Lynn, Zack Burdi, Michael Kopech, Carlos Rodon, Ryan Burr, Jimmy Lambert | D15: 1 | E15: Jimmy Cordero
A16: OAK | B16: 10 | C16: Andrew Chafin, Cam Bedrosian, Cole Irvin, Burch Smith, Jesus Luzardo, Chris Bassitt, J.B. Wendelken, James Kaprielian, Daulton Jefferies, A.J. Puk | D16: 1 | E16: Trevor Rosenthal
A17: PHI | B17: 10 | C17: Vince Velasquez, Kyle Gibson, Neftali Feliz, David Paulino, Andrew Knapp, Matt Moore, Zack Wheeler, Sam Coonrod, Seranthony Dominguez, JoJo Romero | D17: 0
A18: SFG | B18: 10 | C18: Jake McGee, Alex Wood, Reyes Moronta, Tyler Chatwood, Logan Webb, Nick Tropeano, Kervin Castro, Johnny Cueto, Tyler Beede, John Brebbia | D18: 2 | E18: Dedniel Nunez, Sam Delaplane
A19: STL | B19: 10 | C19: Matt Carpenter, Tyler Webb, Giovanny Gallegos, Adam Wainwright, Justin Miller, Kodi Whitley, Kwang-hyun Kim, Alex Reyes, Jordan Hicks, Dakota Hudson | D19: 0
A20: DET | B20: 9 | C20: Wily Peralta, Drew Hutchison, Jose Cisnero, Tarik Skubal, Miguel Del Pozo, Jason Foley, Bryan Garcia, Michael Fulmer, Spencer Turnbull | D20: 1 | E20: Justin Verlander
A21: MIA | B21: 9 | C21: Pablo Lopez, Taylor Williams, Jesus Luzardo, Yimi Garcia, Jordan Holloway, Braxton Garrett, Andrew Bellatti, Zach Pop, John Curtiss | D21: 1 | E21: Jeff Brigham
A22: TEX | B22: 9 | C22: Kyle Gibson, Wes Benjamin, Drew Anderson, John King, Jharel Cotton, Kyle Cody, Dane Dunning, Matt Bush, Nick Snyder | D22: 1 | E22: Jose Leclerc
A23: HOU | B23: 8 | C23: Kent Emanuel, Blake Taylor, Yimi Garcia, Jose Urquidy, Rafael Montero, Kendall Graveman, Lance McCullers Jr., Peter Solomon | D23: 0
A24: PIT | B24: 8 | C24: Clay Holmes, Dillon Peters, Wil Crowe, Miguel Yajure, Connor Overton, Shelby Miller, Anthony Banda, Chad Kuhl | D24: 2 | E24: Blake Cederlind, Jose Soriano
A25: BAL | B25: 7 | C25: Manny Barreda, Matt Harvey, Cole Sulser, Hunter Harvey, Brooks Kriske, Zack Burdi, Tyler Wells | D25: 0
A26: KCR | B26: 7 | C26: Jesse Hahn, Scott Barlow, Danny Duffy, Gabe Speier, Domingo Tapia, Greg Holland, Richard Lovelady | D26: 0
A27: LAA | B27: 7 | C27: AJ Ramos, Packy Naughton, Hunter Strickland, Dylan Bundy, Alex Cobb, Andrew Heaney, Shohei Ohtani | D27: 0
A28: ARI | B28: 6 | C28: Joakim Soria, Taylor Clarke, J.B. Wendelken, Joe Mantiply, Corbin Martin, Chris Devenski | D28: 0
A29: CIN | B29: 6 | C29: Josh Osich, Cam Bedrosian, Art Warren, Jeff Hoffman, Jose De Leon, Tejay Antone | D29: 1 | E29: Brandon Bailey
A30: MIN | B30: 6 | C30: Andrew Albers, Danny Coulombe, Derek Law, Bailey Ober, Lewis Thorpe, Michael Pineda | D30: 0
A31: CLE | B31: 4 | C31: Cal Quantrill, Justin Garza, Zach Plesac, Sam Hentges | D31: 0
A32: COL | B32: 4 | C32: Jordan Sheffield, Chi Chi Gonzalez, Julian Fernandez, Peter Lambert | D32: 1 | E32: Scott Oberg
A33: Total | B33: 260 | D33: 22
A34: Percentage | B34: 0.30480657 | D34: 0.78571429
A35: Games Ended | B35: 44472 | D35: 44472
A37: Overall | B37: 0.32009081
A38: Games Ended | B38: 44472

Sheet MLB 2020
A1: 2020 MLB Pitchers Who Have Had TJ Surgery, By Team & Usage
A2: Team | B2: Pitchers Used | C2: Pitchers | D2: Pitchers Not Used, on IL | E2: Pitchers on IL
A3: Blue Jays | B3: 13 | C3: Hyun-Jin Ryu, Rafael Dolis, Wilmer Font, Patrick Murphy, Ryan Borucki, Ross Stripling, Brian Moran, Jordan Romano, Travis Bergen, Anthony Kay, Julian Merryweather, Taijuan Walker, Ken Giles | D3: 0
A4: Nationals | B4: 12 | C4: Anibal Sanchez, Javy Guerra, Will Harris, Stephen Strasburg, Daniel Hudson, Patrick Corbin, Erick Fedde, Wil Crowe, James Bourque, Aaron Barrett, Seth Romero, Sam Freeman | D4: 0
A5: Royals | B5: 11 | C5: Jesse Hahn, Scott Barlow, Danny Duffy, Gabe Speier, Matt Harvey, Randy Rosario, Glenn Sparkman, Greg Holland, Trevor Rosenthal, Foster Griffin, Chance Adams | D5: 0
A6: Braves | B6: 10 | C6: Mark Melancon, Shane Greene, Josh Tomlin, Max Fried, A.J. Minter, Jacob Webb, Robbie Erlin, Will Smith, Patrick Weigel, Grant Dayton | D6: 0
A7: Cubs | B7: 10 | C7: Andrew Chafin, Josh Osich, Brad Wieck, Alec Mills, Dan Winkler, Tyler Chatwood, Yu Darvish, Casey Sadler, Colin Rea, Matt Dermody | D7: 0
A8: Padres | B8: 10 | C8: Kirby Yates, Matt Strahm, Cal Quantrill, Taylor Williams, Chris Paddack, Trevor Rosenthal, Dinelson Lamet, Garrett Richards, Luis Perdomo, Mike Clevinger | D8: 2 | E8: Anderson Espinoza, Trey Wingenter
A9: Brewers | B9: 9 | C9: Ray Black, Brett Anderson, Justin Topa, Adrian Houser, Devin Williams, Drew Rasmussen, David Phelps, Brent Suter, Corey Knebel | D9: 0
A10: Marlins | B10: 9 | C10: Josh A. Smith, Jeff Brigham, Pablo Lopez, Brian Moran, Yimi Garcia, Jordan Holloway, Braxton Garrett, Brett Eibner, Brandon Leibrandt | D10: 1 | E10: Drew Steckenrider
A11: Rangers | B11: 9 | C11: Kyle Gibson, Nick Goody, Wes Benjamin, Lance Lynn, John King, Joseph Palumbo, Edinson Volquez, Rafael Montero, Kyle Cody | D11: 0
A12: Red Sox | B12: 9 | C12: Andrew Triggs, Josh Osich, Marcus Walden, Kyle Hart, Martin Perez, Ryan Brasier, Domingo Tapia, Brandon Workman, Nathan Eovaldi | D12: 1 | E12: Chris Sale
A13: White Sox | B13: 9 | C13: Lucas Giolito, Dylan Cease, Drew Anderson, Jace Fry, Aaron Bummer, Zack Burdi, Dane Dunning, Carlos Rodon, Jimmy Lambert | D13: 0
A14: Cardinals | B14: 8 | C14: Tyler Webb, Giovanny Gallegos, Adam Wainwright, Kodi Whitley, Kwang-hyun Kim, Alex Reyes, Dakota Hudson, Ricardo Sanchez | D14: 2 | E14: Jordan Hicks, John Brebbia
A15: Dodgers | B15: 8 | C15: Jake McGee, Alex Wood, Mitchell White, Ross Stripling, Brusdar Graterol, Walker Buehler, Victor Gonzalez, Caleb Ferguson | D15: 0
A16: Pirates | B16: 8 | C16: Clay Holmes, Tyler Bashlor, Miguel Del Pozo, Robbie Erlin, Nick Tropeano, Nik Turley, Chad Kuhl, Nick Burdi | D16: 1 | E16: Jameson Taillon
A17: Rays | B17: 8 | C17: Charlie Morton, John Curtiss, Peter Fairbanks, Ryan Thompson, Ryan Sherriff, Anthony Banda, Yonny Chirinos, Jalen Beeks | D17: 1 | E17: Colin Poche
A18: Yankees | B18: 8 | C18: Adam Ottavino, Jonathan Loaisiga, Brooks Kriske, Miguel Yajure, Clarke Schmidt, Ben Heller, Jordan Montgomery, Tommy Kahnle | D18: 1 | E18: Luis Severino
A19: Astros | B19: 7 | C19: Joe Biagini, Brandon Bailey, Roberto Osuna, Blake Taylor, Jose Urquidy, Lance McCullers Jr., Justin Verlander | D19: 0
A20: Athletics | B20: 7 | C20: Joakim Soria, Burch Smith, Jesus Luzardo, Chris Bassitt, J.B. Wendelken, James Kaprielian, Daulton Jefferies | D20: 1 | E20: A.J. Puk
A21: Diamondbacks | B21: 7 | C21: Andrew Chafin, Hector Rondon, Taylor Clarke, Travis Bergen, Joe Mantiply, Artie Lewicki, Silvino Bracho | D21: 1 | E21: Corbin Martin
A22: Mariners | B22: 7 | C22: Brandon Brennan, Matt Magill, Taylor Williams, Casey Sadler, Marco Gonzales, Taijuan Walker, Kendall Graveman | D22: 1 | E22: Andres Munoz
A23: Tigers | B23: 7 | C23: Jordan Zimmermann, Ivan Nova, Jose Cisnero, Anthony Castro, Tarik Skubal, Bryan Garcia, Michael Fulmer | D23: 0
A24: Twins | B24: 7 | C24: Daniel Coulombe, Rich Hill, Cory Gearrin, Lewis Thorpe, Homer Bailey, Trevor May, Michael Pineda | D24: 0
A25: Angels | B25: 6 | C25: Cam Bedrosian, Dylan Bundy, Dillon Peters, Andrew Heaney, Keynan Middleton, Shohei Ohtani | D25: 1 | E25: Justin Anderson
A26: Rockies | B26: 6 | C26: AJ Ramos, Jeff Hoffman, Joe Harvey, Jairo Diaz, Chi Chi Gonzalez, Jose Mujica | D26: 2 | E26: Scott Oberg, Peter Lambert
A27: Giants | B27: 5 | C27: Andrew Triggs, Logan Webb, Drew Smyly, Sam Coonrod, Johnny Cueto | D27: 2 | E27: Reyes Moronta, Tyler Beede
A28: Indians | B28: 5 | C28: Carlos Carrasco, Cal Quantrill, Zach Plesac, Cameron Hill, Mike Clevinger | D28: 0
A29: Mets | B29: 5 | C29: Steven Matz, Jacob deGrom, Hunter Strickland, Franklyn Kilome, Drew Smith | D29: 1 | E29: Noah Syndergaard
A30: Orioles | B30: 5 | C30: Cody Carroll, Cole Sulser, Alex Cobb, Branden Kline, Hunter Harvey | D30: 0
A31: Phillies | B31: 5 | C31: Vince Velasquez, Cole Irvin, Zack Wheeler, Brandon Workman, David Phelps | D31: 2 | E31: David Robertson, Seranthony Dominguez
A32: Reds | B32: 5 | C32: Nate Jones, Jesse Biddle, Tejay Antone, Jose De Leon, Tyler Thornburg | D32: 1 | E32: Matt Bowman
A33: Total | B33: 220 | D33: 21
A34: Percentage | B34: 0.30812325 | D34: 0.53846154
A35: Games Ended | B35: 44101 | D35: 44101
A37: Overall | B37: 0.32005312
A38: Games Ended | B38: 44101

Sheet MLB 2019
A1: 2019 MLB Pitchers Who Have Had TJ Surgery, By Team & Usage
A2: Team | B2: Pitchers Used | C2: Pitchers | D2: Pitchers Not Used, on IL | E2: Pitchers on IL
A3: Nationals | B3: 15 | C3: Anibal Sanchez, Fernando Rodney, Javy Guerra, Tony Sipp, Stephen Strasburg, Justin Miller, Hunter Strickland, Daniel Hudson, Patrick Corbin, Erick Fedde, Jonny Venters, James Bourque, Aaron Barrett, Joe Ross, Trevor Rosenthal | D3: 1 | E3: Koda Glover
A4: Angels | B4: 14 | C4: Cody Allen, Sam Freeman, Matt Ramsey, Cam Bedrosian, Jared Walsh, John Curtiss, Matt Harvey, Dillon Peters, Tyler Skaggs, Miguel Del Pozo, Andrew Heaney, Nick Tropeano, JC Ramirez, Keynan Middleton | D4: 0
A5: Blue Jays | B5: 12 | C5: Javy Guerra, Ryan Feierabend, Joe Biagini, Wilmer Font, Ryan Borucki, Daniel Hudson, Derek Law, Jordan Romano, Nick Kingham, Anthony Kay, David Phelps, Tim Mayza | D5: 0
A6: Rangers | B6: 12 | C6: Adrian Sampson, Shawn Kelley, Taylor Guerrieri, Kyle Dowdy, Jesse Biddle, Lance Lynn, Peter Fairbanks, Joseph Palumbo, Shelby Miller, Drew Smyly, Edinson Volquez, Rafael Montero | D6: 0
A7: Braves | B7: 11 | C7: Mark Melancon, Shane Greene, Arodys Vizcaino, Josh Tomlin, Dan Winkler, Max Fried, Jonny Venters, A.J. Minter, Jacob Webb, Jesse Biddle, Grant Dayton | D7: 0
A8: Giants | B8: 11 | C8: Mark Melancon, Ray Black, Sam Dyson, Reyes Moronta, Burch Smith, Travis Bergen, Logan Webb, Will Smith, Jandel Gustave, Sam Coonrod, Johnny Cueto | D8: 0
A9: White Sox | B9: 11 | C9: Josh Osich, Lucas Giolito, Manny Banuelos, Caleb Frare, Ivan Nova, Dylan Cease, Nate Jones, Jace Fry, Aaron Bummer, Carlos Rodon, Ryan Burr | D9: 1 | E9: Michael Kopech
A10: Athletics | B10: 10 | C10: Fernando Rodney, Wei-Chung Wang, Brian Schlitter, Brett Anderson, Joakim Soria, Homer Bailey, Jesus Luzardo, Chris Bassitt, J.B. Wendelken, A.J. Puk | D10: 1 | E10: Daniel Gossett
A11: Mariners | B11: 10 | C11: Hunter Strickland, Brandon Brennan, Art Warren, Connor Sadzeck, Cory Gearrin, Matt Magill, Jesse Biddle, Marco Gonzales, Nick Rumbelow, Chasen Bradford | D11: 0
A12: Padres | B12: 10 | C12: Kirby Yates, Brad Wieck, Matt Strahm, Cal Quantrill, Robbie Erlin, Chris Paddack, Dinelson Lamet, Garrett Richards, Pedro Avila, Adam Warren | D12: 0
A13: Dodgers | B13: 9 | C13: Hyun-Jin Ryu, Rich Hill, Jaime Schultz, JT Chargois, Ross Stripling, Caleb Ferguson, Walker Buehler, Casey Sadler, Yimi Garcia | D13: 0
A14: Mets | B14: 9 | C14: Steven Matz, Wilmer Font, Jacob deGrom, Brooks Pounders, Tyler Bashlor, Chris Flexen, Zack Wheeler, Jason Vargas, Ryan O'Rourke | D14: 1 | E14: Drew Smith
A15: Rockies | B15: 9 | C15: Seunghwan Oh, Jake McGee, Scott Oberg, Harrison Musgrave, Tim Melville, Jeff Hoffman, Joe Harvey, Jairo Diaz, Chi Chi Gonzalez | D15: 0
A16: Tigers | B16: 9 | C16: Shane Greene, Drew VerHagen, Jordan Zimmermann, Matt Moore, Jose Cisnero, Eduardo Jimenez, Zac Reininger, Trevor Rosenthal, Bryan Garcia | D16: 1 | E16: Michael Fulmer
A17: Twins | B17: 9 | C17: Sam Dyson, Kyle Gibson, Martin Perez, Fernando Romero, Lewis Thorpe, Matt Magill, Brusdar Graterol, Trevor May, Michael Pineda | D17: 0
A18: Brewers | B18: 8 | C18: Alex Wilson, Ray Black, Aaron Wilkerson, Burch Smith, Taylor Williams, Adrian Houser, Devin Williams, Brent Suter | D18: 1 | E18: Corey Knebel
A19: Rays | B19: 8 | C19: Wilmer Font, Charlie Morton, Colin Poche, Cole Sulser, Casey Sadler, Peter Fairbanks, Jose De Leon, Anthony Banda | D19: 0
A20: Royals | B20: 8 | C20: Wily Peralta, Jesse Hahn, Scott Barlow, Danny Duffy, Gabe Speier, Randy Rosario, Homer Bailey, Glenn Sparkman | D20: 1 | E20: Trevor Oaks
A21: Yankees | B21: 8 | C21: Cory Gearrin, Domingo German, Adam Ottavino, Joe Harvey, Jonathan Loaisiga, Joe Mantiply, Ben Heller, Jordan Montgomery | D21: 0
A22: Astros | B22: 7 | C22: Will Harris, Joe Biagini, Hector Rondon, Roberto Osuna, Jose Urquidy, Brady Rodgers, Corbin Martin | D22: 1 | E22: Lance McCullers Jr.
A23: Cubs | B23: 7 | C23: Brad Wieck, Alec Mills, Randy Rosario, Tyler Chatwood, Yu Darvish, Tim Collins, David Phelps | D23: 1 | E23: Kendall Graveman
A24: Indians | B24: 7 | C24: Dan Otero, Danny Salazar, Carlos Carrasco, Mike Clevinger, Nick Goody, Zach Plesac, Cody Anderson | D24: 0
A25: Orioles | B25: 7 | C25: Chandler Shepherd, Josh Lucas, Dylan Bundy, Alex Cobb, Branden Kline, Hunter Harvey, Josh Rogers | D25: 0
A26: Phillies | B26: 7 | C26: Pat Neshek, Vince Velasquez, Cole Irvin, Drew Anderson, Jason Vargas, Drew Smyly, David Robertson | D26: 0
A27: Pirates | B27: 7 | C27: Francisco Liriano, Wei-Chung Wang, Clay Holmes, James Marvel, Nick Kingham, Nick Burdi, Jameson Taillon | D27: 2 | E27: Chad Kuhl, Edgar Santana
A28: Marlins | B28: 6 | C28: Wei-Yin Chen, Hector Noesi, Jeff Brigham, Drew Steckenrider, Pablo Lopez, Brian Moran | D28: 1 | E28: Julian Fernandez
A29: Red Sox | B29: 6 | C29: Josh A. Smith, Marcus Walden, Ryan Brasier, Brandon Workman, Nathan Eovaldi, Steven Wright | D29: 0
A30: Cardinals | B30: 5 | C30: Tyler Webb, Giovanny Gallegos, Adam Wainwright, Alex Reyes, Jordan Hicks | D30: 0
A31: Diamondbacks | B31: 4 | C31: Andrew Chafin, Taylor Clarke, Greg Holland, Taijuan Walker | D31: 1 | E31: Silvino Bracho
A32: Reds | B32: 3 | C32: Alex Wood, David Hernandez, Zach Duke | D32: 0
A33: Total | B33: 230 | D33: 13
A34: Percentage | B34: 0.29831388 | D34: 0.68421053
A35: Games Ended | B35: 43737 | D35: 43737
A37: Overall | B37: 0.30759494
A38: Games Ended | B38: 43737

Sheet MLB 2018
A1: 2018 MLB Pitchers Who Have Had TJ Surgery, By Team & Usage | F1: Pitcher Used in 2018 | G1: Team | H1: playerid | I1: TJ
A2: Team | B2: Pitchers Used | C2: Pitchers | D2: Pitchers Not Used, on DL | E2: Pitchers on DL | F2: Wilmer Font | G2: - - - | H2: 5257 | I2: 40452
A3: Dodgers | B3: 14 | C3: John Axford, Hyun-Jin Ryu, Erik Goeddel, Adam Liberatore, Alex Wood, Wilmer Font, Rich Hill, Ryan Madson, Daniel Hudson, J.T. Chargois, Ross Stripling, Caleb Ferguson, Walker Buehler, Yimi Garcia | D3: 0 | F3: George Kontos | G3: - - - | H3: 9486 | I3: 40001
A4: Athletics | B4: 12 | C4: Fernando Rodney, Andrew Triggs, Shawn Kelley, Wilmer Font, Josh Lucas, Daniel Coulombe, Brett Anderson, Cory Gearrin, Chris Bassitt, J.B. Wendelken, Kendall Graveman, Daniel Gossett | D4: 1 | E4: Jharel Cotton | F4: Cory Gearrin | G4: - - - | H4: 7947 | I4: 41745
A5: Braves | B5: 12 | C5: Anibal Sanchez, Miguel Socolovich, Sam Freeman, Arodys Vizcaino, Peter Moylan, Dan Winkler, Max Fried, Jonny Venters, A.J. Minter, Brandon McCarthy, Chase Whitley, Jesse Biddle | D5: 2 | E5: Grant Dayton, Jacob Lindgren | F5: Seung Hwan Oh | G5: - - - | H5: 18719 | I5: 36892
A6: Angels | B6: 11 | C6: Junichi Tazawa, Cam Bedrosian, Tyler Skaggs, Andrew Heaney, Nick Tropeano, JC Ramirez, Keynan Middleton, Blake Wood, John Lamb, Garrett Richards, Shohei Ohtani | D6: 0 | F6: John Axford | G6: - - - | H6: 9059 | I6: 37930
A7: Giants | B7: 11 | C7: Mark Melancon, Ray Black, Josh Osich, Sam Dyson, Reyes Moronta, Casey Kelly, Hunter Strickland, Cory Gearrin, Derek Law, Will Smith, Johnny Cueto | D7: 1 | E7: Julian Fernandez | F7: Fernando Rodney | G7: - - - | H7: 494 | I7: 38106
A8: Nationals | B8: 10 | C8: Shawn Kelley, Stephen Strasburg, Koda Glover, Sammy Solis, Justin Miller, Ryan Madson, Erick Fedde, Greg Holland, Tim Collins, Joe Ross | D8: 0 | F8: Erik Goeddel | G8: - - - | H8: 11712 | I8: 39083
A9: Blue Jays | B9: 9 | C9: Seung Hwan Oh, John Axford, Jaime Garcia, Joe Biagini, Ryan Borucki, David Paulino, Taylor Guerrieri, Roberto Osuna, Brandon Cumpton | D9: 0 | F9: Tyler Webb | G9: - - - | H9: 14974 | I9: 39448
A10: Pirates | B10: 9 | C10: George Kontos, Clay Holmes, Jameson Taillon, Ivan Nova, Nick Kingham, Casey Sadler, Nick Burdi, Chad Kuhl, Edgar Santana | D10: 1 | E10: Nik Turley | F10: Jaime Garcia | G10: - - - | H10: 8137 | I10: 39699
A11: White Sox | B11: 9 | C11: Miguel Gonzalez, Joakim Soria, Lucas Giolito, Caleb Frare, Bruce Rondon, Nate Jones, Jace Fry, Aaron Bummer, Michael Kopech | D11: 0 | F11: George Kontos | G11: - - - | H11: 9486 | I11: 40001
A12: Marlins | B12: 8 | C12: Javy Guerra, Wei-Yin Chen, Junichi Tazawa, Jeff Brigham, Drew Steckenrider, Pablo Lopez, Dillon Peters, Tyler Cloyd | D12: 0 | F12: Junichi Tazawa | G12: - - - | H12: 4079 | I12: 40274
A13: Mets | B13: 8 | C13: AJ Ramos, Steven Matz, Jacob deGrom, Matt Harvey, Tyler Bashlor, Chris Flexen, Zack Wheeler, Jason Vargas | D13: 1 | E13: Rafael Montero | F13: Shawn Kelley | G13: - - - | H13: 7773 | I13: 40422
A14: Rangers | B14: 8 | C14: Matt Bush, Adrian Sampson, Drew Hutchison, Connor Sadzeck, Cory Gearrin, Matt Moore, Martin Perez, Ricardo Rodriguez | D14: 1 | E14: Clayton Blackburn | F14: Wilmer Font | G14: - - - | H14: 5257 | I14: 40452
A15: Tigers | B15: 8 | C15: Francisco Liriano, Alex Wilson, Shane Greene, Drew VerHagen, Jordan Zimmermann, Chad Bell, Zac Reininger, Artie Lewicki | D15: 0 | F15: Jorge De La Rosa | G15: - - - | H15: 2047 | I15: 40697
A16: Twins | B16: 8 | C16: Fernando Rodney, Kyle Gibson, John Curtiss, Fernando Romero, Matt Magill, Lance Lynn, Zach Duke, Trevor May | D16: 1 | E16: Michael Pineda | F16: Joakim Soria | G16: - - - | H16: 6941 | I16: 41001
A17: Brewers | B17: 7 | C17: Alec Asher, Mike Zagurski, Aaron Wilkerson, Joakim Soria, Taylor Williams, Adrian Houser, Brent Suter | D17: 0 | F17: Ryan Madson | G17: - - - | H17: 1852 | I17: 41010
A18: Cubs | B18: 7 | C18: Brian Duensing, Jaime Garcia, Jorge De La Rosa, Alec Mills, Randy Rosario, Tyler Chatwood, Yu Darvish | D18: 1 | E18: Drew Smyly | F18: Drew Hutchison | G18: - - - | H18: 10732 | I18: 41130
A19: Indians | B19: 7 | C19: Cody Allen, Dan Otero, George Kontos, Carlos Carrasco, Mike Clevinger, Josh Tomlin, Nick Goody | D19: 2 | E19: Cody Anderson, Danny Salazar | F19: Roberto Osuna | G19: - - - | H19: 13764 | I19: 41485
A20: Rockies | B20: 7 | C20: Seung Hwan Oh, Jake McGee, Scott Oberg, Harrison Musgrave, Brooks Pounders, Jeff Hoffman, Adam Ottavino | D20: 0 | F20: Matt Harvey | G20: - - - | H20: 11713 | I20: 41569
A21: Astros | B21: 7 | C21: Tony Sipp, Will Harris, Hector Rondon, Dean Deetz, Charlie Morton, Roberto Osuna, Joe Smith | D21: 1 | E21: Jandel Gustave | F21: Cory Gearrin | G21: - - - | H21: 7947 | I21: 41745
A22: Cardinals | B22: 6 | C22: Tyler Webb, Giovanny Gallegos, Adam Wainwright, Greg Holland, Alex Reyes, Ryan Sherriff | D22: 0 | F22: Jonny Venters | G22: - - - | H22: 7175 | I22: 41899
A23: Diamondbacks | B23: 6 | C23: Andrew Chafin, Jorge De La Rosa, Kris Medlen, Patrick Corbin, Shelby Miller, Taijuan Walker | D23: 0 | F23: Greg Holland | G23: - - - | H23: 7196 | I23: 42279
A24: Royals | B24: 6 | C24: Wily Peralta, Trevor Oaks, Scott Barlow, Danny Duffy, Burch Smith, Glenn Sparkman | D24: 1 | E24: Jesse Hahn | F24: Lance Lynn | G24: - - - | H24: 2520 | I24: 42318
A25: Yankees | B25: 6 | C25: George Kontos, Giovanny Gallegos, Domingo German, Lance Lynn, Jonathan Loaisiga, Jordan Montgomery | D25: 1 | E25: Ben Heller | F25: Nathan Eovaldi | G25: - - - | H25: 9132 | I25: 42601
A26: Mariners | B26: 5 | C26: Erik Goeddel, Marco Gonzales, Nick Rumbelow, Zach Duke, Ryan Cook | D26: 1 | E26: David Phelps | F26: Zach Duke | G26: - - - | H26: 3840 | I26: 42650
A27: Padres | B27: 5 | C27: Kirby Yates, Tyler Webb, Brad Wieck, Matt Strahm, Robbie Erlin | D27: 1 | E27: Dinelson Lamet | F27: Giovanny Gallegos | G27: - - - | H27: 14986 | I27: 40544
A28: Rays | B28: 5 | C28: Jaime Schultz, Wilmer Font, Jonny Venters, Nathan Eovaldi, Anthony Banda | D28: 2 | E28: Jose De Leon, Jose Mujica
A29: Red Sox | B29: 5 | C29: Marcus Walden, Ryan Brasier, Brandon Workman, Carson Smith, Nathan Eovaldi | D29: 0
A30: Orioles | B30: 4 | C30: Cody Carroll, Josh Rogers, Dylan Bundy, Alex Cobb | D30: 0
A31: Phillies | B31: 4 | C31: Pat Neshek, Vince Velasquez, Drew Hutchison, Drew Anderson | D31: 0
A32: Reds | B32: 4 | C32: Matt Harvey, David Hernandez, Homer Bailey, Kevin Shackelford | D32: 0
A33: Total | B33: 202 | D33: 18
A34: Percentage | B34: 0.27114094 | D34: 0.69230769
A35: Games Ended | B35: 43374 | D35: 43374
A37: Overall | B37: 0.28534371
A38: Games Ended | B38: 43374

Sheet MLB 2017
A1: 2017 MLB Pitchers Who Have Had TJ Surgery, By Team & Usage | F1: Pitcher Used in 2017 | G1: Team | H1: playerid | I1: TJ
A2: Team | B2: Pitchers Used | C2: Pitchers | D2: Pitchers Not Used, on DL | E2: Pitchers on DL | F2: Jason Grilli | G2: - - - | H2: 521 | I2: 37257
A3: Dodgers | B3: 10 | C3: Hyun-Jin Ryu, Adam Liberatore, Alex Wood, Wilmer Font, Rich Hill, Ross Stripling, Yu Darvish, Brandon McCarthy, Walker Buehler, Grant Dayton | D3: 1 | E3: Yimi Garcia | F3: Kirby Yates | G3: - - - | H3: 9073 | I3: 38718
A4: Giants | B4: 10 | C4: Bryan Morris, Mark Melancon, Albert Suarez, George Kontos, Josh Osich, Sam Dyson, Hunter Strickland, Cory Gearrin, Matt Moore, Derek Law | D4: 1 | E4: Will Smith | F4: Francisco Liriano | G4: - - - | H4: 3201 | I4: 39027
A5: Tigers | B5: 10 | C5: Anibal Sanchez, Alex Wilson, Shane Greene, Drew VerHagen, Jordan Zimmermann, Jeff Ferrell, Artie Lewicki, Chad Bell, Bruce Rondon, Zac Reininger | D5: 0 | F5: Tyler Webb | G5: - - - | H5: 14974 | I5: 39448
A6: Braves | B6: 9 | C6: Jaime Garcia, Sam Freeman, Jason Hursh, Arodys Vizcaino, Jason Motte, Eric O'Flaherty, Daniel Winkler, Max Fried, A.J. Minter | D6: 1 | E6: Jacob Lindgren | F6: A.J. Ramos | G6: - - - | H6: 8350 | I6: 39568
A7: Marlins | B7: 9 | C7: Dustin McGowan, Javy Guerra, Wei-Yin Chen, Brian Ellington, A.J. Ramos, Junichi Tazawa, Drew Steckenrider, Dillon Peters, Edinson Volquez | D7: 0 | F7: Jaime Garcia | G7: - - - | H7: 8137 | I7: 39699
A8: White Sox | B8: 9 | C8: Al Alburquerque, Miguel Gonzalez, Michael Ynoa, Mike Pelfrey, Lucas Giolito, Nate Jones, Jace Fry, Aaron Bummer, Zach Putnam | D8: 0 | F8: Pat Neshek | G8: - - - | H8: 4682 | I8: 39763
A9: Angels | B9: 8 | C9: Andrew Bailey, Kirby Yates, Cam Bedrosian, Blake Wood, Brooks Pounders, David Hernandez, Tyler Skaggs, Andrew Heaney | D9: 1 | E9: Nick Tropeano | F9: George Kontos | G9: - - - | H9: 9486 | I9: 40001
A10: Athletics | B10: 8 | C10: John Axford, Josh Smith, Andrew Triggs, Jesse Hahn, Daniel Coulombe, Ryan Madson, Simon Castro, Raul Alcantara | D10: 0 | F10: Sam Dyson | G10: - - - | H10: 11710 | I10: 40483
A11: Cardinals | B11: 8 | C11: Seung Hwan Oh, Miguel Socolovich, Josh Lucas, Adam Wainwright, Lance Lynn, Marco Gonzales, Zach Duke, Trevor Rosenthal | D11: 1 | E11: Alex Reyes | F11: Brett Anderson | G11: - - - | H11: 8223 | I11: 40738
A12: Mets | B12: 8 | C12: Erik Goeddel, A.J. Ramos, Jacob deGrom, Steven Matz, Matt Harvey, Chris Flexen, Josh Edgin, Zack Wheeler | D12: 0 | F12: Ryan Madson | G12: - - - | H12: 1852 | I12: 41010
A13: Rangers | B13: 8 | C13: Jason Grilli, Matt Bush, Miguel Gonzalez, Sam Dyson, A.J. Griffin, Martin Perez, Ricardo Rodriguez, Yu Darvish | D13: 1 | E13: Chi Chi Gonzalez | F13: Blake Wood | G13: - - - | H13: 1345 | I13: 41054
A14: Rockies | B14: 8 | C14: Jake McGee, Pat Neshek, Scott Oberg, Jeff Hoffman, Tyler Chatwood, Adam Ottavino, Greg Holland, Jairo Diaz | D14: 0 | F14: Neftali Feliz | G14: - - - | H14: 18 | I14: 41122
A15: Royals | B15: 8 | C15: Al Alburquerque, Joakim Soria, Danny Duffy, Neftali Feliz, Matt Strahm, Peter Moylan, Andres Machado, Jason Vargas | D15: 0 | F15: Dillon Overton | G15: - - - | H15: 15627 | I15: 41456
A16: Astros | B16: 7 | C16: Francisco Liriano, Tony Sipp, Will Harris, Dayan Diaz, Charlie Morton, David Paulino, Jandel Gustave | D16: 1 | E16: Brady Rodgers | F16: David Hernandez | G16: - - - | H16: 4259 | I16: 41730
A17: Blue Jays | B17: 7 | C17: Jason Grilli, Francisco Liriano, Joe Biagini, Brett Anderson, Leonel Campos, Roberto Osuna, Glenn Sparkman | D17: 1 | E17: Bo Schultz | F17: Yu Darvish | G17: - - - | H17: 13074 | I17: 42080
A18: Diamondbacks | B18: 7 | C18: Fernando Rodney, Andrew Chafin, Jorge de la Rosa, Patrick Corbin, David Hernandez, Shelby Miller, Rubby de la Rosa | D18: 0 | F18: Marco Gonzales | G18: - - - | H18: 15467 | I18: 42475
A19: Indians | B19: 7 | C19: Cody Allen, Dan Otero, Danny Salazar, Carlos Carrasco, Mike Clevinger, Josh Tomlin, Nick Goody | D19: 2 | E19: Dylan Baker, Cody Anderson | F19: Jack Leathersich | G19: - - - | H19: 12562 | I19: 42215
A20: Nationals | B20: 7 | C20: Shawn Kelley, Stephen Strasburg, Koda Glover, Sammy Solis, Ryan Madson, Erick Fedde, Joe Ross | D20: 0 | F20: Miguel Gonzalez | G20: - - - | H20: 7024 | I20: 39880
A21: Twins | B21: 7 | C21: Jaime Garcia, Kyle Gibson, John Curtiss, Alex Wimmers, Tim Melville, Randy Rosario, Dietrich Enns | D21: 3 | E21: J.T. Chargois, Trevor May, Ryan O'Rourke | F21: Al Alburquerque | G21: - - - | H21: 6324 | I21: 38353
A22: Brewers | B22: 6 | C22: Wily Peralta, Tyler Webb, Wei-Chung Wang, Aaron Wilkerson, Neftali Feliz, Taylor Williams | D22: 0 | F22: Tim Melville | G22: - - - | H22: 9149 | I22: 41183
A23: Pirates | B23: 6 | C23: George Kontos, Daniel Hudson, Jameson Taillon, Ivan Nova, Jack Leathersich, Angel Sanchez | D23: 0 | F23: Jaime Garcia | G23: - - - | H23: 8137 | I23: 39699
A24: Reds | B24: 6 | C24: Scott Feldman, Blake Wood, Bronson Arroyo, Lisalverto Bonilla, Homer Bailey, Drew Storen | D24: 0
A25: Cubs | B25: 5 | C25: Brian Duensing, Hector Rondon, Brett Anderson, John Lackey, Jack Leathersich | D25: 0
A26: Mariners | B26: 5 | C26: Andrew Albers, Dillon Overton, Shae Simmons, Marco Gonzales, Tyler Cloyd | D26: 1 | E26: Drew Smyly
A27: Phillies | B27: 5 | C27: Pedro Beato, Pat Neshek, Vince Velasquez, Drew Anderson, Jesen Therrien | D27: 0
A28: Yankees | B28: 5 | C28: Tyler Webb, Jaime Garcia, Giovanny Gallegos, Domingo German, Michael Pineda | D28: 0
A29: Padres | B29: 4 | C29: Kirby Yates, Tim Melville, Dillon Overton, Carter Capps | D29: 2 | E29: Robbie Erlin, Colin Rea
A30: Rays | B30: 4 | C30: Jumbo Diaz, Diego Moreno, Alex Cobb, Chase Whitley | D30: 3 | E30: Taylor Guerrieri, Nathan Eovaldi, Shawn Tolleson
A31: Orioles | B31: 2 | C31: Alec Asher, Dylan Bundy | D31: 0
A32: Red Sox | B32: 2 | C32: Brandon Workman, Carson Smith | D32: 0
A33: Total | B33: 183 | D33: 19
A34: Percentage | B34: 0.25 | D34: 0.704
A35: Games Ended | B35: 43009 | D35: 43009
A37: Overall | B37: 0.259
A38: Games Ended | B38: 43009

Sheet MLB 2016
A1: 2016 MLB Pitchers Who Have Had TJ Surgery, By Team & Usage
A2: Team | B2: Pitchers Used | C2: Pitchers | D2: Pitchers Not Used, on DL | E2: Pitchers on DL
A3: Reds | B3: 13 | C3: Steve Delabar, Jumbo Diaz, Josh Smith, Dayan Diaz, Alfredo Simon, Layne Somsen, A.J. Morris, John Lamb, Blake Wood, Tim Melville, Matt Magill, Homer Bailey, Jon Moscot | D3: 0
A4: Athletics | B4: 11 | C4: John Axford, Andrew Triggs, Jesse Hahn, Daniel Coulombe, Rich Hill, Ryan Madson, Eric Surkamp, Fernando Rodriguez, Dillon Overton, Raul Alcantara, Chris Bassitt | D4: 2 | E4: Jarrod Parker, Felix Doubront
A5: Royals | B5: 10 | C5: Edinson Volquez, Joakim Soria, Danny Duffy, Matt Strahm, Alec Mills, Brooks Pounders, Luke Hochevar, Kris Medlen, Peter Moylan, Jason Vargas | D5: 1 | E5: Tim Collins
A6: Tigers | B6: 10 | C6: Anibal Sanchez, Dustin Molleken, Logan Kensing, Alex Wilson, Shane Greene, Drew VerHagen, Jordan Zimmermann, Mike Pelfrey, Bruce Rondon, Bobby Parnell | D6: 0
A7: Blue Jays | B7: 9 | C7: Jason Grilli, Scott Feldman, Francisco Liriano, Joseph Biagini, Arnold Leon, Dustin Antolin, Drew Hutchison, Gavin Floyd, Roberto Osuna | D7: 0
A8: Braves | B8: 9 | C8: Jason Grilli, Matt Marksberry, Jason Hursh, Arodys Vizcaino, Casey Kelly, Eric O'Flaherty, Chris Withrow, Daniel Winkler, Shae Simmons | D8: 3 | E8: Paco Rodriguez, Jesse Biddle, Andrew McKirahan
A9: Giants | B9: 9 | C9: Albert Suarez, George Kontos, Josh Osich, Hunter Strickland, Matt Reynolds, Cory Gearrin, Matt Moore, Derek Law, Joe Nathan | D9: 1 | E9: Raymond Black
A10: Indians | B10: 9 | C10: Jeff Manship, Cody Allen, Dan Otero, Joseph Colon, Danny Salazar, Joba Chamberlain, Carlos Carrasco, Mike Clevinger, Josh Tomlin | D10: 0
A11: Marlins | B11: 9 | C11: Chris Narveson, Jo-Jo Reyes, Fernando Rodney, Dustin McGowan, Wei-Yin Chen, Bryan Morris, Brian Ellington, A.J. Ramos, Jose Fernandez | D11: 0
A12: Pirates | B12: 9 | C12: Ryan Vogelsong, Mark Melancon, Francisco Liriano, Arquimedes Caminero, Neftali Feliz, Drew Hutchison, Cory Luebke, Jameson Taillon, Ivan Nova | D12: 0
A13: Dodgers | B13: 8 | C13: Chin-hui Tsao, Hyun-Jin Ryu, Adam Liberatore, Alex Wood, Rich Hill, Brett Anderson, Ross Stripling, Brandon McCarthy | D13: 0
A14: Rockies | B14: 8 | C14: Jake McGee, Scott Oberg, Jorge de la Rosa, Justin Miller, Jason Motte, Jeff Hoffman, Tyler Chatwood, Adam Ottavino | D14: 1 | E14: Jairo Diaz
A15: Angels | B15: 7 | C15: Al Alburquerque, Javy Guerra, Andrew Bailey, Cam Bedrosian, Tyler Skaggs, Andrew Heaney, Nick Tropeano | D15: 1 | E15: C.J. Wilson
A16: Diamondbacks | B16: 7 | C16: Keith Hessler, Andrew Chafin, Rubby de la Rosa, Kyle Drabek, Daniel Hudson, Patrick Corbin, Vicente Campos | D16: 0
A17: Nationals | B17: 7 | C17: Mark Melancon, Shawn Kelley, Stephen Strasburg, Koda Glover, Sammy Solis, Lucas Giolito, Sean Burnett | D17: 1 | E17: Aaron Barrett
A18: Phillies | B18: 7 | C18: Andrew Bailey, Alec Asher, Elvis Araujo, Vince Velasquez, Charlie Morton, Frank Herrmann, David Hernandez | D18: 0
A19: Rangers | B19: 7 | C19: Colby Lewis, Shawn Tolleson, Matt Bush, Sam Dyson, A.J. Griffin, Martin Perez, Yu Darvish | D19: 0
A20: Astros | B20: 6 | C20: Scott Feldman, Tony Sipp, Kevin Chapman, Pat Neshek, Will Harris, David Paulino | D20: 0
A21: White Sox | B21: 6 | C21: Miguel Gonzalez, Michael Ynoa, Scott Carroll, Matt Purke, Nate Jones, Daniel Webb | D21: 0
A22: Yankees | B22: 6 | C22: Kirby Yates, Conor Mullee, Nick Goody, Ivan Nova, Branden Pinder, Nathan Eovaldi | D22: 1 | E22: Nick Rumbelow
A23: Mets | B23: 5 | C23: Erik Goeddel, Jacob deGrom, Steven Matz, Matt Harvey, Josh Edgin | D23: 1 | E23: Zack Wheeler
A24: Padres | B24: 5 | C24: Matt Thornton, Fernando Rodney, Keith Hessler, Leonel Campos, Robbie Erlin | D24: 1 | E24: Carter Capps
A25: Rays | B25: 5 | C25: Eddie Gamboa, Tyler Sturdevant, Matt Moore, Alex Cobb, Chase Whitley | D25: 0
A26: Cardinals | B26: 4 | C26: Seung Hwan Oh, Miguel Socolovich, Jaime Garcia, Adam Wainwright | D26: 1 | E26: Lance Lynn
A27: Twins | B27: 4 | C27: Andrew Albers, Kyle Gibson, Alex Wimmers, J.T. Chargois | D27: 0
A28: Brewers | B28: 3 | C28: Wily Peralta, Chris Capuano, Sam Freeman | D28: 1 | E28: Sean Nolin
A29: Cubs | B29: 3 | C29: Hector Rondon, John Lackey, Joe Nathan | D29: 1 | E29: Dallas Beeler
A30: Mariners | B30: 3 | C30: Adrian Sampson, Arquimedes Caminero, Joe Wieland | D30: 2 | E30: Charlie Furbush, Ryan Cook
A31: Orioles | B31: 2 | C31: Brian Duensing, Dylan Bundy | D31: 0
A32: Red Sox | B32: 2 | C32: Junichi Tazawa, Carson Smith | D32: 1 | E32: Brandon Workman
A33: Total | B33: 190 | D33: 19
A34: Percentage | B34: 0.26388889 | D34: 0.65517241
A35: Games Ended | B35: 42645 | D35: 42645
A37: Overall | B37: 0.27427822
A38: Games Ended | B38: 42645

Sheet D1 Colleges
A1: Player | B1: TJ Surgery Date | C1: Team | D1: Level | E1: Position | F1: Throws | G1: Return Date (same level) | H1: Recovery Time (months) | I1: Surgeon(s) | J1: Done
A2: Peyton Prescott | B2: 45839 | C2: Florida State | D2: SO | E2: P | F2: R
A3: Brayden Jones | B3: 45778 | C3: Ole Miss | D3: JR | E3: P | F3: R
A4: Evan Smith | B4: 45778 | C4: Maryland | D4: SO | E4: P | F4: L | I4: Dr. Christopher Ahmad
A5: Braden Osbolt | B5: 45770 | C5: Kennesaw State | D5: JR | E5: P | F5: R
A6: Mason McConnaughey | B6: 45748 | C6: Nebraska | D6: JR | E6: P | F6: R
A7: Dane Moehler | B7: 45689 | C7: Clemson | D7: FR | E7: P | F7: R
A8: AJ Russell | B8: 45454 | C8: Tennessee | D8: SO | E8: P | F8: R | G8: 45713 | H8: =ROUND(((G8-B8)/365)*12,0) -> 9
A9: Shane Van Dam | B9: 45413 | C9: NC State | D9: SO | E9: P | F9: R
A10: Patrick Steitz | B10: 45383 | C10: Kansas | D10: JR | E10: P | F10: R | G10: 45704 | H10: =ROUND(((G10-B10)/365)*12,0) -> 11
A11: Aiden Jimenez | B11: 45356 | C11: Arkansas | D11: SO | E11: P | F11: R | G11: 45702 | H11: =ROUND(((G11-B11)/365)*12,0) -> 11
A12: Bradley Hodges | B12: 45356 | C12: Virginia | D12: SO | E12: P | F12: L
A13: Matt Willadsen | B13: 45352 | C13: North Carolina State | D13: SR | E13: P | F13: R
A14: Gavin Adams | B14: 45352 | C14: Florida State | D14: JR | E14: P | F14: R
A15: Riley Quick | B15: 45342 | C15: Alabama | D15: SO | E15: P | F15: R
A16: Alex Bouchard | B16: 45323 | C16: Lehigh | D16: JR | E16: P | F16: R
A17: Xavier Rivas | B17: 45323 | C17: Ole Miss | D17: SR | E17: P | F17: L
A18: Cooper Dossett | B18: 45292 | C18: Arkansas | D18: JR | E18: P | F18: R
A19: Joey Gartrell | B19: 45292 | C19: Portland | D19: JR | E19: P | F19: R
A20: Shane Sdao | B20: 45292 | C20: Texas A&M | D20: JR | E20: P | F20: L
A21: Renzo Gonazlez | B21: 45292 | C21: Miami | D21: JR | E21: P | F21: L
A22: Evan Kleinhans | B22: 45292 | C22: Columbia | D22: SO | E22: P | F22: R | G22: 45710
A23: Jake Knapp | B23: 45292 | C23: North Carolina | D23: JR | E23: P | F23: R | G23: 45702
A24: Finnegan Wall | B24: 45292 | C24: UC Irvine | D24: JR | E24: P | F24: R
A25: Garrett Horn | B25: 45292 | C25: Liberty | D25: JR | E25: P | F25: L
A26: Kyle Ayers | B26: 45292 | C26: Texas Christian | D26: JR | E26: P | F26: R
A27: Ryan Szczepaniak | B27: 45147 | C27: Michigan State | D27: SO | E27: P | F27: R
A28: Josh Hyneman | B28: 45135 | C28: Arkansas | D28: FR | E28: P | F28: R | I28: Dr. Keith Meister
A29: Tate Farquhar | B29: 45114 | C29: Michigan State | D29: FR | E29: P | F29: R
A30: Ryan Brown | B30: 45106 | C30: Ball State | D30: JR | E30: P | F30: R | I30: Dr. Jeffrey Dugas
A31: Kyle McCoy | B31: 45104 | C31: Maryland | D31: FR | E31: P | F31: L
A32: Eli Jerzembeck | B32: 45076 | C32: South Carolina | D32: FR | E32: P | F32: R
A33: Hunter Elliott | B33: 45049 | C33: Ole Miss | D33: FR | E33: P | F33: L
A34: Grayson Hitt | B34: 45047 | C34: Alabama | D34: JR | E34: P | F34: L
A35: Dylan Carter | B35: 45047 | C35: Arkansas | D35: SO | E35: P | F35: R | G35: 45361 | H35: =ROUND(((G35-B35)/365)*12,0) -> 10
A36: Connor Lockwood | B36: 45044 | C36: Valparaiso | D36: SO | E36: P | F36: R
A37: Garrett Edwards | B37: 45042 | C37: LSU | D37: JR | E37: P | F37: R | I37: Dr. Keith Meister
A38: Wyatt Crowell | B38: 45029 | C38: Florida State | D38: JR | E38: P | F38: L
A39: Jack Findlay | B39: 45017 | C39: Notre Dame | D39: JR | E39: P | F39: L
A40: Matthew Hoskins | B40: 45017 | C40: Georgia | D40: FR | E40: P | F40: R
A41: Christian Worley | B41: 45017 | C41: Virginia Tech | D41: JR | E41: P | F41: R
A42: Chase Shores | B42: 45017 | C42: LSU | D42: FR | E42: P | F42: R
A43: Pico Kohn | B43: 45017 | C43: Arkansas | D43: SO | E43: P | F43: L
A44: Jaxon Wiggins | B44: 44979 | C44: Arkansas | D44: JR | E44: P | F44: R | I44: Dr. Keith Meister
A45: Grant Taylor | B45: 44958 | C45: LSU | D45: SO | E45: P | F45: R
A46: Tanner Gresham | B46: 44927 | C46: Army | D46: JR | E46: P | F46: R | G46: 45409
A47: Ashton Crowther | B47: 44927 | C47: Miami | D47: FR | E47: P | F47: L
A48: Myles Caba | B48: 44927 | C48: Miami | D48: JR | E48: P | F48: L
A49: Owen Puk | B49: 44927 | C49: Florida International | D49: SO | E49: P | F49: R
A50: Josh Mallitz | B50: 44894 | C50: Ole Miss | D50: SO | E50: P | F50: R
A51: Roman Kimball | B51: 44881 | C51: South Carolina | D51: FR | E51: P | F51: R | I51: Dr. Keith Meister
A52: Ryan Prager | B52: 44805 | C52: Texas A&M | D52: SO | E52: P | F52: L | G52: 45338 | H52: =ROUND(((G52-B52)/365)*12,0) -> 18
A53: Antoine Jean | B53: 44743 | C53: Alabama | D53: SR | E53: P | F53: L
A54: Bo Bonds | B54: 44713 | C54: Louisiana | D54: SO | E54: P | F54: R
A55: Riley Maddox | B55: 44698 | C55: Ole Miss | D55: FR | E55: P | F55: R | G55: 44982 | H55: =ROUND(((G55-B55)/365)*12,0) -> 9 | I55: Dr. Jeffrey Dugas
A56: Hunter Barco | B56: 44682 | C56: Florida | D56: SO | E56: P | F56: L
A57: Brooks Auger | B57: 44682 | C57: Mississippi State | D57: SO | E57: P | F57: R
A58: Tyler Thomas | B58: 44682 | C58: Baylor | D58: SR | E58: P | F58: L
A59: Ryan McLinskey | B59: 44682 | C59: Notre Dame | D59: SR | E59: P | F59: R
A60: Darren Williams | B60: 44652 | C60: Kentucky | D60: SR | E60: P | F60: R | G60: 44974 | H60: =ROUND(((G60-B60)/365)*12,0) -> 11
A61: Hunter Patteson | B61: 44652 | C61: UCF | D61: SO | E61: P | F61: L
A62: Stone Simmons | B62: 44636 | C62: Mississippi State | D62: JR | E62: P | F62: R
A63: James Hicks | B63: 44624 | C63: South Carolina | D63: JR | E63: P | F63: R
A64: Javen Coleman | B64: 44621 | C64: LSU | D64: SO | E64: P | F64: L | G64: 45034 | H64: =ROUND(((G64-B64)/365)*12,0) -> 14
A65: Landon Sims | B65: 44621 | C65: Mississippi State | D65: JR | E65: P | F65: R
A66: Tanner Witt | B66: 44621 | C66: Texas | D66: SO | E66: P | F66: R | G66: 45047 | H66: =ROUND(((G66-B66)/365)*12,0) -> 14
A67: Will Frisch | B67: 44621 | C67: Oregon State | D67: SO | E67: P | F67: R
A68: Peyton Pallette | B68: 44592 | C68: Arkansas | D68: JR | E68: P | F68: R
A69: Eric Hammond | B69: 44580 | C69: USC | D69: FR | E69: P | F69: R
A70: Jake Eddington | B70: 44562 | C70: Alabama | D70: SO | E70: P | F70: R
A71: Luke Fox | B71: 44562 | C71: Duke | D71: SO | E71: P | F71: L
A72: Caedmon Parker | B72: 44562 | C72: Texas Christian | D72: FR | E72: P | F72: R | G72: 45338
A73: Ethan Bosacker | B73: 44562 | C73: Xavier | D73: JR | E73: P | F73: R | G73: 44974
A74: Trent Turzenski | B74: 44562 | C74: Valparaiso | D74: SO | E74: P | F74: R
A75: Gage Jump | B75: 44562 | C75: UCLA | D75: FR | E75: P | F75: L
A76: Hayden Mullins | B76: 44562 | C76: Auburn | D76: JR | E76: P | F76: L
A77: Will Childers | B77: 44562 | C77: Georgia | D77: SO | E77: P | F77: R
A78: Kyle Perry | B78: 44562 | C78: Nebraska | D78: SR | E78: P | F78: L
A79: Henry Williams | B79: 44546 | C79: Duke | D79: JR | E79: P | F79: R
A80: Reggie Crawford | B80: 44501 | C80: Connecticut | D80: SO | E80: P | F80: L
A81: Michael Doolin | B81: 44531 | C81: Vanderbilt | D81: SO | E81: P | F81: R | I81: Dr. David Altchek
A82: Charlie Hodges | B82: 44494 | C82: East Carolina | D82: JR | E82: P | F82: R
A83: Ryan Calvert | B83: 44490 | C83: UNC Wilmington | D83: FR | E83: P | F83: R | I83: Dr. Timothy Griffith
A84: Paulshawn Pasqualotto | B84: 44409 | C84: California | D84: FR | E84: P | F84: R | I84: Dr. Neal ElAttrache
A85: Andrew Vail | B85: 44348 | C85: Missouri | D85: JR | E85: P | F85: L
A86: Connor Prielipp | B86: 44343 | C86: Alabama | D86: SO | E86: P | F86: L | I86: Dr. Lyle Cain
A87: Gunnar Hoglund | B87: 44334 | C87: Ole Miss | D87: JR | E87: P | F87: R | I87: Dr. James Andrews
A88: Colton Gordon | B88: 44326 | C88: UCF | D88: SO | E88: P | F88: L | I88: Dr. Koco Eaton
A89: Max Carlson | B89: 44322 | C89: North Carolina | D89: FR | E89: P | F89: R | I89: Dr. Keith Meister
A90: Justin Wrobleski | B90: 44317 | C90: Oklahoma State | D90: SO | E90: P | F90: L
A91: Ryan Webb | B91: 44317 | C91: Georgia | D91: SR | E91: P | F91: L
A92: Jack Mahoney | B92: 44317 | C92: South Carolina | D92: FR | E92: P | F92: R | G92: 44976 | H92: =ROUND(((G92-B92)/365)*12,0) -> 22
A93: Sam Hliboki | B93: 44317 | C93: Vanderbilt | D93: SO | E93: P | F93: R | G93: 44974 | H93: =ROUND(((G93-B93)/365)*12,0) -> 22
A94: Jaden Hill | B94: 44306 | C94: LSU | D94: JR | E94: P | F94: R
A95: Riley Self | B95: 44292 | C95: Mississippi State | D95: SR | E95: P | F95: R
A96: Max Cioffi | B96: 44287 | C96: Ole Miss | D96: SR | E96: P | F96: R | G96: 44663 | H96: =ROUND(((G96-B96)/365)*12,0) -> 12
A97: Cam Cowan | B97: 44287 | C97: Campbell | D97: JR | E97: P | F97: R
A98: Doug Kirkland | B98: 44287 | C98: Florida State | D98: FR | E98: P | F98: R | G98: 44976 | H98: =ROUND(((G98-B98)/365)*12,0) -> 23
A99: Brett Thomas | B99: 44287 | C99: South Carolina | D99: SO | E99: P | F99: R | G99: 44642 | H99: =ROUND(((G99-B99)/365)*12,0) -> 12
A100: Joey Lancellotti | B100: 44285 | C100: North Carolina | D100: JR | E100: P | F100: R
...

Sheet Unsigned Draftees
A1: Player | B1: TJ Surgery Date | C1: Team | D1: Position | E1: Draft Year | F1: Draft Position
A2: Jaxon Jelkin | B2: 45292 | C2: NYM | D2: P | E2: 2024 | F2: 263
A3: Dane Burns | B3: 44958 | C3: KC | D3: P | E3: 2024 | F3: 497
A4: Ryan Ure | B4: 44927 | C4: SF | D4: P | E4: 2024 | F4: 568
A5: Hunter Elliott | B5: 45047 | C5: LAD | D5: P | E5: 2024 | F5: 610
A6: Javan Coleman | B6: 44621 | C6: LAD | D6: P | E6: 2023 | F6: 490
A7: Isaiah Bennett | B7: 43101 | C7: SD | D7: P | E7: 2019 | F7: 1073
A8: Chris Newell | B8: 42984 | C8: STL | D8: OF | E8: 2019 | F8: 1115
A9: Waylon Richardson | B9: 42736 | C9: PHI | D9: P | E9: 2018 | F9: 1187
A10: Justin Wilson | B10: 42370 | C10: NYY | D10: P | E10: 2018 | F10: 697
A11: Hunter Ruth | B11: 42370 | C11: CHC | D11: P | E11: 2017 | F11: 975
A12: Jaxon Shirley | B12: 42125 | C12: CHW | D12: 2B | E12: 2016 | F12: 1016
A13: Welby Malczewski | B13: 41913 | C13: ARI | D13: P | E13: 2016 | F13: 1109
... A18: Josh Dezse | B18: 41821 | C18: NYY | D18: P | E18: 2010 | F18: 865

Sheet Unconfirmed Dates and Surgeries
A1: Player | B1: Notes | C1: Link
A2: Alan Busenitz
A3: Bartolome Fortunato | B3: Scheduled for May 18, 2006, but decided to get second opinion
A4: Brandon Webb | B4: Conflicting online claims, seems like shoulder surgery not TJ
A5: Brent Billingsley
A6: Brett Gray
A7: Carlos Almanzar
A8: Carlos Beltran
A9: Chad Fox | B9: Third UCL injury did not lead to TJ | C9: http://www.baseballprospectus.com/article.php?articleid=16104
A10: Chang-Yong Lim | B10: First one date unknown, second one was July 2012
A11: Chris Spurling | B11: Maybe no second one
A12: Conor Mullee | B12: Only had one TJ, other two surgeries were not TJs | C12: https://twitter.com/cmullee11/status/728238350306578436
A13: Colby Lewis | B13: Seems 2004 surgery was rotator cuff
A14: Damian Moss | B14: Not sure source is reliable
A15: Dana Eveland | B15: Boston Globe says TJ in 2013, but was pitching in KBO
A16: Dario Beltre
A17: Deion Sanders
A18: Dellin Betances | B18: NYY media guide says TJ 8/27/2009, Wikipedia says not TJ
A19: Didi Gregorius | B19: BP has surgery 7/8/2009, but he played games through then
A20: Dustin McGowan | B20: Seems 2008 was rotator cuff and labrum
A21: Eric Gagne | B21: 2005 surgery just repaired tear in original graft from 1997 TJ | C21: http://www.cbc.ca/sports/baseball/eric-gagne-dodges-tommy-john-surgery-1.550244
A22: Eric Stults
A23: Harrison Bishop
A24: Jamie Brown
A25: Jaret Wright
A26: Jason Isringhausen | B26: 2008 surgery was not a TJ, confirmed by the patient himself
A27: Jimmy Key | B27: 1988 surgery was to remove bone chips
A28: Johan Santana | B28: Probably not TJ
A29: John Webb
A30: Jose Rijo | B30: Second operation may not have been TJS | C30: http://books.google.ca/books?id=4TJ4gxrpRTQC&pg=PA71&lpg=PA71&dq=Jose+Rijo+first+Tommy+John+surgery&source=bl&ots=-Q_0TB9nBe&sig=Pl7KrbAaRCB2DvETYoAhDiNmXlc&hl=en&sa=X&ei=GForU8aRMIPG0QH5z4DQAg&ved=0CG4Q6AEwCQ#v=onepage&q=Rijo&f=false
A31: Jose Rijo | B31: Third operation may not have been TJS | C31: http://books.google.ca/books?id=4TJ4gxrpRTQC&pg=PA71&lpg=PA71&dq=Jose+Rijo+first+Tommy+John+surgery&source=bl&ots=-Q_0TB9nBe&sig=Pl7KrbAaRCB2DvETYoAhDiNmXlc&hl=en&sa=X&ei=GForU8aRMIPG0QH5z4DQAg&ved=0CG4Q6AEwCQ#v=onepage&q=Rijo&f=false
A32: Jose Rijo | B32: Fourth operation was not TJS | C32: http://books.google.ca/books?id=4TJ4gxrpRTQC&pg=PA71&lpg=PA71&dq=Jose+Rijo+first+Tommy+John+surgery&source=bl&ots=-Q_0TB9nBe&sig=Pl7KrbAaRCB2DvETYoAhDiNmXlc&hl=en&sa=X&ei=GForU8aRMIPG0QH5z4DQAg&ved=0CG4Q6AEwCQ#v=onepage&q=Rijo&f=false
A33: Jose Rijo | B33: Fifth operation was not TJS | C33: http://books.google.ca/books?id=4TJ4gxrpRTQC&pg=PA71&lpg=PA71&dq=Jose+Rijo+first+Tommy+John+surgery&source=bl&ots=-Q_0TB9nBe&sig=Pl7KrbAaRCB2DvETYoAhDiNmXlc&hl=en&sa=X&ei=GForU8aRMIPG0QH5z4DQAg&ved=0CG4Q6AEwCQ#v=onepage&q=Rijo&f=false
A34: Jose Rojas
A35: Kenny Rogers | B35: Seems 2006 was shoulder surgery, 2007 was non-TJ elbow
A36: Mariano Rivera | B36: Probably not TJ
A37: Mark DiFelice | B37: Confirmed 2009 was shoulder surgery
A38: Mark Harriger
A39: Paul Bush
A40: Roberto Alomar
A41: Sandy Koufax | B41: Confirmed no TJS from Dr. Jobe HOF Group
A42: Scott Williamson | B42: Only had two TJs | C42: http://blogs.mycentraljersey.com/patriots/2010/08/03/scott-williamson-q-a/
A43: Shintaro Ejiri | B43: Never pitched outside of Japan
A44: Tyson Ross | B44: BP has 2005, but looks like he pitched through 2005 and 2006 | C44: https://calbears.com/roster.aspx?rp_id=5128 | F44: https://www.baseballfactory.com/video/tyson-ross-2005-baseball-factory-pre-season/ | K44: https://www.eastbaytimes.com/2005/04/01/oakland-high-frolics-15-0/

Sheet Recovery Time
A1: Tommy John Surgery Recovery Time (to same level) in Months (for those recovered), by Era and Time of Year Surgery Occurred
C2: 1 | D2: 4 | E2: 7 | F2: 10 | G2: 1
C3: 3 | D3: 6 | E3: 9 | F3: 12 | G3: 12
A4: Start Year | B4: End Year | C4: All Professionals | G4: All Professionals | L4: MLB Only
C5: Jan-Mar | D5: Apr-Jun | E5: Jul-Sep | F5: Oct-Dec | G5: Average | H5: Median | I5: Mode | J5: Return% | K5: Surgeries | L5: Average | M5: Return% | N5: Surgeries
A6: 2022 | B6: 2023 | C6: =IF(COUNTIFS('TJ List'!$L:$L,">0",'TJ List'!$S:$S,">="&$A6,'TJ List'!$S:$S,"<="&$B6,'TJ List'!$T:$T,">="&C$2,'TJ List'!$T:$T,"<="&C$3)>0,SUMIFS('TJ List'!$L:$L,'TJ List'!$S:$S,">="&$A6,'TJ List'!$S:$S,"<="&$B6,'TJ List'!$T:$T,">="&C$2,'TJ List'!$T:$T,"<="&C$3)/COUNTIFS('TJ List'!$L:$L,">0",'TJ List'!$S:$S,">="&$A6,'TJ List'!$S:$S,"<="&$B6,'TJ List'!$T:$T,">="&C$2,'TJ List'!$T:$T,"<="&C$3),"N/A") -> 18.62963 | D6: =IF(COUNTIFS('TJ List'!$L:$L,">0",'TJ List'!$S:$S,">="&$A6,'TJ List'!$S:$S,"<="&$B6,'TJ List'!$T:$T,">="&D$2,'TJ List'!$T:$T,"<="&D$3)>0,SUMIFS('TJ List'!$L:$L,'TJ List'!$S:$S,">="&$A6,'TJ List'!$S:$S,"<="&$B6,'TJ List'!$T:$T,">="&D$2,'TJ List'!$T:$T,"<="&D$3)/COUNTIFS('TJ List'!$L:$L,">0",'TJ List'!$S:$S,">="&$A6,'TJ List'!$S:$S,"<="&$B6,'TJ List'!$T:$T,">="&D$2,'TJ List'!$T:$T,"<="&D$3),"N/A") -> 17.956522 | E6: =IF(COUNTIFS('TJ List'!$L:$L,">0",'TJ List'!$S:$S,">="&$A6,'TJ List'!$S:$S,"<="&$B6,'TJ List'!$T:$T,">="&E$2,'TJ List'!$T:$T,"<="&E$3)>0,SUMIFS('TJ List'!$L:$L,'TJ List'!$S:$S,">="&$A6,'TJ List'!$S:$S,"<="&$B6,'TJ List'!$T:$T,">="&E$2,'TJ List'!$T:$T,"<="&E$3)/COUNTIFS('TJ List'!$L:$L,">0",'TJ List'!$S:$S,">="&$A6,'TJ List'!$S:$S,"<="&$B6,'TJ List'!$T:$T,">="&E$2,'TJ List'!$T:$T,"<="&E$3),"N/A") -> 18.170213 | F6: =IF(COUNTIFS('TJ List'!$L:$L,">0",'TJ List'!$S:$S,">="&$A6,'TJ List'!$S:$S,"<="&$B6,'TJ List'!$T:$T,">="&F$2,'TJ List'!$T:$T,"<="&F$3)>0,SUMIFS('TJ List'!$L:$L,'TJ List'!$S:$S,">="&$A6,'TJ List'!$S:$S,"<="&$B6,'TJ List'!$T:$T,">="&F$2,'TJ List'!$T:$T,"<="&F$3)/COUNTIFS('TJ List'!$L:$L,">0",'TJ List'!$S:$S,">="&$A6,'TJ List'!$S:$S,"<="&$B6,'TJ List'!$T:$T,">="&F$2,'TJ List'!$T:$T,"<="&F$3),"N/A") -> 16.272727 | G6: {=AVERAGE(INDIRECT(CONCATENATE(ADDRESS(ROW(INDEX('TJ List'!A:A,MATCH(45291,'TJ List'!B:B,-1)+1,0)),12,1,TRUE,"TJ List"),":",ADDRESS(ROW(INDEX('TJ List'!A:A,MATCH(44561,'TJ List'!B:B,-1),0)),12))))} -> 18.019481 | H6: {=MEDIAN(INDIRECT(CONCATENATE(ADDRESS(ROW(INDEX('TJ List'!A:A,MATCH(45291,'TJ List'!B:B,-1)+1,0)),12,1,TRUE,"TJ List"),":",ADDRESS(ROW(INDEX('TJ List'!A:A,MATCH(44561,'TJ List'!B:B,-1),0)),12))))} -> 17 | I6: {=MODE(INDIRECT(CONCATENATE(ADDRESS(ROW(INDEX('TJ List'!A:A,MATCH(45291,'TJ List'!B:B,-1)+1,0)),12,1,TRUE,"TJ List"),":",ADDRESS(ROW(INDEX('TJ List'!A:A,MATCH(44561,'TJ List'!B:B,-1),0)),12))))} -> 15 | J6: {=COUNTIFS(INDIRECT(CONCATENATE(ADDRESS(ROW(INDEX('TJ List'!A:A,MATCH(45291,'TJ List'!B:B,-1)+1,0)),11,1,TRUE,"TJ List"),":",ADDRESS(ROW(INDEX('TJ List'!A:A,MATCH(44561,'TJ List'!B:B,-1),0)),11))),">0")/COUNTIFS(INDIRECT(CONCATENATE(ADDRESS(ROW(INDEX('TJ List'!A:A,MATCH(44561,'TJ List'!B:B,-1)+1,0)),1,1,TRUE,"TJ List"),":",ADDRESS(ROW(INDEX('TJ List'!A:A,MATCH(43830,'TJ List'!B:B,-1),0)),1))),"<>0")} -> 0.8045977 | K6: {=COUNTIFS(INDIRECT(CONCATENATE(ADDRESS(ROW(INDEX('TJ List'!A:A,MATCH(45291,'TJ List'!B:B,-1)+1,0)),11,1,TRUE,"TJ List"),":",ADDRESS(ROW(INDEX('TJ List'!A:A,MATCH(44561,'TJ List'!B:B,-1),0)),11))),"<>X")} -> 260 | L6: {=AVERAGEIFS(INDIRECT(CONCATENATE(ADDRESS(ROW(INDEX('TJ List'!A:A,MATCH(45291,'TJ List'!B:B,-1)+1,0)),12,1,TRUE,"TJ List"),":",ADDRESS(ROW(INDEX('TJ List'!A:A,MATCH(44561,'TJ List'!B:B,-1),0)),12))),INDIRECT(CONCATENATE(ADDRESS(ROW(INDEX('TJ List'!A:A,MATCH(45291,'TJ List'!B:B,-1)+1,0)),4,1,TRUE,"TJ List"),":",ADDRESS(ROW(INDEX('TJ List'!A:A,MATCH(44561,'TJ List'!B:B,-1),0)),4))),"MLB",INDIRECT(CONCATENATE(ADDRESS(ROW(INDEX('TJ List'!A:A,MATCH(45291,'TJ List'!B:B,-1)+1,0)),12,1,TRUE,"TJ List"),":",ADDRESS(ROW(INDEX('TJ List'!A:A,MATCH(44561,'TJ List'!B:B,-1),0)),12))),">0")} -> 18.410714 | M6: {=COUNTIFS(INDIRECT(CONCATENATE(ADDRESS(ROW(INDEX('TJ List'!A:A,MATCH(45291,'TJ List'!B:B,-1)+1,0)),11,1,TRUE,"TJ List"),":",ADDRESS(ROW(INDEX('TJ List'!A:A,MATCH(44561,'TJ List'!B:B,-1),0)),11))),">0",INDIRECT(CONCATENATE(ADDRESS(ROW(INDEX('TJ List'!A:A,MATCH(45291,'TJ List'!B:B,-1)+1,0)),4,1,TRUE,"TJ List"),":",ADDRESS(ROW(INDEX('TJ List'!A:A,MATCH(44561,'TJ List'!B:B,-1),0)),4))),"MLB")/COUNTIFS(INDIRECT(CONCATENATE(ADDRESS(ROW(INDEX('TJ List'!A:A,MATCH(45291,'TJ List'!B:B,-1)+1,0)),1,1,TRUE,"TJ List"),":",ADDRESS(ROW(INDEX('TJ List'!A:A,MATCH(44561,'TJ List'!B:B,-1),0)),1))),"<>0",INDIRECT(CONCATENATE(ADDRESS(ROW(INDEX('TJ List'!A:A,MATCH(45291,'TJ List'!B:B,-1)+1,0)),4,1,TRUE,"TJ List"),":",ADDRESS(ROW(INDEX('TJ List'!A:A,MATCH(44561,'TJ List'!B:B,-1),0)),4))),"MLB")} -> 0.90322581 | N6: {=COUNTIFS(INDIRECT(CONCATENATE(ADDRESS(ROW(INDEX('TJ List'!A:A,MATCH(45291,'TJ List'!B:B,-1)+1,0)),11,1,TRUE,"TJ List"),":",ADDRESS(ROW(INDEX('TJ List'!A:A,MATCH(44561,'TJ List'!B:B,-1),0)),11))),"<>X",INDIRECT(CONCATENATE(ADDRESS(ROW(INDEX('TJ List'!A:A,MATCH(45291,'TJ List'!B:B,-1)+1,0)),4,1,TRUE,"TJ List"),":",ADDRESS(ROW(INDEX('TJ List'!A:A,MATCH(44561,'TJ List'!B:B,-1),0)),4))),"MLB")} -> 62
A7: 2020 | B7: 2021 | C7: =IF(COUNTIFS('TJ List'!$L:$L,">0",'TJ List'!$S:$S,">="&$A7,'TJ List'!$S:$S,"<="&$B7,'TJ List'!$T:$T,">="&C$2,'TJ List'!$T:$T,"<="&C$3)>0,SUMIFS('TJ List'!$L:$L,'TJ List'!$S:$S,">="&$A7,'TJ List'!$S:$S,"<="&$B7,'TJ List'!$T:$T,">="&C$2,'TJ List'!$T:$T,"<="&C$3)/COUNTIFS('TJ List'!$L:$L,">0",'TJ List'!$S:$S,">="&$A7,'TJ List'!$S:$S,"<="&$B7,'TJ List'!$T:$T,">="&C$2,'TJ List'!$T:$T,"<="&C$3),"N/A") -> 17.628571 | D7: =IF(COUNTIFS('TJ List'!$L:$L,">0",'TJ List'!$S:$S,">="&$A7,'TJ List'!$S:$S,"<="&$B7,'TJ List'!$T:$T,">="&D$2,'TJ List'!$T:$T,"<="&D$3)>0,SUMIFS('TJ List'!$L:$L,'TJ List'!$S:$S,">="&$A7,'TJ List'!$S:$S,"<="&$B7,'TJ List'!$T:$T,">="&D$2,'TJ List'!$T:$T,"<="&D$3)/COUNTIFS('TJ List'!$L:$L,">0",'TJ List'!$S:$S,">="&$A7,'TJ List'!$S:$S,"<="&$B7,'TJ List'!$T:$T,">="&D$2,'TJ List'!$T:$T,"<="&D$3),"N/A") -> 18.045455 | E7: =IF(COUNTIFS('TJ List'!$L:$L,">0",'TJ List'!$S:$S,">="&$A7,'TJ List'!$S:$S,"<="&$B7,'TJ List'!$T:$T,">="&E$2,'TJ List'!$T:$T,"<="&E$3)>0,SUMIFS('TJ List'!$L:$L,'TJ List'!$S:$S,">="&$A7,'TJ List'!$S:$S,"<="&$B7,'TJ List'!$T:$T,">="&E$2,'TJ List'!$T:$T,"<="&E$3)/COUNTIFS('TJ List'!$L:$L,">0",'TJ List'!$S:$S,">="&$A7,'TJ List'!$S:$S,"<="&$B7,'TJ List'!$T:$T,">="&E$2,'TJ List'!$T:$T,"<="&E$3),"N/A") -> 19.086957 | F7: =IF(COUNTIFS('TJ List'!$L:$L,">0",'TJ List'!$S:$S,">="&$A7,'TJ List'!$S:$S,"<="&$B7,'TJ List'!$T:$T,">="&F$2,'TJ List'!$T:$T,"<="&F$3)>0,SUMIFS('TJ List'!$L:$L,'TJ List'!$S:$S,">="&$A7,'TJ List'!$S:$S,"<="&$B7,'TJ List'!$T:$T,">="&F$2,'TJ List'!$T:$T,"<="&F$3)/COUNTIFS('TJ List'!$L:$L,">0",'TJ List'!$S:$S,">="&$A7,'TJ List'!$S:$S,"<="&$B7,'TJ List'!$T:$T,">="&F$2,'TJ List'!$T:$T,"<="&F$3),"N/A") -> 18.3 | G7: {=AVERAGE(INDIRECT(CONCATENATE(ADDRESS(ROW(INDEX('TJ List'!A:A,MATCH(44561,'TJ List'!B:B,-1)+1,0)),12,1,TRUE,"TJ List"),":",ADDRESS(ROW(INDEX('TJ List'!A:A,MATCH(43830,'TJ List'!B:B,-1),0)),12))))} -> 18.310345 | H7: {=MEDIAN(INDIRECT(CONCATENATE(ADDRESS(ROW(INDEX('TJ List'!A:A,MATCH(44561,'TJ List'!B:B,-1)+1,0)),12,1,TRUE,"TJ List"),":",ADDRESS(ROW(INDEX('TJ List'!A:A,MATCH(43830,'TJ List'!B:B,-1),0)),12))))} -> 17 | I7: {=MODE(INDIRECT(CONCATENATE(ADDRESS(ROW(INDEX('TJ List'!A:A,MATCH(44561,'TJ List'!B:B,-1)+1,0)),12,1,TRUE,"TJ List"),":",ADDRESS(ROW(INDEX('TJ List'!A:A,MATCH(43830,'TJ List'!B:B,-1),0)),12))))} -> 14 | J7: {=COUNTIFS(INDIRECT(CONCATENATE(ADDRESS(ROW(INDEX('TJ List'!A:A,MATCH(44561,'TJ List'!B:B,-1)+1,0)),11,1,TRUE,"TJ List"),":",ADDRESS(ROW(INDEX('TJ List'!A:A,MATCH(43830,'TJ List'!B:B,-1),0)),11))),">0")/COUNTIFS(INDIRECT(CONCATENATE(ADDRESS(ROW(INDEX('TJ List'!A:A,MATCH(44561,'TJ List'!B:B,-1)+1,0)),1,1,TRUE,"TJ List"),":",ADDRESS(ROW(INDEX('TJ List'!A:A,MATCH(43830,'TJ List'!B:B,-1),0)),1))),"<>0")} -> 0.85440613 | K7: {=COUNTIFS(INDIRECT(CONCATENATE(ADDRESS(ROW(INDEX('TJ List'!A:A,MATCH(44561,'TJ List'!B:B,-1)+1,0)),11,1,TRUE,"TJ List"),":",ADDRESS(ROW(INDEX('TJ List'!A:A,MATCH(43830,'TJ List'!B:B,-1),0)),11))),"<>X")} -> 261 | L7: {=AVERAGEIFS(INDIRECT(CONCATENATE(ADDRESS(ROW(INDEX('TJ List'!A:A,MATCH(44561,'TJ List'!B:B,-1)+1,0)),12,1,TRUE,"TJ List"),":",ADDRESS(ROW(INDEX('TJ List'!A:A,MATCH(43830,'TJ List'!B:B,-1),0)),12))),INDIRECT(CONCATENATE(ADDRESS(ROW(INDEX('TJ List'!A:A,MATCH(44561,'TJ List'!B:B,-1)+1,0)),4,1,TRUE,"TJ List"),":",ADDRESS(ROW(INDEX('TJ List'!A:A,MATCH(43830,'TJ List'!B:B,-1),0)),4))),"MLB",INDIRECT(CONCATENATE(ADDRESS(ROW(INDEX('TJ List'!A:A,MATCH(44561,'TJ List'!B:B,-1)+1,0)),12,1,TRUE,"TJ List"),":",ADDRESS(ROW(INDEX('TJ List'!A:A,MATCH(43830,'TJ List'!B:B,-1),0)),12))),">0")} -> 19.8 | M7: {=COUNTIFS(INDIRECT(CONCATENATE(ADDRESS(ROW(INDEX('TJ List'!A:A,MATCH(44561,'TJ List'!B:B,-1)+1,0)),11,1,TRUE,"TJ List"),":",ADDRESS(ROW(INDEX('TJ List'!A:A,MATCH(43830,'TJ List'!B:B,-1),0)),11))),">0",INDIRECT(CONCATENATE(ADDRESS(ROW(INDEX('TJ List'!A:A,MATCH(44561,'TJ List'!B:B,-1)+1,0)),4,1,TRUE,"TJ List"),":",ADDRESS(ROW(INDEX('TJ List'!A:A,MATCH(43830,'TJ List'!B:B,-1),0)),4))),"MLB")/COUNTIFS(INDIRECT(CONCATENATE(ADDRESS(ROW(INDEX('TJ List'!A:A,MATCH(44561,'TJ List'!B:B,-1)+1,0)),1,1,TRUE,"TJ List"),":",ADDRESS(ROW(INDEX('TJ List'!A:A,MATCH(43830,'TJ List'!B:B,-1),0)),1))),"<>0",INDIRECT(CONCATENATE(ADDRESS(ROW(INDEX('TJ List'!A:A,MATCH(44561,'TJ List'!B:B,-1)+1,0)),4,1,TRUE,"TJ List"),":",ADDRESS(ROW(INDEX('TJ List'!A:A,MATCH(43830,'TJ List'!B:B,-1),0)),4))),"MLB")} -> 0.796875 | N7: {=COUNTIFS(INDIRECT(CONCATENATE(ADDRESS(ROW(INDEX('TJ List'!A:A,MATCH(44561,'TJ List'!B:B,-1)+1,0)),11,1,TRUE,"TJ List"),":",ADDRESS(ROW(INDEX('TJ List'!A:A,MATCH(43830,'TJ List'!B:B,-1),0)),11))),"<>X",INDIRECT(CONCATENATE(ADDRESS(ROW(INDEX('TJ List'!A:A,MATCH(44561,'TJ List'!B:B,-1)+1,0)),4,1,TRUE,"TJ List"),":",ADDRESS(ROW(INDEX('TJ List'!A:A,MATCH(43830,'TJ List'!B:B,-1),0)),4))),"MLB")} -> 64
A8: 2018 | B8: 2019 | C8: =IF(COUNTIFS('TJ List'!$L:$L,">0",'TJ List'!$S:$S,">="&$A8,'TJ List'!$S:$S,"<="&$B8,'TJ List'!$T:$T,">="&C$2,'TJ List'!$T:$T,"<="&C$3)>0,SUMIFS('TJ List'!$L:$L,'TJ List'!$S:$S,">="&$A8,'TJ List'!$S:$S,"<="&$B8,'TJ List'!$T:$T,">="&C$2,'TJ List'!$T:$T,"<="&C$3)/COUNTIFS('TJ List'!$L:$L,">0",'TJ List'!$S:$S,">="&$A8,'TJ List'!$S:$S,"<="&$B8,'TJ List'!$T:$T,">="&C$2,'TJ List'!$T:$T,"<="&C$3),"N/A") -> 21.285714 | D8: =IF(COUNTIFS('TJ List'!$L:$L,">0",'TJ List'!$S:$S,">="&$A8,'TJ List'!$S:$S,"<="&$B8,'TJ List'!$T:$T,">="&D$2,'TJ List'!$T:$T,"<="&D$3)>0,SUMIFS('TJ List'!$L:$L,'TJ List'!$S:$S,">="&$A8,'TJ List'!$S:$S,"<="&$B8,'TJ List'!$T:$T,">="&D$2,'TJ List'!$T:$T,"<="&D$3)/COUNTIFS('TJ List'!$L:$L,">0",'TJ List'!$S:$S,">="&$A8,'TJ List'!$S:$S,"<="&$B8,'TJ List'!$T:$T,">="&D$2,'TJ List'!$T:$T,"<="&D$3),"N/A") -> 22.032787 | E8: =IF(COUNTIFS('TJ List'!$L:$L,">0",'TJ List'!$S:$S,">="&$A8,'TJ List'!$S:$S,"<="&$B8,'TJ List'!$T:$T,">="&E$2,'TJ List'!$T:$T,"<="&E$3)>0,SUMIFS('TJ List'!$L:$L,'TJ List'!$S:$S,">="&$A8,'TJ List'!$S:$S,"<="&$B8,'TJ List'!$T:$T,">="&E$2,'TJ List'!$T:$T,"<="&E$3)/COUNTIFS('TJ List'!$L:$L,">0",'TJ List'!$S:$S,">="&$A8,'TJ List'!$S:$S,"<="&$B8,'TJ List'!$T:$T,">="&E$2,'TJ List'!$T:$T,"<="&E$3),"N/A") -> 22.175 | F8: =IF(COUNTIFS('TJ List'!$L:$L,">0",'TJ List'!$S:$S,">="&$A8,'TJ List'!$S:$S,"<="&$B8,'TJ List'!$T:$T,">="&F$2,'TJ List'!$T:$T,"<="&F$3)>0,SUMIFS('TJ List'!$L:$L,'TJ List'!$S:$S,">="&$A8,'TJ List'!$S:$S,"<="&$B8,'TJ List'!$T:$T,">="&F$2,'TJ List'!$T:$T,"<="&F$3)/COUNTIFS('TJ List'!$L:$L,">0",'TJ List'!$S:$S,">="&$A8,'TJ List'!$S:$S,"<="&$B8,'TJ List'!$T:$T,">="&F$2,'TJ List'!$T:$T,"<="&F$3),"N/A") -> 20.4 | G8: {=AVERAGE(INDIRECT(CONCATENATE(ADDRESS(ROW(INDEX('TJ List'!A:A,MATCH(43830,'TJ List'!B:B,-1)+1,0)),12,1,TRUE,"TJ List"),":",ADDRESS(ROW(INDEX('TJ List'!A:A,MATCH(43100,'TJ List'!B:B,-1),0)),12))))} -> 21.805755 | H8: {=MEDIAN(INDIRECT(CONCATENATE(ADDRESS(ROW(INDEX('TJ List'!A:A,MATCH(43830,'TJ List'!B:B,-1)+1,0)),12,1,TRUE,"TJ List"),":",ADDRESS(ROW(INDEX('TJ List'!A:A,MATCH(43100,'TJ List'!B:B,-1),0)),12))))} -> 21 | I8: {=MODE(INDIRECT(CONCATENATE(ADDRESS(ROW(INDEX('TJ List'!A:A,MATCH(43830,'TJ List'!B:B,-1)+1,0)),12,1,TRUE,"TJ List"),":",ADDRESS(ROW(INDEX('TJ List'!A:A,MATCH(43100,'TJ List'!B:B,-1),0)),12))))} -> 14 | J8: {=COUNTIFS(INDIRECT(CONCATENATE(ADDRESS(ROW(INDEX('TJ List'!A:A,MATCH(43830,'TJ List'!B:B,-1)+1,0)),11,1,TRUE,"TJ List"),":",ADDRESS(ROW(INDEX('TJ List'!A:A,MATCH(43100,'TJ List'!B:B,-1),0)),11))),">0")/COUNTIFS(INDIRECT(CONCATENATE(ADDRESS(ROW(INDEX('TJ List'!A:A,MATCH(43830,'TJ List'!B:B,-1)+1,0)),1,1,TRUE,"TJ List"),":",ADDRESS(ROW(INDEX('TJ List'!A:A,MATCH(43100,'TJ List'!B:B,-1),0)),1))),"<>0")} -> 0.81052632 | K8: {=COUNTIFS(INDIRECT(CONCATENATE(ADDRESS(ROW(INDEX('TJ List'!A:A,MATCH(43830,'TJ List'!B:B,-1)+1,0)),11,1,TRUE,"TJ List"),":",ADDRESS(ROW(INDEX('TJ List'!A:A,MATCH(43100,'TJ List'!B:B,-1),0)),11))),"<>X")} -> 285 | L8: {=AVERAGEIFS(INDIRECT(CONCATENATE(ADDRESS(ROW(INDEX('TJ List'!A:A,MATCH(43830,'TJ List'!B:B,-1)+1,0)),12,1,TRUE,"TJ List"),":",ADDRESS(ROW(INDEX('TJ List'!A:A,MATCH(43100,'TJ List'!B:B,-1),0)),12))),INDIRECT(CONCATENATE(ADDRESS(ROW(INDEX('TJ List'!A:A,MATCH(43830,'TJ List'!B:B,-1)+1,0)),4,1,TRUE,"TJ List"),":",ADDRESS(ROW(INDEX('TJ List'!A:A,MATCH(43100,'TJ List'!B:B,-1),0)),4))),"MLB",INDIRECT(CONCATENATE(ADDRESS(ROW(INDEX('TJ List'!A:A,MATCH(43830,'TJ List'!B:B,-1)+1,0)),12,1,TRUE,"TJ List"),":",ADDRESS(ROW(INDEX('TJ List'!A:A,MATCH(43100,'TJ List'!B:B,-1),0)),12))),">0")} -> 18.947368 | M8: {=COUNTIFS(INDIRECT(CONCATENATE(ADDRESS(ROW(INDEX('TJ List'!A:A,MATCH(43830,'TJ List'!B:B,-1)+1,0)),11,1,TRUE,"TJ List"),":",ADDRESS(ROW(INDEX('TJ List'!A:A,MATCH(43100,'TJ List'!B:B,-1),0)),11))),">0",INDIRECT(CONCATENATE(ADDRESS(ROW(INDEX('TJ List'!A:A,MATCH(43830,'TJ List'!B:B,-1)+1,0)),4,1,TRUE,"TJ List"),":",ADDRESS(ROW(INDEX('TJ List'!A:A,MATCH(43100,'TJ List'!B:B,-1),0)),4))),"MLB")/COUNTIFS(INDIRECT(CONCATENATE(ADDRESS(ROW(INDEX('TJ List'!A:A,MATCH(43830,'TJ List'!B:B,-1)+1,0)),1,1,TRUE,"TJ List"),":",ADDRESS(ROW(INDEX('TJ List'!A:A,MATCH(43100,'TJ List'!B:B,-1),0)),1))),"<>0",INDIRECT(CONCATENATE(ADDRESS(ROW(INDEX('TJ List'!A:A,MATCH(43830,'TJ List'!B:B,-1)+1,0)),4,1,TRUE,"TJ List"),":",ADDRESS(ROW(INDEX('TJ List'!A:A,MATCH(43100,'TJ List'!B:B,-1),0)),4))),"MLB")} -> 0.82978723 | N8: {=COUNTIFS(INDIRECT(CONCATENATE(ADDRESS(ROW(INDEX('TJ List'!A:A,MATCH(43830,'TJ List'!B:B,-1)+1,0)),11,1,TRUE,"TJ List"),":",ADDRESS(ROW(INDEX('TJ List'!A:A,MATCH(43100,'TJ List'!B:B,-1),0)),11))),"<>X",INDIRECT(CONCATENATE(ADDRESS(ROW(INDEX('TJ List'!A:A,MATCH(43830,'TJ List'!B:B,-1)+1,0)),4,1,TRUE,"TJ List"),":",ADDRESS(ROW(INDEX('TJ List'!A:A,MATCH(43100,'TJ List'!B:B,-1),0)),4))),"MLB")} -> 47
A9: 2016 | B9: 2017 | C9: =IF(COUNTIFS('TJ List'!$L:$L,">0",'TJ List'!$S:$S,">="&$A9,'TJ List'!$S:$S,"<="&$B9,'TJ List'!$T:$T,">="&C$2,'TJ List'!$T:$T,"<="&C$3)>0,SUMIFS('TJ List'!$L:$L,'TJ List'!$S:$S,">="&$A9,'TJ List'!$S:$S,"<="&$B9,'TJ List'!$T:$T,">="&C$2,'TJ List'!$T:$T,"<="&C$3)/COUNTIFS('TJ List'!$L:$L,">0",'TJ List'!$S:$S,">="&$A9,'TJ List'!$S:$S,"<="&$B9,'TJ List'!$T:$T,">="&C$2,'TJ List'!$T:$T,"<="&C$3),"N/A") -> 17.73913 | D9: =IF(COUNTIFS('TJ List'!$L:$L,">0",'TJ List'!$S:$S,">="&$A9,'TJ List'!$S:$S,"<="&$B9,'TJ List'!$T:$T,">="&D$2,'TJ List'!$T:$T,"<="&D$3)>0,SUMIFS('TJ List'!$L:$L,'TJ List'!$S:$S,">="&$A9,'TJ List'!$S:$S,"<="&$B9,'TJ List'!$T:$T,">="&D$2,'TJ List'!$T:$T,"<="&D$3)/COUNTIFS('TJ List'!$L:$L,">0",'TJ List'!$S:$S,">="&$A9,'TJ List'!$S:$S,"<="&$B9,'TJ List'!$T:$T,">="&D$2,'TJ List'!$T:$T,"<="&D$3),"N/A") -> 17.364865 | E9: =IF(COUNTIFS('TJ List'!$L:$L,">0",'TJ List'!$S:$S,">="&$A9,'TJ List'!$S:$S,"<="&$B9,'TJ List'!$T:$T,">="&E$2,'TJ List'!$T:$T,"<="&E$3)>0,SUMIFS('TJ List'!$L:$L,'TJ List'!$S:$S,">="&$A9,'TJ List'!$S:$S,"<="&$B9,'TJ List'!$T:$T,">="&E$2,'TJ List'!$T:$T,"<="&E$3)/COUNTIFS('TJ List'!$L:$L,">0",'TJ List'!$S:$S,">="&$A9,'TJ List'!$S:$S,"<="&$B9,'TJ List'!$T:$T,">="&E$2,'TJ List'!$T:$T,"<="&E$3),"N/A") -> 21.204082 | F9: =IF(COUNTIFS('TJ List'!$L:$L,">0",'TJ List'!$S:$S,">="&$A9,'TJ List'!$S:$S,"<="&$B9,'TJ List'!$T:$T,">="&F$2,'TJ List'!$T:$T,"<="&F$3)>0,SUMIFS('TJ List'!$L:$L,'TJ List'!$S:$S,">="&$A9,'TJ List'!$S:$S,"<="&$B9,'TJ List'!$T:$T,">="&F$2,'TJ List'!$T:$T,"<="&F$3)/COUNTIFS('TJ List'!$L:$L,">0",'TJ List'!$S:$S,">="&$A9,'TJ List'!$S:$S,"<="&$B9,'TJ List'!$T:$T,">="&F$2,'TJ List'!$T:$T,"<="&F$3),"N/A") -> 20.083333 | G9: {=AVERAGE(INDIRECT(CONCATENATE(ADDRESS(ROW(INDEX('TJ List'!A:A,MATCH(43100,'TJ List'!B:B,-1)+1,0)),12,1,TRUE,"TJ List"),":",ADDRESS(ROW(INDEX('TJ List'!A:A,MATCH(42369,'TJ List'!B:B,-1),0)),12))))} -> 18.816456 | H9: {=MEDIAN(INDIRECT(CONCATENATE(ADDRESS(ROW(INDEX('TJ List'!A:A,MATCH(43100,'TJ List'!B:B,-1)+1,0)),12,1,TRUE,"TJ List"),":",ADDRESS(ROW(INDEX('TJ List'!A:A,MATCH(42369,'TJ List'!B:B,-1),0)),12))))} -> 17 | I9: {=MODE(INDIRECT(CONCATENATE(ADDRESS(ROW(INDEX('TJ List'!A:A,MATCH(43100,'TJ List'!B:B,-1)+1,0)),12,1,TRUE,"TJ List"),":",ADDRESS(ROW(INDEX('TJ List'!A:A,MATCH(42369,'TJ List'!B:B,-1),0)),12))))} -> 14 | J9: {=COUNTIFS(INDIRECT(CONCATENATE(ADDRESS(ROW(INDEX('TJ List'!A:A,MATCH(43100,'TJ List'!B:B,-1)+1,0)),11,1,TRUE,"TJ List"),":",ADDRESS(ROW(INDEX('TJ List'!A:A,MATCH(42369,'TJ List'!B:B,-1),0)),11))),">0")/COUNTIFS(INDIRECT(CONCATENATE(ADDRESS(ROW(INDEX('TJ List'!A:A,MATCH(43100,'TJ List'!B:B,-1)+1,0)),1,1,TRUE,"TJ List"),":",ADDRESS(ROW(INDEX('TJ List'!A:A,MATCH(42369,'TJ List'!B:B,-1),0)),1))),"<>0")} -> 0.81875 | K9: {=COUNTIFS(INDIRECT(CONCATENATE(ADDRESS(ROW(INDEX('TJ List'!A:A,MATCH(43100,'TJ List'!B:B,-1)+1,0)),11,1,TRUE,"TJ List"),":",ADDRESS(ROW(INDEX('TJ List'!A:A,MATCH(42369,'TJ List'!B:B,-1),0)),11))),"<>X")} -> 320 | L9: {=AVERAGEIFS(INDIRECT(CONCATENATE(ADDRESS(ROW(INDEX('TJ List'!A:A,MATCH(43100,'TJ List'!B:B,-1)+1,0)),12,1,TRUE,"TJ List"),":",ADDRESS(ROW(INDEX('TJ List'!A:A,MATCH(42369,'TJ List'!B:B,-1),0)),12))),INDIRECT(CONCATENATE(ADDRESS(ROW(INDEX('TJ List'!A:A,MATCH(43100,'TJ List'!B:B,-1)+1,0)),4,1,TRUE,"TJ List"),":",ADDRESS(ROW(INDEX('TJ List'!A:A,MATCH(42369,'TJ List'!B:B,-1),0)),4))),"MLB",INDIRECT(CONCATENATE(ADDRESS(ROW(INDEX('TJ List'!A:A,MATCH(43100,'TJ List'!B:B,-1)+1,0)),12,1,TRUE,"TJ List"),":",ADDRESS(ROW(INDEX('TJ List'!A:A,MATCH(42369,'TJ List'!B:B,-1),0)),12))),">0")} -> 21.346154 | M9: {=COUNTIFS(INDIRECT(CONCATENATE(ADDRESS(ROW(INDEX('TJ List'!A:A,MATCH(43100,'TJ List'!B:B,-1)+1,0)),11,1,TRUE,"TJ List"),":",ADDRESS(ROW(INDEX('TJ List'!A:A,MATCH(42369,'TJ List'!B:B,-1),0)),11))),">0",INDIRECT(CONCATENATE(ADDRESS(ROW(INDEX('TJ List'!A:A,MATCH(43100,'TJ List'!B:B,-1)+1,0)),4,1,TRUE,"TJ List"),":",ADDRESS(ROW(INDEX('TJ List'!A:A,MATCH(42369,'TJ List'!B:B,-1),0)),4))),"MLB")/COUNTIFS(INDIRECT(CONCATENATE(ADDRESS(ROW(INDEX('TJ List'!A:A,MATCH(43100,'TJ List'!B:B,-1)+1,0)),1,1,TRUE,"TJ List"),":",ADDRESS(ROW(INDEX('TJ List'!A:A,MATCH(42369,'TJ List'!B:B,-1),0)),1))),"<>0",INDIRECT(CONCATENATE(ADDRESS(ROW(INDEX('TJ List'!A:A,MATCH(43100,'TJ List'!B:B,-1)+1,0)),4,1,TRUE,"TJ List"),":",ADDRESS(ROW(INDEX('TJ List'!A:A,MATCH(42369,'TJ List'!B:B,-1),0)),4))),"MLB")} -> 0.66666667 | N9: {=COUNTIFS(INDIRECT(CONCATENATE(ADDRESS(ROW(INDEX('TJ List'!A:A,MATCH(43100,'TJ List'!B:B,-1)+1,0)),11,1,TRUE,"TJ List"),":",ADDRESS(ROW(INDEX('TJ List'!A:A,MATCH(42369,'TJ List'!B:B,-1),0)),11))),"<>X",INDIRECT(CONCATENATE(ADDRESS(ROW(INDEX('TJ List'!A:A,MATCH(43100,'TJ List'!B:B,-1)+1,0)),4,1,TRUE,"TJ List"),":",ADDRESS(ROW(INDEX('TJ List'!A:A,MATCH(42369,'TJ List'!B:B,-1),0)),4))),"MLB")} -> 39
A10: 2014 | B10: 2015 | C10: =IF(COUNTIFS('TJ List'!$L:$L,">0",'TJ List'!$S:$S,">="&$A10,'TJ List'!$S:$S,"<="&$B10,'TJ List'!$T:$T,">="&C$2,'TJ List'!$T:$T,"<="&C$3)>0,SUMIFS('TJ List'!$L:$L,'TJ List'!$S:$S,">="&$A10,'TJ List'!$S:$S,"<="&$B10,'TJ List'!$T:$T,">="&C$2,'TJ List'!$T:$T,"<="&C$3)/COUNTIFS('TJ List'!$L:$L,">0",'TJ List'!$S:$S,">="&$A10,'TJ List'!$S:$S,"<="&$B10,'TJ List'!$T:$T,">="&C$2,'TJ List'!$T:$T,"<="&C$3),"N/A") -> 17.971429 | D10: =IF(COUNTIFS('TJ List'!$L:$L,">0",'TJ List'!$S:$S,">="&$A10,'TJ List'!$S:$S,"<="&$B10,'TJ List'!$T:$T,">="&D$2,'TJ List'!$T:$T,"<="&D$3)>0,SUMIFS('TJ List'!$L:$L,'TJ List'!$S:$S,">="&$A10,'TJ List'!$S:$S,"<="&$B10,'TJ List'!$T:$T,">="&D$2,'TJ List'!$T:$T,"<="&D$3)/COUNTIFS('TJ List'!$L:$L,">0",'TJ List'!$S:$S,">="&$A10,'TJ List'!$S:$S,"<="&$B10,'TJ List'!$T:$T,">="&D$2,'TJ List'!$T:$T,"<="&D$3),"N/A") -> 17.602273 | E10: =IF(COUNTIFS('TJ List'!$L:$L,">0",'TJ List'!$S:$S,">="&$A10,'TJ List'!$S:$S,"<="&$B10,'TJ List'!$T:$T,">="&E$2,'TJ List'!$T:$T,"<="&E$3)>0,SUMIFS('TJ List'!$L:$L,'TJ List'!$S:$S,">="&$A10,'TJ List'!$S:$S,"<="&$B10,'TJ List'!$T:$T,">="&E$2,'TJ List'!$T:$T,"<="&E$3)/COUNTIFS('TJ List'!$L:$L,">0",'TJ List'!$S:$S,">="&$A10,'TJ List'!$S:$S,"<="&$B10,'TJ List'!$T:$T,">="&E$2,'TJ List'!$T:$T,"<="&E$3),"N/A") -> 18.103448 | F10: =IF(COUNTIFS('TJ List'!$L:$L,">0",'TJ List'!$S:$S,">="&$A10,'TJ List'!$S:$S,"<="&$B10,'TJ List'!$T:$T,">="&F$2,'TJ List'!$T:$T,"<="&F$3)>0,SUMIFS('TJ List'!$L:$L,'TJ List'!$S:$S,">="&$A10,'TJ List'!$S:$S,"<="&$B10,'TJ List'!$T:$T,">="&F$2,'TJ List'!$T:$T,"<="&F$3)/COUNTIFS('TJ List'!$L:$L,">0",'TJ List'!$S:$S,">="&$A10,'TJ List'!$S:$S,"<="&$B10,'TJ List'!$T:$T,">="&F$2,'TJ List'!$T:$T,"<="&F$3),"N/A") -> 21.333333 | G10: {=AVERAGE(INDIRECT(CONCATENATE(ADDRESS(ROW(INDEX('TJ List'!A:A,MATCH(42369,'TJ List'!B:B,-1)+1,0)),12,1,TRUE,"TJ List"),":",ADDRESS(ROW(INDEX('TJ List'!A:A,MATCH(41639,'TJ List'!B:B,-1),0)),12))))} -> 18 | H10: {=MEDIAN(INDIRECT(CONCATENATE(ADDRESS(ROW(INDEX('TJ List'!A:A,MATCH(42369,'TJ List'!B:B,-1)+1,0)),12,1,TRUE,"TJ List"),":",ADDRESS(ROW(INDEX('TJ List'!A:A,MATCH(41639,'TJ List'!B:B,-1),0)),12))))} -> 15 | I10: {=MODE(INDIRECT(CONCATENATE(ADDRESS(ROW(INDEX('TJ List'!A:A,MATCH(42369,'TJ List'!B:B,-1)+1,0)),12,1,TRUE,"TJ List"),":",ADDRESS(ROW(INDEX('TJ List'!A:A,MATCH(41639,'TJ List'!B:B,-1),0)),12))))} -> 14 | J10: {=COUNTIFS(INDIRECT(CONCATENATE(ADDRESS(ROW(INDEX('TJ List'!A:A,MATCH(42369,'TJ List'!B:B,-1)+1,0)),11,1,TRUE,"TJ List"),":",ADDRESS(ROW(INDEX('TJ List'!A:A,MATCH(41639,'TJ List'!B:B,-1),0)),11))),">0")/COUNTIFS(INDIRECT(CONCATENATE(ADDRESS(ROW(INDEX('TJ List'!A:A,MATCH(42369,'TJ List'!B:B,-1)+1,0)),1,1,TRUE,"TJ List"),":",ADDRESS(ROW(INDEX('TJ List'!A:A,MATCH(41639,'TJ List'!B:B,-1),0)),1))),"<>0")} -> 0.85626911 | K10: {=COUNTIFS(INDIRECT(CONCATENATE(ADDRESS(ROW(INDEX('TJ List'!A:A,MATCH(42369,'TJ List'!B:B,-1)+1,0)),11,1,TRUE,"TJ List"),":",ADDRESS(ROW(INDEX('TJ List'!A:A,MATCH(41639,'TJ List'!B:B,-1),0)),11))),"<>X")} -> 327 | L10: {=AVERAGEIFS(INDIRECT(CONCATENATE(ADDRESS(ROW(INDEX('TJ List'!A:A,MATCH(42369,'TJ List'!B:B,-1)+1,0)),12,1,TRUE,"TJ List"),":",ADDRESS(ROW(INDEX('TJ List'!A:A,MATCH(41639,'TJ List'!B:B,-1),0)),12))),INDIRECT(CONCATENATE(ADDRESS(ROW(INDEX('TJ List'!A:A,MATCH(42369,'TJ List'!B:B,-1)+1,0)),4,1,TRUE,"TJ List"),":",ADDRESS(ROW(INDEX('TJ List'!A:A,MATCH(41639,'TJ List'!B:B,-1),0)),4))),"MLB",INDIRECT(CONCATENATE(ADDRESS(ROW(INDEX('TJ List'!A:A,MATCH(42369,'TJ List'!B:B,-1)+1,0)),12,1,TRUE,"TJ List"),":",ADDRESS(ROW(INDEX('TJ List'!A:A,MATCH(41639,'TJ List'!B:B,-1),0)),12))),">0")} -> 21.26087 | M10: {=COUNTIFS(INDIRECT(CONCATENATE(ADDRESS(ROW(INDEX('TJ List'!A:A,MATCH(42369,'TJ List'!B:B,-1)+1,0)),11,1,TRUE,"TJ List"),":",ADDRESS(ROW(INDEX('TJ List'!A:A,MATCH(41639,'TJ List'!B:B,-1),0)),11))),">0",INDIRECT(CONCATENATE(ADDRESS(ROW(INDEX('TJ List'!A:A,MATCH(42369,'TJ List'!B:B,-1)+1,0)),4,1,TRUE,"TJ List"),":",ADDRESS(ROW(INDEX('TJ List'!A:A,MATCH(41639,'TJ List'!B:B,-1),0)),4))),"MLB")/COUNTIFS(INDIRECT(CONCATENATE(ADDRESS(ROW(INDEX('TJ List'!A:A,MATCH(42369,'TJ List'!B:B,-1)+1,0)),1,1,TRUE,"TJ List"),":",ADDRESS(ROW(INDEX('TJ List'!A:A,MATCH(41639,'TJ List'!B:B,-1),0)),1))),"<>0",INDIRECT(CONCATENATE(ADDRESS(ROW(INDEX('TJ List'!A:A,MATCH(42369,'TJ List'!B:B,-1)+1,0)),4,1,TRUE,"TJ List"),":",ADDRESS(ROW(INDEX('TJ List'!A:A,MATCH(41639,'TJ List'!B:B,-1),0)),4))),"MLB")} -> 0.80701754 | N10: {=COUNTIFS(INDIRECT(CONCATENATE(ADDRESS(ROW(INDEX('TJ List'!A:A,MATCH(42369,'TJ List'!B:B,-1)+1,0)),11,1,TRUE,"TJ List"),":",ADDRESS(ROW(INDEX('TJ List'!A:A,MATCH(41639,'TJ List'!B:B,-1),0)),11))),"<>X",INDIRECT(CONCATENATE(ADDRESS(ROW(INDEX('TJ List'!A:A,MATCH(42369,'TJ List'!B:B,-1)+1,0)),4,1,TRUE,"TJ List"),":",ADDRESS(ROW(INDEX('TJ List'!A:A,MATCH(41639,'TJ List'!B:B,-1),0)),4))),"MLB")} -> 57
A11: 2012 | B11: 2013 | C11: =IF(COUNTIFS('TJ List'!$L:$L,">0",'TJ List'!$S:$S,">="&$A11,'TJ List'!$S:$S,"<="&$B11,'TJ List'!$T:$T,">="&C$2,'TJ List'!$T:$T,"<="&C$3)>0,SUMIFS('TJ List'!$L:$L,'TJ List'!$S:$S,">="&$A11,'TJ List'!$S:$S,"<="&$B11,'TJ List'!$T:$T,">="&C$2,'TJ List'!$T:$T,"<="&C$3)/COUNTIFS('TJ List'!$L:$L,">0",'TJ List'!$S:$S,">="&$A11,'TJ List'!$S:$S,"<="&$B11,'TJ List'!$T:$T,">="&C$2,'TJ List'!$T:$T,"<="&C$3),"N/A") -> 18.666667 | D11: =IF(COUNTIFS('TJ List'!$L:$L,">0",'TJ List'!$S:$S,">="&$A11,'TJ List'!$S:$S,"<="&$B11,'TJ List'!$T:$T,">="&D$2,'TJ List'!$T:$T,"<="&D$3)>0,SUMIFS('TJ List'!$L:$L,'TJ List'!$S:$S,">="&$A11,'TJ List'!$S:$S,"<="&$B11,'TJ List'!$T:$T,">="&D$2,'TJ List'!$T:$T,"<="&D$3)/COUNTIFS('TJ List'!$L:$L,">0",'TJ List'!$S:$S,">="&$A11,'TJ List'!$S:$S,"<="&$B11,'TJ List'!$T:$T,">="&D$2,'TJ List'!$T:$T,"<="&D$3),"N/A") -> 18.596774 | E11: =IF(COUNTIFS('TJ List'!$L:$L,">0",'TJ List'!$S:$S,">="&$A11,'TJ List'!$S:$S,"<="&$B11,'TJ List'!$T:$T,">="&E$2,'TJ List'!$T:$T,"<="&E$3)>0,SUMIFS('TJ List'!$L:$L,'TJ List'!$S:$S,">="&$A11,'TJ List'!$S:$S,"<="&$B11,'TJ List'!$T:$T,">="&E$2,'TJ List'!$T:$T,"<="&E$3)/COUNTIFS('TJ List'!$L:$L,">0",'TJ List'!$S:$S,">="&$A11,'TJ List'!$S:$S,"<="&$B11,'TJ List'!$T:$T,">="&E$2,'TJ List'!$T:$T,"<="&E$3),"N/A") -> 16.304348 | F11: =IF(COUNTIFS('TJ List'!$L:$L,">0",'TJ List'!$S:$S,">="&$A11,'TJ List'!$S:$S,"<="&$B11,'TJ List'!$T:$T,">="&F$2,'TJ List'!$T:$T,"<="&F$3)>0,SUMIFS('TJ List'!$L:$L,'TJ List'!$S:$S,">="&$A11,'TJ List'!$S:$S,"<="&$B11,'TJ List'!$T:$T,">="&F$2,'TJ List'!$T:$T,"<="&F$3)/COUNTIFS('TJ List'!$L:$L,">0",'TJ List'!$S:$S,">="&$A11,'TJ List'!$S:$S,"<="&$B11,'TJ List'!$T:$T,">="&F$2,'TJ List'!$T:$T,"<="&F$3),"N/A") -> 20.230769 | G11: {=AVERAGE(INDIRECT(CONCATENATE(ADDRESS(ROW(INDEX('TJ List'!A:A,MATCH(41639,'TJ List'!B:B,-1)+1,0)),12,1,TRUE,"TJ List"),":",ADDRESS(ROW(INDEX('TJ List'!A:A,MATCH(40908,'TJ List'!B:B,-1),0)),12))))} -> 17.953846 | H11: {=MEDIAN(INDIRECT(CONCATENATE(ADDRESS(ROW(INDEX('TJ List'!A:A,MATCH(41639,'TJ List'!B:B,-1)+1,0)),12,1,TRUE,"TJ List"),":",ADDRESS(ROW(INDEX('TJ List'!A:A,MATCH(40908,'TJ List'!B:B,-1),0)),12))))} -> 14 | I11: {=MODE(INDIRECT(CONCATENATE(ADDRESS(ROW(INDEX('TJ List'!A:A,MATCH(41639,'TJ List'!B:B,-1)+1,0)),12,1,TRUE,"TJ List"),":",ADDRESS(ROW(INDEX('TJ List'!A:A,MATCH(40908,'TJ List'!B:B,-1),0)),12))))} -> 12 | J11: {=COUNTIFS(INDIRECT(CONCATENATE(ADDRESS(ROW(INDEX('TJ List'!A:A,MATCH(41639,'TJ List'!B:B,-1)+1,0)),11,1,TRUE,"TJ List"),":",ADDRESS(ROW(INDEX('TJ List'!A:A,MATCH(40908,'TJ List'!B:B,-1),0)),11))),">0")/COUNTIFS(INDIRECT(CONCATENATE(ADDRESS(ROW(INDEX('TJ List'!A:A,MATCH(41639,'TJ List'!B:B,-1)+1,0)),1,1,TRUE,"TJ List"),":",ADDRESS(ROW(INDEX('TJ List'!A:A,MATCH(40908,'TJ List'!B:B,-1),0)),1))),"<>0")} -> 0.86403509 | K11: {=COUNTIFS(INDIRECT(CONCATENATE(ADDRESS(ROW(INDEX('TJ List'!A:A,MATCH(41639,'TJ List'!B:B,-1)+1,0)),11,1,TRUE,"TJ List"),":",ADDRESS(ROW(INDEX('TJ List'!A:A,MATCH(40908,'TJ List'!B:B,-1),0)),11))),"<>X")} -> 228 | L11: {=AVERAGEIFS(INDIRECT(CONCATENATE(ADDRESS(ROW(INDEX('TJ List'!A:A,MATCH(41639,'TJ List'!B:B,-1)+1,0)),12,1,TRUE,"TJ List"),":",ADDRESS(ROW(INDEX('TJ List'!A:A,MATCH(40908,'TJ List'!B:B,-1),0)),12))),INDIRECT(CONCATENATE(ADDRESS(ROW(INDEX('TJ List'!A:A,MATCH(41639,'TJ List'!B:B,-1)+1,0)),4,1,TRUE,"TJ List"),":",ADDRESS(ROW(INDEX('TJ List'!A:A,MATCH(40908,'TJ List'!B:B,-1),0)),4))),"MLB",INDIRECT(CONCATENATE(ADDRESS(ROW(INDEX('TJ List'!A:A,MATCH(41639,'TJ List'!B:B,-1)+1,0)),12,1,TRUE,"TJ List"),":",ADDRESS(ROW(INDEX('TJ List'!A:A,MATCH(40908,'TJ List'!B:B,-1),0)),12))),">0")} -> 20.136364 | M11: {=COUNTIFS(INDIRECT(CONCATENATE(ADDRESS(ROW(INDEX('TJ List'!A:A,MATCH(41639,'TJ List'!B:B,-1)+1,0)),11,1,TRUE,"TJ List"),":",ADDRESS(ROW(INDEX('TJ List'!A:A,MATCH(40908,'TJ List'!B:B,-1),0)),11))),">0",INDIRECT(CONCATENATE(ADDRESS(ROW(INDEX('TJ List'!A:A,MATCH(41639,'TJ List'!B:B,-1)+1,0)),4,1,TRUE,"TJ List"),":",ADDRESS(ROW(INDEX('TJ List'!A:A,MATCH(40908,'TJ List'!B:B,-1),0)),4))),"MLB")/COUNTIFS(INDIRECT(CONCATENATE(ADDRESS(ROW(INDEX('TJ List'!A:A,MATCH(41639,'TJ List'!B:B,-1)+1,0)),1,1,TRUE,"TJ List"),":",ADDRESS(ROW(INDEX('TJ List'!A:A,MATCH(40908,'TJ List'!B:B,-1),0)),1))),"<>0",INDIRECT(CONCATENATE(ADDRESS(ROW(INDEX('TJ List'!A:A,MATCH(41639,'TJ List'!B:B,-1)+1,0)),4,1,TRUE,"TJ List"),":",ADDRESS(ROW(INDEX('TJ List'!A:A,MATCH(40908,'TJ List'!B:B,-1),0)),4))),"MLB")} -> 0.78571429 | N11: {=COUNTIFS(INDIRECT(CONCATENATE(ADDRESS(ROW(INDEX('TJ List'!A:A,MATCH(41639,'TJ List'!B:B,-1)+1,0)),11,1,TRUE,"TJ List"),":",ADDRESS(ROW(INDEX('TJ List'!A:A,MATCH(40908,'TJ List'!B:B,-1),0)),11))),"<>X",INDIRECT(CONCATENATE(ADDRESS(ROW(INDEX('TJ List'!A:A,MATCH(41639,'TJ List'!B:B,-1)+1,0)),4,1,TRUE,"TJ List"),":",ADDRESS(ROW(INDEX('TJ List'!A:A,MATCH(40908,'TJ List'!B:B,-1),0)),4))),"MLB")} -> 56
A12: 2010 | B12: 2011 | C12: =IF(COUNTIFS('TJ List'!$L:$L,">0",'TJ List'!$S:$S,">="&$A12,'TJ List'!$S:$S,"<="&$B12,'TJ List'!$T:$T,">="&C$2,'TJ List'!$T:$T,"<="&C$3)>0,SUMIFS('TJ List'!$L:$L,'TJ List'!$S:$S,">="&$A12,'TJ List'!$S:$S,"<="&$B12,'TJ List'!$T:$T,">="&C$2,'TJ List'!$T:$T,"<="&C$3)/COUNTIFS('TJ List'!$L:$L,">0",'TJ List'!$S:$S,">="&$A12,'TJ List'!$S:$S,"<="&$B12,'TJ List'!$T:$T,">="&C$2,'TJ List'!$T:$T,"<="&C$3),"N/A") -> 15.1 | D12: =IF(COUNTIFS('TJ List'!$L:$L,">0",'TJ List'!$S:$S,">="&$A12,'TJ List'!$S:$S,"<="&$B12,'TJ List'!$T:$T,">="&D$2,'TJ List'!$T:$T,"<="&D$3)>0,SUMIFS('TJ List'!$L:$L,'TJ List'!$S:$S,">="&$A12,'TJ List'!$S:$S,"<="&$B12,'TJ List'!$T:$T,">="&D$2,'TJ List'!$T:$T,"<="&D$3)/COUNTIFS('TJ List'!$L:$L,">0",'TJ List'!$S:$S,">="&$A12,'TJ List'!$S:$S,"<="&$B12,'TJ List'!$T:$T,">="&D$2,'TJ List'!$T:$T,"<="&D$3),"N/A") -> 16.962963 | E12: =IF(COUNTIFS('TJ List'!$L:$L,">0",'TJ List'!$S:$S,">="&$A12,'TJ List'!$S:$S,"<="&$B12,'TJ List'!$T:$T,">="&E$2,'TJ List'!$T:$T,"<="&E$3)>0,SUMIFS('TJ List'!$L:$L,'TJ List'!$S:$S,">="&$A12,'TJ List'!$S:$S,"<="&$B12,'TJ List'!$T:$T,">="&E$2,'TJ List'!$T:$T,"<="&E$3)/COUNTIFS('TJ List'!$L:$L,">0",'TJ List'!$S:$S,">="&$A12,'TJ List'!$S:$S,"<="&$B12,'TJ List'!$T:$T,">="&E$2,'TJ List'!$T:$T,"<="&E$3),"N/A") -> 17.71875 | F12: =IF(COUNTIFS('TJ List'!$L:$L,">0",'TJ List'!$S:$S,">="&$A12,'TJ List'!$S:$S,"<="&$B12,'TJ List'!$T:$T,">="&F$2,'TJ List'!$T:$T,"<="&F$3)>0,SUMIFS('TJ List'!$L:$L,'TJ List'!$S:$S,">="&$A12,'TJ List'!$S:$S,"<="&$B12,'TJ List'!$T:$T,">="&F$2,'TJ List'!$T:$T,"<="&F$3)/COUNTIFS('TJ List'!$L:$L,">0",'TJ List'!$S:$S,">="&$A12,'TJ List'!$S:$S,"<="&$B12,'TJ List'!$T:$T,">="&F$2,'TJ List'!$T:$T,"<="&F$3),"N/A") -> 18.222222 | G12: {=AVERAGE(INDIRECT(CONCATENATE(ADDRESS(ROW(INDEX('TJ List'!A:A,MATCH(40908,'TJ List'!B:B,-1)+1,0)),12,1,TRUE,"TJ List"),":",ADDRESS(ROW(INDEX('TJ List'!A:A,MATCH(40178,'TJ List'!B:B,-1),0)),12))))} -> 17.179487 | H12: {=MEDIAN(INDIRECT(CONCATENATE(ADDRESS(ROW(INDEX('TJ List'!A:A,MATCH(40908,'TJ List'!B:B,-1)+1,0)),12,1,TRUE,"TJ List"),":",ADDRESS(ROW(INDEX('TJ List'!A:A,MATCH(40178,'TJ List'!B:B,-1),0)),12))))} -> 15 | I12: {=MODE(INDIRECT(CONCATENATE(ADDRESS(ROW(INDEX('TJ List'!A:A,MATCH(40908,'TJ List'!B:B,-1)+1,0)),12,1,TRUE,"TJ List"),":",ADDRESS(ROW(INDEX('TJ List'!A:A,MATCH(40178,'TJ List'!B:B,-1),0)),12))))} -> 12 | J12: {=COUNTIFS(INDIRECT(CONCATENATE(ADDRESS(ROW(INDEX('TJ List'!A:A,MATCH(40908,'TJ List'!B:B,-1)+1,0)),11,1,TRUE,"TJ List"),":",ADDRESS(ROW(INDEX('TJ List'!A:A,MATCH(40178,'TJ List'!B:B,-1),0)),11))),">0")/COUNTIFS(INDIRECT(CONCATENATE(ADDRESS(ROW(INDEX('TJ List'!A:A,MATCH(40908,'TJ List'!B:B,-1)+1,0)),1,1,TRUE,"TJ List"),":",ADDRESS(ROW(INDEX('TJ List'!A:A,MATCH(40178,'TJ List'!B:B,-1),0)),1))),"<>0")} -> 0.89375 | K12: {=COUNTIFS(INDIRECT(CONCATENATE(ADDRESS(ROW(INDEX('TJ List'!A:A,MATCH(40908,'TJ List'!B:B,-1)+1,0)),11,1,TRUE,"TJ List"),":",ADDRESS(ROW(INDEX('TJ List'!A:A,MATCH(40178,'TJ List'!B:B,-1),0)),11))),"<>X")} -> 160 | L12: {=AVERAGEIFS(INDIRECT(CONCATENATE(ADDRESS(ROW(INDEX('TJ List'!A:A,MATCH(40908,'TJ List'!B:B,-1)+1,0)),12,1,TRUE,"TJ List"),":",ADDRESS(ROW(INDEX('TJ List'!A:A,MATCH(40178,'TJ List'!B:B,-1),0)),12))),INDIRECT(CONCATENATE(ADDRESS(ROW(INDEX('TJ List'!A:A,MATCH(40908,'TJ List'!B:B,-1)+1,0)),4,1,TRUE,"TJ List"),":",ADDRESS(ROW(INDEX('TJ List'!A:A,MATCH(40178,'TJ List'!B:B,-1),0)),4))),"MLB",INDIRECT(CONCATENATE(ADDRESS(ROW(INDEX('TJ List'!A:A,MATCH(40908,'TJ List'!B:B,-1)+1,0)),12,1,TRUE,"TJ List"),":",ADDRESS(ROW(INDEX('TJ List'!A:A,MATCH(40178,'TJ List'!B:B,-1),0)),12))),">0")} -> 16.071429 | M12: {=COUNTIFS(INDIRECT(CONCATENATE(ADDRESS(ROW(INDEX('TJ List'!A:A,MATCH(40908,'TJ List'!B:B,-1)+1,0)),11,1,TRUE,"TJ List"),":",ADDRESS(ROW(INDEX('TJ List'!A:A,MATCH(40178,'TJ List'!B:B,-1),0)),11))),">0",INDIRECT(CONCATENATE(ADDRESS(ROW(INDEX('TJ List'!A:A,MATCH(40908,'TJ List'!B:B,-1)+1,0)),4,1,TRUE,"TJ List"),":",ADDRESS(ROW(INDEX('TJ List'!A:A,MATCH(40178,'TJ List'!B:B,-1),0)),4))),"MLB")/COUNTIFS(INDIRECT(CONCATENATE(ADDRESS(ROW(INDEX('TJ List'!A:A,MATCH(40908,'TJ List'!B:B,-1)+1,0)),1,1,TRUE,"TJ List"),":",ADDRESS(ROW(INDEX('TJ List'!A:A,MATCH(40178,'TJ List'!B:B,-1),0)),1))),"<>0",INDIRECT(CONCATENATE(ADDRESS(ROW(INDEX('TJ List'!A:A,MATCH(40908,'TJ List'!B:B,-1)+1,0)),4,1,TRUE,"TJ List"),":",ADDRESS(ROW(INDEX('TJ List'!A:A,MATCH(40178,'TJ List'!B:B,-1),0)),4))),"MLB")} -> 0.82352941 | N12: {=COUNTIFS(INDIRECT(CONCATENATE(ADDRESS(ROW(INDEX('TJ List'!A:A,MATCH(40908,'TJ List'!B:B,-1)+1,0)),11,1,TRUE,"TJ List"),":",ADDRESS(ROW(INDEX('TJ List'!A:A,MATCH(40178,'TJ List'!B:B,-1),0)),11))),"<>X",INDIRECT(CONCATENATE(ADDRESS(ROW(INDEX('TJ List'!A:A,MATCH(40908,'TJ List'!B:B,-1)+1,0)),4,1,TRUE,"TJ List"),":",ADDRESS(ROW(INDEX('TJ List'!A:A,MATCH(40178,'TJ List'!B:B,-1),0)),4))),"MLB")} -> 34
A13: 2008 | B13: 2009 | C13: =IF(COUNTIFS('TJ List'!$L:$L,">0",'TJ List'!$S:$S,">="&$A13,'TJ List'!$S:$S,"<="&$B13,'TJ List'!$T:$T,">="&C$2,'TJ List'!$T:$T,"<="&C$3)>0,SUMIFS('TJ List'!$L:$L,'TJ List'!$S:$S,">="&$A13,'TJ List'!$S:$S,"<="&$B13,'TJ List'!$T:$T,">="&C$2,'TJ List'!$T:$T,"<="&C$3)/COUNTIFS('TJ List'!$L:$L,">0",'TJ List'!$S:$S,">="&$A13,'TJ List'!$S:$S,"<="&$B13,'TJ List'!$T:$T,">="&C$2,'TJ List'!$T:$T,"<="&C$3),"N/A") -> 27.5 | D13: =IF(COUNTIFS('TJ List'!$L:$L,">0",'TJ List'!$S:$S,">="&$A13,'TJ List'!$S:$S,"<="&$B13,'TJ List'!$T:$T,">="&D$2,'TJ List'!$T:$T,"<="&D$3)>0,SUMIFS('TJ List'!$L:$L,'TJ List'!$S:$S,">="&$A13,'TJ List'!$S:$S,"<="&$B13,'TJ List'!$T:$T,">="&D$2,'TJ List'!$T:$T,"<="&D$3)/COUNTIFS('TJ List'!$L:$L,">0",'TJ List'!$S:$S,">="&$A13,'TJ List'!$S:$S,"<="&$B13,'TJ List'!$T:$T,">="&D$2,'TJ List'!$T:$T,"<="&D$3),"N/A") -> 16.9375 | E13: =IF(COUNTIFS('TJ List'!$L:$L,">0",'TJ List'!$S:$S,">="&$A13,'TJ List'!$S:$S,"<="&$B13,'TJ List'!$T:$T,">="&E$2,'TJ List'!$T:$T,"<="&E$3)>0,SUMIFS('TJ List'!$L:$L,'TJ List'!$S:$S,">="&$A13,'TJ List'!$S:$S,"<="&$B13,'TJ List'!$T:$T,">="&E$2,'TJ List'!$T:$T,"<="&E$3)/COUNTIFS('TJ List'!$L:$L,">0",'TJ List'!$S:$S,">="&$A13,'TJ List'!$S:$S,"<="&$B13,'TJ List'!$T:$T,">="&E$2,'TJ List'!$T:$T,"<="&E$3),"N/A") -> 16.869565 | F13: =IF(COUNTIFS('TJ List'!$L:$L,">0",'TJ List'!$S:$S,">="&$A13,'TJ List'!$S:$S,"<="&$B13,'TJ List'!$T:$T,">="&F$2,'TJ List'!$T:$T,"<="&F$3)>0,SUMIFS('TJ List'!$L:$L,'TJ List'!$S:$S,">="&$A13,'TJ List'!$S:$S,"<="&$B13,'TJ List'!$T:$T,">="&F$2,'TJ List'!$T:$T,"<="&F$3)/COUNTIFS('TJ List'!$L:$L,">0",'TJ List'!$S:$S,">="&$A13,'TJ List'!$S:$S,"<="&$B13,'TJ List'!$T:$T,">="&F$2,'TJ List'!$T:$T,"<="&F$3),"N/A") -> 21.333333 | G13: {=AVERAGE(INDIRECT(CONCATENATE(ADDRESS(ROW(INDEX('TJ List'!A:A,MATCH(40178,'TJ List'!B:B,-1)+1,0)),12,1,TRUE,"TJ List"),":",ADDRESS(ROW(INDEX('TJ List'!A:A,MATCH(39447,'TJ List'!B:B,-1),0)),12))))} -> 17.806452 | H13: {=MEDIAN(INDIRECT(CONCATENATE(ADDRESS(ROW(INDEX('TJ List'!A:A,MATCH(40178,'TJ List'!B:B,-1)+1,0)),12,1,TRUE,"TJ List"),":",ADDRESS(ROW(INDEX('TJ List'!A:A,MATCH(39447,'TJ List'!B:B,-1),0)),12))))} -> 14 | I13: {=MODE(INDIRECT(CONCATENATE(ADDRESS(ROW(INDEX('TJ List'!A:A,MATCH(40178,'TJ List'!B:B,-1)+1,0)),12,1,TRUE,"TJ List"),":",ADDRESS(ROW(INDEX('TJ List'!A:A,MATCH(39447,'TJ List'!B:B,-1),0)),12))))} -> 11 | J13: {=COUNTIFS(INDIRECT(CONCATENATE(ADDRESS(ROW(INDEX('TJ List'!A:A,MATCH(40178,'TJ List'!B:B,-1)+1,0)),11,1,TRUE,"TJ List"),":",ADDRESS(ROW(INDEX('TJ List'!A:A,MATCH(39447,'TJ List'!B:B,-1),0)),11))),">0")/COUNTIFS(INDIRECT(CONCATENATE(ADDRESS(ROW(INDEX('TJ List'!A:A,MATCH(40178,'TJ List'!B:B,-1)+1,0)),1,1,TRUE,"TJ List"),":",ADDRESS(ROW(INDEX('TJ List'!A:A,MATCH(39447,'TJ List'!B:B,-1),0)),1))),"<>0")} -> 0.875 | K13: {=COUNTIFS(INDIRECT(CONCATENATE(ADDRESS(ROW(INDEX('TJ List'!A:A,MATCH(40178,'TJ List'!B:B,-1)+1,0)),11,1,TRUE,"TJ List"),":",ADDRESS(ROW(INDEX('TJ List'!A:A,MATCH(39447,'TJ List'!B:B,-1),0)),11))),"<>X")} -> 128 | L13: {=AVERAGEIFS(INDIRECT(CONCATENATE(ADDRESS(ROW(INDEX('TJ List'!A:A,MATCH(40178,'TJ List'!B:B,-1)+1,0)),12,1,TRUE,"TJ List"),":",ADDRESS(ROW(INDEX('TJ List'!A:A,MATCH(39447,'TJ List'!B:B,-1),0)),12))),INDIRECT(CONCATENATE(ADDRESS(ROW(INDEX('TJ List'!A:A,MATCH(40178,'TJ List'!B:B,-1)+1,0)),4,1,TRUE,"TJ List"),":",ADDRESS(ROW(INDEX('TJ List'!A:A,MATCH(39447,'TJ List'!B:B,-1),0)),4))),"MLB",INDIRECT(CONCATENATE(ADDRESS(ROW(INDEX('TJ List'!A:A,MATCH(40178,'TJ List'!B:B,-1)+1,0)),12,1,TRUE,"TJ List"),":",ADDRESS(ROW(INDEX('TJ List'!A:A,MATCH(39447,'TJ List'!B:B,-1),0)),12))),">0")} -> 18.928571 | M13: {=COUNTIFS(INDIRECT(CONCATENATE(ADDRESS(ROW(INDEX('TJ List'!A:A,MATCH(40178,'TJ List'!B:B,-1)+1,0)),11,1,TRUE,"TJ List"),":",ADDRESS(ROW(INDEX('TJ List'!A:A,MATCH(39447,'TJ List'!B:B,-1),0)),11))),">0",INDIRECT(CONCATENATE(ADDRESS(ROW(INDEX('TJ List'!A:A,MATCH(40178,'TJ List'!B:B,-1)+1,0)),4,1,TRUE,"TJ List"),":",ADDRESS(ROW(INDEX('TJ List'!A:A,MATCH(39447,'TJ List'!B:B,-1),0)),4))),"MLB")/COUNTIFS(INDIRECT(CONCATENATE(ADDRESS(ROW(INDEX('TJ List'!A:A,MATCH(40178,'TJ List'!B:B,-1)+1,0)),1,1,TRUE,"TJ List"),":",ADDRESS(ROW(INDEX('TJ List'!A:A,MATCH(39447,'TJ List'!B:B,-1),0)),1))),"<>0",INDIRECT(CONCATENATE(ADDRESS(ROW(INDEX('TJ List'!A:A,MATCH(40178,'TJ List'!B:B,-1)+1,0)),4,1,TRUE,"TJ List"),":",ADDRESS(ROW(INDEX('TJ List'!A:A,MATCH(39447,'TJ List'!B:B,-1),0)),4))),"MLB")} -> 0.77777778 | N13: {=COUNTIFS(INDIRECT(CONCATENATE(ADDRESS(ROW(INDEX('TJ List'!A:A,MATCH(40178,'TJ List'!B:B,-1)+1,0)),11,1,TRUE,"TJ List"),":",ADDRESS(ROW(INDEX('TJ List'!A:A,MATCH(39447,'TJ List'!B:B,-1),0)),11))),"<>X",INDIRECT(CONCATENATE(ADDRESS(ROW(INDEX('TJ List'!A:A,MATCH(40178,'TJ List'!B:B,-1)+1,0)),4,1,TRUE,"TJ List"),":",ADDRESS(ROW(INDEX('TJ List'!A:A,MATCH(39447,'TJ List'!B:B,-1),0)),4))),"MLB")} -> 36
